{
  "team": "Codnor Sports Chargers U13",
  "league": "YEL East Midlands Sunday 25/26",
  "generated": "2026-03-21T14:04:04Z",
  "fixtures": [
    {
      "id": "71a8fe96c24bd1b8e3aa62ad79e823bf",
      "date": "2026-03-22",
      "time": "12:30",
      "home_team": "Arnold Town White U13",
      "away_team": "Codnor Sports Chargers U13",
      "venue": "Eagle Valley NG5 8PS",
      "division": "U13 Sun Spring Div 2 Blue",
      "home_away": "away",
      "opponent": "Arnold Town White U13"
    },
    {
      "id": "5f671116e55e07e36f37587c58e6b717",
      "date": "2026-04-19",
      "time": "10:00",
      "home_team": "Mickleover FC Juniors Phoenix U13",
      "away_team": "Codnor Sports Chargers U13",
      "venue": "Varsity Grange Football Complex DE3 9EB",
      "division": "U13 Sun Spring Div 2 Blue",
      "home_away": "away",
      "opponent": "Mickleover FC Juniors Phoenix U13"
    },
    {
      "id": "9eaa4382769e340b132bf5c2b70288a1",
      "date": "2026-04-26",
      "time": "10:00",
      "home_team": "Codnor Sports Chargers U13",
      "away_team": "Breaston Park Black U13",
      "venue": "Codnor Rec Ground DE5 9QY",
      "division": "U13 Sun Spring Div 2 Blue",
      "home_away": "home",
      "opponent": "Breaston Park Black U13"
    }
  ],
  "results": []
}