{
  "team": "Eastwood CFC Aces U10",
  "league": "YEL East Midlands Sunday 25/26",
  "generated": "2026-04-19T13:56:15Z",
  "fixtures": [
    {
      "id": "17b7f1511baf70fcdc4aa4c58817bc1a",
      "date": "2026-04-26",
      "time": "10:00",
      "home_team": "Eastwood CFC Aces U10",
      "away_team": "Mansfield Town Grassroots U10",
      "venue": "Coronation Park NG16 3HB",
      "division": "U10 Sunday",
      "home_away": "home",
      "opponent": "Mansfield Town Grassroots U10"
    }
  ],
  "results": [
    {
      "id": "6f2bf0e2890354845de5d019bf2c559f",
      "date": "2026-04-19",
      "time": "10:00",
      "home_team": "Eastwood CFC Aces U10",
      "away_team": "DLFC Gold U10",
      "home_score": 3,
      "away_score": 2,
      "venue": "",
      "division": "U10 Sun Spring Div 1 Gold",
      "home_away": "home",
      "opponent": "DLFC Gold U10",
      "goals_for": 3,
      "goals_against": 2
    },
    {
      "id": "657450090561124d7c94561b52d3c3ea",
      "date": "2026-03-22",
      "time": "10:00",
      "home_team": "Mansfield Town Grassroots U10",
      "away_team": "Eastwood CFC Aces U10",
      "home_score": 1,
      "away_score": 2,
      "venue": "",
      "division": "U10 Sun Spring Div 1 Gold",
      "home_away": "away",
      "opponent": "Mansfield Town Grassroots U10",
      "goals_for": 2,
      "goals_against": 1
    },
    {
      "id": "80daaf3b86199afcd9ac7eb6c2c463d7",
      "date": "2026-03-15",
      "time": "10:00",
      "home_team": "Hemington Hammers All Stars U10",
      "away_team": "Eastwood CFC Aces U10",
      "home_score": 2,
      "away_score": 6,
      "venue": "",
      "division": "U10 Sun Spring Div 1 Gold",
      "home_away": "away",
      "opponent": "Hemington Hammers All Stars U10",
      "goals_for": 6,
      "goals_against": 2
    },
    {
      "id": "13458c5a7aa174094d47b82634cc4f08",
      "date": "2026-03-08",
      "time": "10:00",
      "home_team": "Eastwood CFC Aces U10",
      "away_team": "Mansfield Town Grassroots U10",
      "home_score": 0,
      "away_score": 3,
      "venue": "",
      "division": "U10 Sun YEL Cup",
      "home_away": "home",
      "opponent": "Mansfield Town Grassroots U10",
      "goals_for": 0,
      "goals_against": 3
    },
    {
      "id": "8f1da1cea48197472f91800393462af8",
      "date": "2026-03-01",
      "time": "10:00",
      "home_team": "Eastwood CFC Madrid U10",
      "away_team": "Eastwood CFC Aces U10",
      "home_score": 0,
      "away_score": 2,
      "venue": "",
      "division": "U10 Sun Spring Div 1 Gold",
      "home_away": "away",
      "opponent": "Eastwood CFC Madrid U10",
      "goals_for": 2,
      "goals_against": 0
    },
    {
      "id": "cfea03be052a89a098d2f0d4c7a9c6f9",
      "date": "2026-02-22",
      "time": "10:00",
      "home_team": "Hemington Hammers All Stars U10",
      "away_team": "Eastwood CFC Aces U10",
      "home_score": null,
      "away_score": null,
      "venue": "",
      "division": "U10 Sun 2026 Friendly 2 Blue",
      "home_away": "away",
      "opponent": "Hemington Hammers All Stars U10",
      "goals_for": null,
      "goals_against": null
    },
    {
      "id": "944f51af2f69e2d6b0123b3bae8df861",
      "date": "2026-02-15",
      "time": "09:00",
      "home_team": "Eastwood CFC Aces U10",
      "away_team": "Stapleford Town Jaguars U10",
      "home_score": null,
      "away_score": null,
      "venue": "",
      "division": "U10 Sun 2026 Friendly 2 Blue",
      "home_away": "home",
      "opponent": "Stapleford Town Jaguars U10",
      "goals_for": null,
      "goals_against": null
    },
    {
      "id": "f892039a195d707863613b32b8934462",
      "date": "2026-02-08",
      "time": "10:00",
      "home_team": "Eastwood CFC Aces U10",
      "away_team": "Tibshelf FC U10",
      "home_score": null,
      "away_score": null,
      "venue": "",
      "division": "U10 Sunday",
      "home_away": "home",
      "opponent": "Tibshelf FC U10",
      "goals_for": null,
      "goals_against": null
    },
    {
      "id": "447a6356d592f43a37a364456f0296be",
      "date": "2026-01-25",
      "time": "10:00",
      "home_team": "Eastwood CFC Aces U10",
      "away_team": "Attenborough Colts Black U10",
      "home_score": null,
      "away_score": null,
      "venue": "",
      "division": "U10 Sun 2026 Friendly 2 Blue",
      "home_away": "home",
      "opponent": "Attenborough Colts Black U10",
      "goals_for": null,
      "goals_against": null
    },
    {
      "id": "310b43df5855d971968f747a0f2af0f4",
      "date": "2026-01-18",
      "time": "11:00",
      "home_team": "WBYFC Bayern U10",
      "away_team": "Eastwood CFC Aces U10",
      "home_score": 2,
      "away_score": 5,
      "venue": "",
      "division": "U10 Sun YEL Cup",
      "home_away": "away",
      "opponent": "WBYFC Bayern U10",
      "goals_for": 5,
      "goals_against": 2
    },
    {
      "id": "9127c3651d5017c22a30aa3f9959c9bf",
      "date": "2025-12-14",
      "time": "10:00",
      "home_team": "PMG Excel U10",
      "away_team": "Eastwood CFC Aces U10",
      "home_score": null,
      "away_score": null,
      "venue": "",
      "division": "U10 Sunday",
      "home_away": "away",
      "opponent": "PMG Excel U10",
      "goals_for": null,
      "goals_against": null
    },
    {
      "id": "07e292f6f89818e317da483d20021b96",
      "date": "2025-12-07",
      "time": "10:00",
      "home_team": "Eastwood CFC Aces U10",
      "away_team": "Hemington Hammers All Stars U10",
      "home_score": 10,
      "away_score": 3,
      "venue": "",
      "division": "U10 Sun YEL Cup",
      "home_away": "home",
      "opponent": "Hemington Hammers All Stars U10",
      "goals_for": 10,
      "goals_against": 3
    },
    {
      "id": "5b0a17bb07c7e90790942587b00b9dc8",
      "date": "2025-11-30",
      "time": "10:00",
      "home_team": "Eastwood CFC Madrid U10",
      "away_team": "Eastwood CFC Aces U10",
      "home_score": null,
      "away_score": null,
      "venue": "",
      "division": "U10 Sunday",
      "home_away": "away",
      "opponent": "Eastwood CFC Madrid U10",
      "goals_for": null,
      "goals_against": null
    },
    {
      "id": "e59de6b41ad00ef6c7cd16bd563beeba",
      "date": "2025-11-23",
      "time": "10:00",
      "home_team": "Eastwood CFC Aces U10",
      "away_team": "Attenborough Colts Blue U10",
      "home_score": 0,
      "away_score": 5,
      "venue": "",
      "division": "U10 Sun Winter Div Prem",
      "home_away": "home",
      "opponent": "Attenborough Colts Blue U10",
      "goals_for": 0,
      "goals_against": 5
    },
    {
      "id": "fd5e7921358f34da7ed805e18abf05ef",
      "date": "2025-11-16",
      "time": "11:30",
      "home_team": "Priory Celtic 1967 U10",
      "away_team": "Eastwood CFC Aces U10",
      "home_score": 0,
      "away_score": 0,
      "venue": "",
      "division": "U10 Sun Winter Div Prem",
      "home_away": "away",
      "opponent": "Priory Celtic 1967 U10",
      "goals_for": 0,
      "goals_against": 0
    },
    {
      "id": "93830baea26caa02249805873982cf31",
      "date": "2025-11-09",
      "time": "10:00",
      "home_team": "Eastwood CFC Aces U10",
      "away_team": "Mansfield Town Grassroots U10",
      "home_score": 1,
      "away_score": 3,
      "venue": "",
      "division": "U10 Sun Winter Div Prem",
      "home_away": "home",
      "opponent": "Mansfield Town Grassroots U10",
      "goals_for": 1,
      "goals_against": 3
    },
    {
      "id": "7775635b9289a68adf81561ab3f0da82",
      "date": "2025-11-02",
      "time": "10:00",
      "home_team": "Silva FC Rushcliffe Red U10",
      "away_team": "Eastwood CFC Aces U10",
      "home_score": null,
      "away_score": null,
      "venue": "",
      "division": "U10 Sunday",
      "home_away": "away",
      "opponent": "Silva FC Rushcliffe Red U10",
      "goals_for": null,
      "goals_against": null
    },
    {
      "id": "3a29f0d7ffda26cfc8aebe73b8c95f0f",
      "date": "2025-10-19",
      "time": "10:00",
      "home_team": "Attenborough Colts Blue U10",
      "away_team": "Eastwood CFC Aces U10",
      "home_score": null,
      "away_score": null,
      "venue": "",
      "division": "U10 Sunday",
      "home_away": "away",
      "opponent": "Attenborough Colts Blue U10",
      "goals_for": null,
      "goals_against": null
    },
    {
      "id": "876a03c3b347a667c2fc59703483e822",
      "date": "2025-10-12",
      "time": "09:45",
      "home_team": "Silva FC Rushcliffe Red U10",
      "away_team": "Eastwood CFC Aces U10",
      "home_score": 4,
      "away_score": 4,
      "venue": "",
      "division": "U10 Sun Winter Div Prem",
      "home_away": "away",
      "opponent": "Silva FC Rushcliffe Red U10",
      "goals_for": 4,
      "goals_against": 4
    },
    {
      "id": "f3549b644fe2c0343f3043533af02321",
      "date": "2025-10-05",
      "time": "10:00",
      "home_team": "Eastwood CFC Aces U10",
      "away_team": "WBYFC Bayern U10",
      "home_score": 3,
      "away_score": 9,
      "venue": "",
      "division": "U10 Sun Winter Div Prem",
      "home_away": "home",
      "opponent": "WBYFC Bayern U10",
      "goals_for": 3,
      "goals_against": 9
    },
    {
      "id": "841d619de12d2b16ca68ad1aef0a1ad0",
      "date": "2025-09-28",
      "time": "10:00",
      "home_team": "Eastwood CFC Aces U10",
      "away_team": "Mansfield Town Grassroots U10",
      "home_score": null,
      "away_score": null,
      "venue": "",
      "division": "U10 Sun Autumn Group 1",
      "home_away": "home",
      "opponent": "Mansfield Town Grassroots U10",
      "goals_for": null,
      "goals_against": null
    },
    {
      "id": "724a1a85f2096c6be62d15ae7ad6ed57",
      "date": "2025-09-14",
      "time": "11:00",
      "home_team": "WBYFC Bayern U10",
      "away_team": "Eastwood CFC Aces U10",
      "home_score": null,
      "away_score": null,
      "venue": "",
      "division": "U10 Sun Autumn Group 1",
      "home_away": "away",
      "opponent": "WBYFC Bayern U10",
      "goals_for": null,
      "goals_against": null
    },
    {
      "id": "2ff6fae115ad8ba9407c771ad4ab4639",
      "date": "2025-09-07",
      "time": "10:00",
      "home_team": "Eastwood CFC Aces U10",
      "away_team": "Priory Celtic 1967 U10",
      "home_score": null,
      "away_score": null,
      "venue": "",
      "division": "U10 Sun Autumn Group 1",
      "home_away": "home",
      "opponent": "Priory Celtic 1967 U10",
      "goals_for": null,
      "goals_against": null
    }
  ]
}