{
  "team": "Long Eaton United Red U11",
  "league": "YEL East Midlands Sunday 25/26",
  "generated": "2026-03-21T14:15:47Z",
  "fixtures": [
    {
      "id": "2325d54b6aa92deeaeabf1b4a2806309",
      "date": "2026-03-22",
      "time": "11:00",
      "home_team": "Long Eaton United Red U11",
      "away_team": "Gedling Southbank Titans U11",
      "venue": "Grange Park NG10 2EG",
      "division": "U11 Sun YEL Shield",
      "home_away": "home",
      "opponent": "Gedling Southbank Titans U11"
    },
    {
      "id": "3e280227d97d3fa0fb1b0b23dc75e3d3",
      "date": "2026-04-19",
      "time": "11:00",
      "home_team": "Stapleford Town Saxons U11",
      "away_team": "Long Eaton United Red U11",
      "venue": "Hickings Lane NG9 8PG",
      "division": "U11 Sun Spring Div 4 Blue",
      "home_away": "away",
      "opponent": "Stapleford Town Saxons U11"
    },
    {
      "id": "99b1adb89e86f8c451dd8c700a36e20e",
      "date": "2026-04-26",
      "time": "10:00",
      "home_team": "Long Eaton United Red U11",
      "away_team": "Moorgreen Colts Blue U11",
      "venue": "Grange Park NG10 2EG",
      "division": "U11 Sun Spring Div 4 Blue",
      "home_away": "home",
      "opponent": "Moorgreen Colts Blue U11"
    }
  ],
  "results": []
}