{
  "team": "Melbourne Dynamo U10 Tigers",
  "league": "YEL East Midlands Sunday 25/26",
  "generated": "2026-03-21T14:33:52Z",
  "fixtures": [
    {
      "id": "e9c25d8dc4972b1ee748d81a9886503b",
      "date": "2026-03-22",
      "time": "10:00",
      "home_team": "West Hallam Roses U10",
      "away_team": "Melbourne Dynamo U10 Tigers",
      "venue": "Stanley Village Rec Ground DE7 6FF",
      "division": "U10 Sun Spring Div 4 Blue",
      "home_away": "away",
      "opponent": "West Hallam Roses U10"
    },
    {
      "id": "25b3914e6edd9aeda9cf75909e68cf77",
      "date": "2026-03-29",
      "time": "11:00",
      "home_team": "Melbourne Dynamo U10 Tigers",
      "away_team": "Cotgrave FC Blue U10",
      "venue": "Melbourne Sports Park DE73 8DG",
      "division": "U10 Sun Spring Div 4 Blue",
      "home_away": "home",
      "opponent": "Cotgrave FC Blue U10"
    }
  ],
  "results": []
}