{
  "team": "Teversal FC U14",
  "league": "YEL East Midlands Sunday 25/26",
  "generated": "2026-03-21T15:46:02Z",
  "fixtures": [
    {
      "id": "632c9c151cb0c1c5f12857fb9d9513d4",
      "date": "2026-03-22",
      "time": "11:30",
      "home_team": "Teversal FC U14",
      "away_team": "Attenborough Colts Yellow U14",
      "venue": "Chilwell Olympia NG9 5HR",
      "division": "U14 Sun Spring Div 1 Silver",
      "home_away": "home",
      "opponent": "Attenborough Colts Yellow U14"
    },
    {
      "id": "de81843c5d0cce5d5cc9bf5965a84e05",
      "date": "2026-04-19",
      "time": "12:30",
      "home_team": "Teversal FC U14",
      "away_team": "DLFC Gold U14",
      "venue": "Peartree Lane NG17 3JP",
      "division": "U14 Sun Spring Div 1 Silver",
      "home_away": "home",
      "opponent": "DLFC Gold U14"
    },
    {
      "id": "ca5f1627765dfa79305542ce8b40407d",
      "date": "2026-04-26",
      "time": "11:00",
      "home_team": "Notts Olympic FC U14",
      "away_team": "Teversal FC U14",
      "venue": "Birchover Park Community Centre NG8 4BW",
      "division": "U14 Sun Spring Div 1 Silver",
      "home_away": "away",
      "opponent": "Notts Olympic FC U14"
    }
  ],
  "results": []
}