{
  "club": "Sherwood Colliery FC",
  "generated": "2026-04-19T09:21:08Z",
  "fixtures": [
    {
      "id": "ea8e3fe0f97307f5ab0e8fd13eb5b878",
      "date": "2026-04-12",
      "time": "10:00",
      "home_team": "Southwell City FC U11 Girls",
      "away_team": "Sherwood Colliery F.C. Ladies U11",
      "venue": "SOUTHWELL MEMORIAL GROUND",
      "division": "U11 Development",
      "league": "Nottinghamshire Girls and Ladies Football League 25/26",
      "team": "Sherwood Colliery F.C. Ladies U11",
      "home_away": "away",
      "opponent": "Southwell City FC U11 Girls"
    },
    {
      "id": "919e098027722c595554150173f6ec30",
      "date": "2026-04-19",
      "time": "10:00",
      "home_team": "Tansley Juniors U12 Girls",
      "away_team": "Sherwood Colliery F.C. Ladies U12 Black",
      "venue": "THE FETE FIELD",
      "division": "U12 Div 5 P2",
      "league": "Nottinghamshire Girls and Ladies Football League 25/26",
      "team": "Sherwood Colliery F.C. Ladies U12 Black",
      "home_away": "away",
      "opponent": "Tansley Juniors U12 Girls"
    },
    {
      "id": "b51c8aaabb9c31a84c146e9f5b7e34c0",
      "date": "2026-04-19",
      "time": "10:30",
      "home_team": "Bottesford U15 Girls",
      "away_team": "Sherwood Colliery F.C. Ladies U15",
      "venue": "BOTTESFORD FC",
      "division": "U15 Div 2",
      "league": "Nottinghamshire Girls and Ladies Football League 25/26",
      "team": "Sherwood Colliery F.C. Ladies U15",
      "home_away": "away",
      "opponent": "Bottesford U15 Girls"
    },
    {
      "id": "75d689631ce49aa71936d14ce424727b",
      "date": "2026-04-19",
      "time": "12:30",
      "home_team": "Sherwood Colliery F.C. Ladies U12 Blue",
      "away_team": "Bingham Town F.C. U12 Girls Blue",
      "venue": "RH ACADEMY",
      "division": "U12 Cup 3",
      "league": "Nottinghamshire Girls and Ladies Football League 25/26",
      "team": "Sherwood Colliery F.C. Ladies U12 Blue",
      "home_away": "home",
      "opponent": "Bingham Town F.C. U12 Girls Blue"
    },
    {
      "id": "f775468f5637279486a792034ae731a5",
      "date": "2026-04-19",
      "time": "12:30",
      "home_team": "Sherwood Colliery F.C. Ladies U14",
      "away_team": "Arnold Eagles F.C. Girls U14 Hurricanes",
      "venue": "DEBDALE PARK SPORTS AND RECREATIONAL CLUB",
      "division": "U14 Div 3",
      "league": "Nottinghamshire Girls and Ladies Football League 25/26",
      "team": "Sherwood Colliery F.C. Ladies U14",
      "home_away": "home",
      "opponent": "Arnold Eagles F.C. Girls U14 Hurricanes"
    },
    {
      "id": "bbd8d7c2e59744da5279f654cd6b5645",
      "date": "2026-04-22",
      "time": "18:00",
      "home_team": "Sherwood Colliery F.C. Ladies U15",
      "away_team": "Keyworth United F.C. U15 Kobras",
      "venue": "DEBDALE PARK SPORTS AND RECREATIONAL CLUB",
      "division": "U15 Div 2",
      "league": "Nottinghamshire Girls and Ladies Football League 25/26",
      "team": "Sherwood Colliery F.C. Ladies U15",
      "home_away": "home",
      "opponent": "Keyworth United F.C. U15 Kobras"
    },
    {
      "id": "ca9138c5d5dcdcec6c73f787e49dd5d9",
      "date": "2026-04-26",
      "time": "10:00",
      "home_team": "Nottingham F.C. Youth U14 Girls",
      "away_team": "Sherwood Colliery F.C. Ladies U14",
      "venue": "MELBOURNE PARK",
      "division": "U14 Div 3",
      "league": "Nottinghamshire Girls and Ladies Football League 25/26",
      "team": "Sherwood Colliery F.C. Ladies U14",
      "home_away": "away",
      "opponent": "Nottingham F.C. Youth U14 Girls"
    },
    {
      "id": "53fe904066630492ea6c870488e52375",
      "date": "2026-04-26",
      "time": "10:00",
      "home_team": "Allenton United FC U15 Ladies Bees",
      "away_team": "Sherwood Colliery F.C. Ladies U15",
      "venue": "Allenton United FC U15 Ladies Bees",
      "division": "U15 Div 2",
      "league": "Nottinghamshire Girls and Ladies Football League 25/26",
      "team": "Sherwood Colliery F.C. Ladies U15",
      "home_away": "away",
      "opponent": "Allenton United FC U15 Ladies Bees"
    },
    {
      "id": "8d30873b6b364e22c65784d2ddbfec5e",
      "date": "2026-04-26",
      "time": "10:00",
      "home_team": "Sherwood Colliery F.C. Ladies U15",
      "away_team": "Allenton United FC U15 Ladies Bees",
      "venue": "Allenton United FC U15 Ladies Bees",
      "division": "U15 Div 2",
      "league": "Nottinghamshire Girls and Ladies Football League 25/26",
      "team": "Sherwood Colliery F.C. Ladies U15",
      "home_away": "home",
      "opponent": "Allenton United FC U15 Ladies Bees"
    },
    {
      "id": "8b658404769e261faf2ad880d56b6e30",
      "date": "2026-04-26",
      "time": "10:15",
      "home_team": "Langwith Whitestar U12 United",
      "away_team": "Sherwood Colliery F.C. Ladies U12 Blue",
      "venue": "Langwith Whitestar U12 United",
      "division": "U12 Div 2 P2",
      "league": "Nottinghamshire Girls and Ladies Football League 25/26",
      "team": "Sherwood Colliery F.C. Ladies U12 Blue",
      "home_away": "away",
      "opponent": "Langwith Whitestar U12 United"
    },
    {
      "id": "00cb79d10d1085763ef5e87ae447a4cd",
      "date": "2026-05-03",
      "time": "10:00",
      "home_team": "Sandiacre Town Youth U15 Girls Sparkle",
      "away_team": "Sherwood Colliery F.C. Ladies U15",
      "venue": "SANDIACRE FRIESLAND SPORTS CENTRE",
      "division": "U15 Div 2",
      "league": "Nottinghamshire Girls and Ladies Football League 25/26",
      "team": "Sherwood Colliery F.C. Ladies U15",
      "home_away": "away",
      "opponent": "Sandiacre Town Youth U15 Girls Sparkle"
    },
    {
      "id": "61d451721cc6126f743a9f075834e28e",
      "date": "2026-05-03",
      "time": "10:00",
      "home_team": "Sherwood Colliery F.C. Ladies U15",
      "away_team": "Sandiacre Town Youth U15 Girls Sparkle",
      "venue": "DEBDALE PARK SPORTS AND RECREATIONAL CLUB",
      "division": "U15 Div 2",
      "league": "Nottinghamshire Girls and Ladies Football League 25/26",
      "team": "Sherwood Colliery F.C. Ladies U15",
      "home_away": "home",
      "opponent": "Sandiacre Town Youth U15 Girls Sparkle"
    },
    {
      "id": "fd34a9555ec4fba79a003bee57810559",
      "date": "2026-05-03",
      "time": "13:30",
      "home_team": "Underwood Villa FC Youth Ladies",
      "away_team": "Sherwood Colliery FC Ladies",
      "venue": "BRACKEN PARK (UNDERWOOD VILLA FC)",
      "division": "Seniors Div 2",
      "league": "Nottinghamshire Girls and Ladies Football League 25/26",
      "team": "Sherwood Colliery FC Ladies",
      "home_away": "away",
      "opponent": "Underwood Villa FC Youth Ladies"
    },
    {
      "id": "8a54a40700e0f038bc682c4fa96cd837",
      "date": "2026-05-10",
      "time": "10:00",
      "home_team": "Matlock Town Juniors U14 Spartans Girls",
      "away_team": "Sherwood Colliery F.C. Ladies U14",
      "venue": "CAVENDISH FIELDS SPORTS ASSOCIATION",
      "division": "U14 Div 3",
      "league": "Nottinghamshire Girls and Ladies Football League 25/26",
      "team": "Sherwood Colliery F.C. Ladies U14",
      "home_away": "away",
      "opponent": "Matlock Town Juniors U14 Spartans Girls"
    },
    {
      "id": "29b55b8392837609238824e4d9be6cb6",
      "date": "2026-05-10",
      "time": "10:00",
      "home_team": "Willow Wanderers F.C. Youth U15 Amazons",
      "away_team": "Sherwood Colliery F.C. Ladies U15",
      "venue": "CARLTON-LE-WILLOWS ACADEMY",
      "division": "U15 Div 2",
      "league": "Nottinghamshire Girls and Ladies Football League 25/26",
      "team": "Sherwood Colliery F.C. Ladies U15",
      "home_away": "away",
      "opponent": "Willow Wanderers F.C. Youth U15 Amazons"
    },
    {
      "id": "35b99ab97434574f35644377d1a41f87",
      "date": "2026-05-10",
      "time": "10:00",
      "home_team": "Shirebrook Rangers Women",
      "away_team": "Sherwood Colliery FC Ladies",
      "venue": "SHIREBROOK ACADEMY",
      "division": "Seniors Div 2",
      "league": "Nottinghamshire Girls and Ladies Football League 25/26",
      "team": "Sherwood Colliery FC Ladies",
      "home_away": "away",
      "opponent": "Shirebrook Rangers Women"
    },
    {
      "id": "a493311c5b9d4973c1b2c7aedb24ba78",
      "date": "2026-05-10",
      "time": "11:15",
      "home_team": "Sherwood Colliery F.C. Ladies U12 Blue",
      "away_team": "Ollerton Town Community FC U12 Girls",
      "venue": "DEBDALE PARK SPORTS AND RECREATIONAL CLUB",
      "division": "U12 Div 2 P2",
      "league": "Nottinghamshire Girls and Ladies Football League 25/26",
      "team": "Sherwood Colliery F.C. Ladies U12 Blue",
      "home_away": "home",
      "opponent": "Ollerton Town Community FC U12 Girls"
    },
    {
      "id": "f3d627667807742c5463b1ad3cd6cfdd",
      "date": "2026-05-14",
      "time": "18:30",
      "home_team": "Arnold Town FC Women",
      "away_team": "Sherwood Colliery FC Ladies",
      "venue": "EAGLE VALLEY",
      "division": "Seniors Div 2",
      "league": "Nottinghamshire Girls and Ladies Football League 25/26",
      "team": "Sherwood Colliery FC Ladies",
      "home_away": "away",
      "opponent": "Arnold Town FC Women"
    },
    {
      "id": "50f398c8f3bcd56c507c1229dc31b53f",
      "date": "2026-05-17",
      "time": "10:00",
      "home_team": "Woodthorpe Community U12 Warriors",
      "away_team": "Sherwood Colliery F.C. Ladies U12 Blue",
      "venue": "POWERLEAGUE (NOTTINGHAM ARNOLD)",
      "division": "U12 Div 2 P2",
      "league": "Nottinghamshire Girls and Ladies Football League 25/26",
      "team": "Sherwood Colliery F.C. Ladies U12 Blue",
      "home_away": "away",
      "opponent": "Woodthorpe Community U12 Warriors"
    },
    {
      "id": "94da195892ce12d18cc97e116d77551c",
      "date": "2026-05-17",
      "time": "10:00",
      "home_team": "Riverside Junior U14 Rubies",
      "away_team": "Sherwood Colliery F.C. Ladies U14",
      "venue": "DEBDALE PARK SPORTS AND RECREATIONAL CLUB",
      "division": "U14 Div 3",
      "league": "Nottinghamshire Girls and Ladies Football League 25/26",
      "team": "Sherwood Colliery F.C. Ladies U14",
      "home_away": "away",
      "opponent": "Riverside Junior U14 Rubies"
    },
    {
      "id": "058a8efe6f0496b843cd32abb66cc12f",
      "date": "2026-05-24",
      "time": "10:00",
      "home_team": "Sherwood FC U12 Girls",
      "away_team": "Sherwood Colliery F.C. Ladies U12 Blue",
      "venue": "CARLTON FOOTBALL CENTRE",
      "division": "U12 Div 2 P2",
      "league": "Nottinghamshire Girls and Ladies Football League 25/26",
      "team": "Sherwood Colliery F.C. Ladies U12 Blue",
      "home_away": "away",
      "opponent": "Sherwood FC U12 Girls"
    },
    {
      "id": "43f51224a4787cb74301d372323b8888",
      "date": "2026-05-24",
      "time": "10:00",
      "home_team": "Sherwood Colliery F.C. Ladies U14",
      "away_team": "Riverside Junior U14 Rubies",
      "venue": "DEBDALE PARK SPORTS AND RECREATIONAL CLUB",
      "division": "U14 Div 3",
      "league": "Nottinghamshire Girls and Ladies Football League 25/26",
      "team": "Sherwood Colliery F.C. Ladies U14",
      "home_away": "home",
      "opponent": "Riverside Junior U14 Rubies"
    },
    {
      "id": "30074013a12bdcf1e142a7728c965a38",
      "date": "2026-05-24",
      "time": "10:00",
      "home_team": "Sherwood Colliery F.C. Ladies U14",
      "away_team": "Matlock Town Juniors U14 Spartans Girls",
      "venue": "DEBDALE PARK SPORTS AND RECREATIONAL CLUB",
      "division": "U14 Div 3",
      "league": "Nottinghamshire Girls and Ladies Football League 25/26",
      "team": "Sherwood Colliery F.C. Ladies U14",
      "home_away": "home",
      "opponent": "Matlock Town Juniors U14 Spartans Girls"
    },
    {
      "id": "093591f73180045a6147b5eddab2fd18",
      "date": "2026-05-24",
      "time": "10:00",
      "home_team": "Sherwood Colliery F.C. Ladies U15",
      "away_team": "Lowdham Colts F.C. Youth U15 Girls",
      "venue": "DEBDALE PARK SPORTS AND RECREATIONAL CLUB",
      "division": "U15 Div 2",
      "league": "Nottinghamshire Girls and Ladies Football League 25/26",
      "team": "Sherwood Colliery F.C. Ladies U15",
      "home_away": "home",
      "opponent": "Lowdham Colts F.C. Youth U15 Girls"
    }
  ],
  "results": [
    {
      "id": "c0aeb3942ef6536925246f24ce9a8f3a",
      "date": "2026-04-12",
      "time": "11:15",
      "home_team": "Sherwood Colliery F.C. Ladies U12 Blue",
      "away_team": "Keyworth United F.C. U12 Vipers",
      "home_score": 2,
      "away_score": 4,
      "venue": "",
      "division": "U12 Div 2 P2",
      "league": "Nottinghamshire Girls and Ladies Football League 25/26",
      "team": "Sherwood Colliery F.C. Ladies U12 Blue",
      "home_away": "home",
      "opponent": "Keyworth United F.C. U12 Vipers",
      "goals_for": 2,
      "goals_against": 4
    },
    {
      "id": "077fb164193e63372ec2f0b2cbd83600",
      "date": "2026-04-12",
      "time": "10:00",
      "home_team": "Quarrydale United FC U12",
      "away_team": "Sherwood Colliery F.C. Ladies U12 Black",
      "home_score": 1,
      "away_score": 1,
      "venue": "",
      "division": "U12 Div 5 P2",
      "league": "Nottinghamshire Girls and Ladies Football League 25/26",
      "team": "Sherwood Colliery F.C. Ladies U12 Black",
      "home_away": "away",
      "opponent": "Quarrydale United FC U12",
      "goals_for": 1,
      "goals_against": 1
    },
    {
      "id": "5d22b133fcf96662a163e94f4b91e0dd",
      "date": "2026-04-12",
      "time": "10:00",
      "home_team": "Hasland Community U14 Girls Sunday",
      "away_team": "Sherwood Colliery F.C. Ladies U14",
      "home_score": 2,
      "away_score": 4,
      "venue": "",
      "division": "U14 Div 3",
      "league": "Nottinghamshire Girls and Ladies Football League 25/26",
      "team": "Sherwood Colliery F.C. Ladies U14",
      "home_away": "away",
      "opponent": "Hasland Community U14 Girls Sunday",
      "goals_for": 4,
      "goals_against": 2
    },
    {
      "id": "dbe0589c7f3b43fc759eacdaebd2dc63",
      "date": "2026-03-29",
      "time": "14:30",
      "home_team": "Sherwood Colliery FC Ladies",
      "away_team": "Shirebrook Rangers Women",
      "home_score": 5,
      "away_score": 0,
      "venue": "",
      "division": "Seniors Div 2",
      "league": "Nottinghamshire Girls and Ladies Football League 25/26",
      "team": "Sherwood Colliery FC Ladies",
      "home_away": "home",
      "opponent": "Shirebrook Rangers Women",
      "goals_for": 5,
      "goals_against": 0
    },
    {
      "id": "90ea229042aa1eb18967418b0d92baf4",
      "date": "2026-03-29",
      "time": "11:15",
      "home_team": "Sherwood Colliery F.C. Ladies U11",
      "away_team": "Hasland Community U11 Girls",
      "home_score": null,
      "away_score": null,
      "venue": "",
      "division": "U11 Development",
      "league": "Nottinghamshire Girls and Ladies Football League 25/26",
      "team": "Sherwood Colliery F.C. Ladies U11",
      "home_away": "home",
      "opponent": "Hasland Community U11 Girls",
      "goals_for": null,
      "goals_against": null
    },
    {
      "id": "c5b7f4d28873520ddd41f39b94fb4b45",
      "date": "2026-03-29",
      "time": "10:00",
      "home_team": "Ravenshead Reds F.C. Youth U10",
      "away_team": "Sherwood Colliery F.C. Ladies U10",
      "home_score": null,
      "away_score": null,
      "venue": "",
      "division": "U10 Development",
      "league": "Nottinghamshire Girls and Ladies Football League 25/26",
      "team": "Sherwood Colliery F.C. Ladies U10",
      "home_away": "away",
      "opponent": "Ravenshead Reds F.C. Youth U10",
      "goals_for": null,
      "goals_against": null
    },
    {
      "id": "16914b3690568e342cf2b8b6abeb666e",
      "date": "2026-03-29",
      "time": "10:00",
      "home_team": "Gedling Southbank FC U14 Warriors",
      "away_team": "Sherwood Colliery F.C. Ladies U14",
      "home_score": 1,
      "away_score": 1,
      "venue": "",
      "division": "U14 Div 3",
      "league": "Nottinghamshire Girls and Ladies Football League 25/26",
      "team": "Sherwood Colliery F.C. Ladies U14",
      "home_away": "away",
      "opponent": "Gedling Southbank FC U14 Warriors",
      "goals_for": 1,
      "goals_against": 1
    },
    {
      "id": "22b86003b0fbc0ef6770f1ec9cff6146",
      "date": "2026-03-22",
      "time": "12:30",
      "home_team": "Sherwood Colliery F.C. Ladies U15",
      "away_team": "Bingham Town F.C. U15 Girls",
      "home_score": 3,
      "away_score": 1,
      "venue": "",
      "division": "U15 Div 2",
      "league": "Nottinghamshire Girls and Ladies Football League 25/26",
      "team": "Sherwood Colliery F.C. Ladies U15",
      "home_away": "home",
      "opponent": "Bingham Town F.C. U15 Girls",
      "goals_for": 3,
      "goals_against": 1
    },
    {
      "id": "09504b789b52bc92e94361af1bad9ae5",
      "date": "2026-03-22",
      "time": "11:15",
      "home_team": "Sherwood Colliery F.C. Ladies U12 Blue",
      "away_team": "Newark Town FC U12 Girls",
      "home_score": 2,
      "away_score": 0,
      "venue": "",
      "division": "U12 Cup 3",
      "league": "Nottinghamshire Girls and Ladies Football League 25/26",
      "team": "Sherwood Colliery F.C. Ladies U12 Blue",
      "home_away": "home",
      "opponent": "Newark Town FC U12 Girls",
      "goals_for": 2,
      "goals_against": 0
    },
    {
      "id": "7987307290f0ddb509416a1fa30437fe",
      "date": "2026-03-22",
      "time": "10:30",
      "home_team": "Sherwood FC Development Women",
      "away_team": "Sherwood Colliery FC Ladies",
      "home_score": 2,
      "away_score": 6,
      "venue": "",
      "division": "Seniors Div 2",
      "league": "Nottinghamshire Girls and Ladies Football League 25/26",
      "team": "Sherwood Colliery FC Ladies",
      "home_away": "away",
      "opponent": "Sherwood FC Development Women",
      "goals_for": 6,
      "goals_against": 2
    },
    {
      "id": "29755bf124c8022465a0e8f3dc9f1c30",
      "date": "2026-03-22",
      "time": "10:00",
      "home_team": "Matlock Town Juniors U11 Girls",
      "away_team": "Sherwood Colliery F.C. Ladies U11",
      "home_score": null,
      "away_score": null,
      "venue": "",
      "division": "U11 Development",
      "league": "Nottinghamshire Girls and Ladies Football League 25/26",
      "team": "Sherwood Colliery F.C. Ladies U11",
      "home_away": "away",
      "opponent": "Matlock Town Juniors U11 Girls",
      "goals_for": null,
      "goals_against": null
    },
    {
      "id": "7856d931ee83ca851389c174d01665ce",
      "date": "2026-03-22",
      "time": "10:00",
      "home_team": "Ravenshead Reds F.C. Youth U14",
      "away_team": "Sherwood Colliery F.C. Ladies U14",
      "home_score": 2,
      "away_score": 1,
      "venue": "",
      "division": "U14 Div 3 League Cup",
      "league": "Nottinghamshire Girls and Ladies Football League 25/26",
      "team": "Sherwood Colliery F.C. Ladies U14",
      "home_away": "away",
      "opponent": "Ravenshead Reds F.C. Youth U14",
      "goals_for": 1,
      "goals_against": 2
    },
    {
      "id": "31c2d8460fece8b328f55abe5a3dfb05",
      "date": "2026-03-22",
      "time": "09:45",
      "home_team": "Sherwood Colliery F.C. Ladies U10",
      "away_team": "Arnold Eagles F.C. Girls U10 Wizards",
      "home_score": null,
      "away_score": null,
      "venue": "",
      "division": "U10 Development",
      "league": "Nottinghamshire Girls and Ladies Football League 25/26",
      "team": "Sherwood Colliery F.C. Ladies U10",
      "home_away": "home",
      "opponent": "Arnold Eagles F.C. Girls U10 Wizards",
      "goals_for": null,
      "goals_against": null
    },
    {
      "id": "0413f69463f694501d9ba9cd3b0d20e1",
      "date": "2026-03-22",
      "time": "09:45",
      "home_team": "Sherwood Colliery F.C. Ladies U12 Black",
      "away_team": "Sutton Bonington U12 Comets",
      "home_score": 3,
      "away_score": 1,
      "venue": "",
      "division": "U12 Div 5 P2",
      "league": "Nottinghamshire Girls and Ladies Football League 25/26",
      "team": "Sherwood Colliery F.C. Ladies U12 Black",
      "home_away": "home",
      "opponent": "Sutton Bonington U12 Comets",
      "goals_for": 3,
      "goals_against": 1
    },
    {
      "id": "08b75ade99da9eab4de0dfe78c8eb96b",
      "date": "2026-03-15",
      "time": "14:00",
      "home_team": "Retford FC Ladies",
      "away_team": "Sherwood Colliery FC Ladies",
      "home_score": 0,
      "away_score": 6,
      "venue": "",
      "division": "Seniors Div 2",
      "league": "Nottinghamshire Girls and Ladies Football League 25/26",
      "team": "Sherwood Colliery FC Ladies",
      "home_away": "away",
      "opponent": "Retford FC Ladies",
      "goals_for": 6,
      "goals_against": 0
    },
    {
      "id": "5bf9d4ce7d656ee6938ff3b0cfa9c4e8",
      "date": "2026-03-15",
      "time": "12:30",
      "home_team": "Sherwood Colliery F.C. Ladies U12 Black",
      "away_team": "Ravenshead Reds F.C. Youth U12",
      "home_score": 9,
      "away_score": 0,
      "venue": "",
      "division": "U12 Div 5 P2",
      "league": "Nottinghamshire Girls and Ladies Football League 25/26",
      "team": "Sherwood Colliery F.C. Ladies U12 Black",
      "home_away": "home",
      "opponent": "Ravenshead Reds F.C. Youth U12",
      "goals_for": 9,
      "goals_against": 0
    },
    {
      "id": "da2380c1d9e06dafba00b99af3962946",
      "date": "2026-03-15",
      "time": "12:30",
      "home_team": "Sherwood Colliery F.C. Ladies U14",
      "away_team": "Gedling Southbank FC U14 Warriors",
      "home_score": 2,
      "away_score": 2,
      "venue": "",
      "division": "U14 Div 3",
      "league": "Nottinghamshire Girls and Ladies Football League 25/26",
      "team": "Sherwood Colliery F.C. Ladies U14",
      "home_away": "home",
      "opponent": "Gedling Southbank FC U14 Warriors",
      "goals_for": 2,
      "goals_against": 2
    },
    {
      "id": "61d82b1f2e80037caa77475237d4d243",
      "date": "2026-03-15",
      "time": "12:30",
      "home_team": "Sherwood Colliery F.C. Ladies U15",
      "away_team": "Priory Celtic F.C. U15 Girls",
      "home_score": 9,
      "away_score": 1,
      "venue": "",
      "division": "U15 Div 2",
      "league": "Nottinghamshire Girls and Ladies Football League 25/26",
      "team": "Sherwood Colliery F.C. Ladies U15",
      "home_away": "home",
      "opponent": "Priory Celtic F.C. U15 Girls",
      "goals_for": 9,
      "goals_against": 1
    },
    {
      "id": "4b9ff04b28b8faf7c440dec10255f113",
      "date": "2026-03-15",
      "time": "11:30",
      "home_team": "Radcliffe Olympic FC U10 Phantoms",
      "away_team": "Sherwood Colliery F.C. Ladies U10",
      "home_score": null,
      "away_score": null,
      "venue": "",
      "division": "U10 Development",
      "league": "Nottinghamshire Girls and Ladies Football League 25/26",
      "team": "Sherwood Colliery F.C. Ladies U10",
      "home_away": "away",
      "opponent": "Radcliffe Olympic FC U10 Phantoms",
      "goals_for": null,
      "goals_against": null
    },
    {
      "id": "e96917ed6777e8bb01c3242587689269",
      "date": "2026-03-15",
      "time": "11:15",
      "home_team": "Sherwood Colliery F.C. Ladies U12 Blue",
      "away_team": "Keyworth United F.C. U12 Shooting Stars",
      "home_score": 0,
      "away_score": 1,
      "venue": "",
      "division": "U12 Div 2 P2",
      "league": "Nottinghamshire Girls and Ladies Football League 25/26",
      "team": "Sherwood Colliery F.C. Ladies U12 Blue",
      "home_away": "home",
      "opponent": "Keyworth United F.C. U12 Shooting Stars",
      "goals_for": 0,
      "goals_against": 1
    },
    {
      "id": "d760ab8ec3e17a877344cd172132405d",
      "date": "2026-03-08",
      "time": "14:00",
      "home_team": "Southwell City FC Ladies",
      "away_team": "Sherwood Colliery FC Ladies",
      "home_score": 0,
      "away_score": 3,
      "venue": "",
      "division": "Seniors Div 2",
      "league": "Nottinghamshire Girls and Ladies Football League 25/26",
      "team": "Sherwood Colliery FC Ladies",
      "home_away": "away",
      "opponent": "Southwell City FC Ladies",
      "goals_for": 3,
      "goals_against": 0
    },
    {
      "id": "3bbe8261c04659ad6115b196bc2ecf5c",
      "date": "2026-03-08",
      "time": "12:30",
      "home_team": "Sherwood Colliery F.C. Ladies U11",
      "away_team": "Keyworth United F.C. U11 Tigers",
      "home_score": null,
      "away_score": null,
      "venue": "",
      "division": "U11 Development",
      "league": "Nottinghamshire Girls and Ladies Football League 25/26",
      "team": "Sherwood Colliery F.C. Ladies U11",
      "home_away": "home",
      "opponent": "Keyworth United F.C. U11 Tigers",
      "goals_for": null,
      "goals_against": null
    },
    {
      "id": "03a98a357e02138269b57954560c9135",
      "date": "2026-03-08",
      "time": "12:30",
      "home_team": "Gedling Southbank FC U14 Reds",
      "away_team": "Sherwood Colliery F.C. Ladies U14",
      "home_score": 1,
      "away_score": 4,
      "venue": "",
      "division": "U14 Div 3",
      "league": "Nottinghamshire Girls and Ladies Football League 25/26",
      "team": "Sherwood Colliery F.C. Ladies U14",
      "home_away": "away",
      "opponent": "Gedling Southbank FC U14 Reds",
      "goals_for": 4,
      "goals_against": 1
    },
    {
      "id": "f86a0b78b73dc5e1659000ecc62444f9",
      "date": "2026-03-08",
      "time": "10:00",
      "home_team": "Sherwood Colliery F.C. Ladies U12 Black",
      "away_team": "Clipstone Welfare Colts F.C. Youth U12",
      "home_score": 1,
      "away_score": 0,
      "venue": "",
      "division": "U12 Div 5 P2",
      "league": "Nottinghamshire Girls and Ladies Football League 25/26",
      "team": "Sherwood Colliery F.C. Ladies U12 Black",
      "home_away": "home",
      "opponent": "Clipstone Welfare Colts F.C. Youth U12",
      "goals_for": 1,
      "goals_against": 0
    },
    {
      "id": "c8e57f0a86eb40072436f79b4bfed9ab",
      "date": "2026-03-08",
      "time": "10:00",
      "home_team": "Hucknall & Linby Harriers FC U12 Jets",
      "away_team": "Sherwood Colliery F.C. Ladies U12 Blue",
      "home_score": 1,
      "away_score": 2,
      "venue": "",
      "division": "U12 Cup 3",
      "league": "Nottinghamshire Girls and Ladies Football League 25/26",
      "team": "Sherwood Colliery F.C. Ladies U12 Blue",
      "home_away": "away",
      "opponent": "Hucknall & Linby Harriers FC U12 Jets",
      "goals_for": 2,
      "goals_against": 1
    },
    {
      "id": "85c96c69b4706948805332ff170df43a",
      "date": "2026-03-08",
      "time": "09:45",
      "home_team": "Sherwood Colliery F.C. Ladies U10",
      "away_team": "Bingham Town F.C. U10 Girls",
      "home_score": null,
      "away_score": null,
      "venue": "",
      "division": "U10 Development",
      "league": "Nottinghamshire Girls and Ladies Football League 25/26",
      "team": "Sherwood Colliery F.C. Ladies U10",
      "home_away": "home",
      "opponent": "Bingham Town F.C. U10 Girls",
      "goals_for": null,
      "goals_against": null
    },
    {
      "id": "2ea3cf350018fe671e5619a6bf7395ff",
      "date": "2026-03-01",
      "time": "14:00",
      "home_team": "Sherwood Colliery F.C. Ladies U14",
      "away_team": "Hasland Community U14 Girls Sunday",
      "home_score": 2,
      "away_score": 4,
      "venue": "",
      "division": "U14 Div 3",
      "league": "Nottinghamshire Girls and Ladies Football League 25/26",
      "team": "Sherwood Colliery F.C. Ladies U14",
      "home_away": "home",
      "opponent": "Hasland Community U14 Girls Sunday",
      "goals_for": 2,
      "goals_against": 4
    },
    {
      "id": "4d4d882462ee22d2758f027286eb5c6b",
      "date": "2026-03-01",
      "time": "14:00",
      "home_team": "Gedling Southbank FC Ladies",
      "away_team": "Sherwood Colliery FC Ladies",
      "home_score": 1,
      "away_score": 1,
      "venue": "",
      "division": "Seniors Div 2",
      "league": "Nottinghamshire Girls and Ladies Football League 25/26",
      "team": "Sherwood Colliery FC Ladies",
      "home_away": "away",
      "opponent": "Gedling Southbank FC Ladies",
      "goals_for": 1,
      "goals_against": 1
    },
    {
      "id": "f8523135db3e1162c34dac2565b02843",
      "date": "2026-03-01",
      "time": "12:30",
      "home_team": "Sherwood Colliery F.C. Ladies U11",
      "away_team": "West Bridgford Colts U11 Hurricanes",
      "home_score": null,
      "away_score": null,
      "venue": "",
      "division": "U11 Development",
      "league": "Nottinghamshire Girls and Ladies Football League 25/26",
      "team": "Sherwood Colliery F.C. Ladies U11",
      "home_away": "home",
      "opponent": "West Bridgford Colts U11 Hurricanes",
      "goals_for": null,
      "goals_against": null
    },
    {
      "id": "64325039e11cf18625fa17a31823ca05",
      "date": "2026-03-01",
      "time": "12:30",
      "home_team": "Sherwood Colliery F.C. Ladies U15",
      "away_team": "Willow Wanderers F.C. Youth U15 Amazons",
      "home_score": 1,
      "away_score": 2,
      "venue": "",
      "division": "U15 Div 2 League Cup",
      "league": "Nottinghamshire Girls and Ladies Football League 25/26",
      "team": "Sherwood Colliery F.C. Ladies U15",
      "home_away": "home",
      "opponent": "Willow Wanderers F.C. Youth U15 Amazons",
      "goals_for": 1,
      "goals_against": 2
    },
    {
      "id": "6b87a156b6705f76fd889d9484aabfcf",
      "date": "2026-03-01",
      "time": "11:15",
      "home_team": "Sherwood Colliery F.C. Ladies U12 Black",
      "away_team": "Clipstone Welfare Colts F.C. Youth U12",
      "home_score": 0,
      "away_score": 1,
      "venue": "",
      "division": "U12 Cup 4",
      "league": "Nottinghamshire Girls and Ladies Football League 25/26",
      "team": "Sherwood Colliery F.C. Ladies U12 Black",
      "home_away": "home",
      "opponent": "Clipstone Welfare Colts F.C. Youth U12",
      "goals_for": 0,
      "goals_against": 1
    },
    {
      "id": "313fe6b31b981d3c0697c7d1ab26e74f",
      "date": "2026-03-01",
      "time": "10:00",
      "home_team": "Burton Joyce F.C. Girls U12 Outlaws",
      "away_team": "Sherwood Colliery F.C. Ladies U12 Blue",
      "home_score": 0,
      "away_score": 2,
      "venue": "",
      "division": "U12 Div 3",
      "league": "Nottinghamshire Girls and Ladies Football League 25/26",
      "team": "Sherwood Colliery F.C. Ladies U12 Blue",
      "home_away": "away",
      "opponent": "Burton Joyce F.C. Girls U12 Outlaws",
      "goals_for": 2,
      "goals_against": 0
    },
    {
      "id": "474eae35a770b335eb4b5196c1b241a0",
      "date": "2026-03-01",
      "time": "09:45",
      "home_team": "Sherwood Colliery F.C. Ladies U10",
      "away_team": "Gedling Southbank FC U10 Wolves",
      "home_score": null,
      "away_score": null,
      "venue": "",
      "division": "U10 Development",
      "league": "Nottinghamshire Girls and Ladies Football League 25/26",
      "team": "Sherwood Colliery F.C. Ladies U10",
      "home_away": "home",
      "opponent": "Gedling Southbank FC U10 Wolves",
      "goals_for": null,
      "goals_against": null
    },
    {
      "id": "f2c72b2631d05ce5c51772743ddba443",
      "date": "2026-02-22",
      "time": "14:00",
      "home_team": "Eastwood & Kimberley FC",
      "away_team": "Sherwood Colliery FC Ladies",
      "home_score": 1,
      "away_score": 3,
      "venue": "",
      "division": "Seniors Div 2",
      "league": "Nottinghamshire Girls and Ladies Football League 25/26",
      "team": "Sherwood Colliery FC Ladies",
      "home_away": "away",
      "opponent": "Eastwood & Kimberley FC",
      "goals_for": 3,
      "goals_against": 1
    },
    {
      "id": "4dc4184e10e736bf565c15bd89200157",
      "date": "2026-02-22",
      "time": "12:30",
      "home_team": "Sherwood Colliery F.C. Ladies U14",
      "away_team": "Shirebrook Rangers & Juniors U14 Girls",
      "home_score": 4,
      "away_score": 0,
      "venue": "",
      "division": "U14 Div 3 League Cup",
      "league": "Nottinghamshire Girls and Ladies Football League 25/26",
      "team": "Sherwood Colliery F.C. Ladies U14",
      "home_away": "home",
      "opponent": "Shirebrook Rangers & Juniors U14 Girls",
      "goals_for": 4,
      "goals_against": 0
    },
    {
      "id": "44851b5bb8435de3443356ea11e6f1fd",
      "date": "2026-02-22",
      "time": "12:30",
      "home_team": "Sherwood Colliery F.C. Ladies U15",
      "away_team": "Hilton Harriers U15 Girls Sunday",
      "home_score": 3,
      "away_score": 3,
      "venue": "",
      "division": "U15 Div 2",
      "league": "Nottinghamshire Girls and Ladies Football League 25/26",
      "team": "Sherwood Colliery F.C. Ladies U15",
      "home_away": "home",
      "opponent": "Hilton Harriers U15 Girls Sunday",
      "goals_for": 3,
      "goals_against": 3
    },
    {
      "id": "808a2ff5df9c5a3e85c16a516729e5f0",
      "date": "2026-02-22",
      "time": "11:00",
      "home_team": "Sutton Bonington U12 Comets",
      "away_team": "Sherwood Colliery F.C. Ladies U12 Black",
      "home_score": 1,
      "away_score": 2,
      "venue": "",
      "division": "U12 Div 5",
      "league": "Nottinghamshire Girls and Ladies Football League 25/26",
      "team": "Sherwood Colliery F.C. Ladies U12 Black",
      "home_away": "away",
      "opponent": "Sutton Bonington U12 Comets",
      "goals_for": 2,
      "goals_against": 1
    },
    {
      "id": "b70e37147d685754f7543d1ea9dd80b1",
      "date": "2026-02-22",
      "time": "10:00",
      "home_team": "Edwalton Cavaliers F.C. Girls U11 Blue",
      "away_team": "Sherwood Colliery F.C. Ladies U11",
      "home_score": 3,
      "away_score": 1,
      "venue": "",
      "division": "U11 CUP 1",
      "league": "Nottinghamshire Girls and Ladies Football League 25/26",
      "team": "Sherwood Colliery F.C. Ladies U11",
      "home_away": "away",
      "opponent": "Edwalton Cavaliers F.C. Girls U11 Blue",
      "goals_for": 1,
      "goals_against": 3
    },
    {
      "id": "16341e34df2011cf39e5f4a7641ea570",
      "date": "2026-02-22",
      "time": "10:00",
      "home_team": "Sherwood Colliery F.C. Ladies U12 Blue",
      "away_team": "Radcliffe Olympic FC U12 Girls Eagles",
      "home_score": 4,
      "away_score": 5,
      "venue": "",
      "division": "U12 Div 2 P2",
      "league": "Nottinghamshire Girls and Ladies Football League 25/26",
      "team": "Sherwood Colliery F.C. Ladies U12 Blue",
      "home_away": "home",
      "opponent": "Radcliffe Olympic FC U12 Girls Eagles",
      "goals_for": 4,
      "goals_against": 5
    },
    {
      "id": "443f1006556aa9ebbdd9d47b815643e7",
      "date": "2026-02-22",
      "time": "09:45",
      "home_team": "Sherwood Colliery F.C. Ladies U10",
      "away_team": "Beeston F.C. U10 Girls",
      "home_score": null,
      "away_score": null,
      "venue": "",
      "division": "U10 Development",
      "league": "Nottinghamshire Girls and Ladies Football League 25/26",
      "team": "Sherwood Colliery F.C. Ladies U10",
      "home_away": "home",
      "opponent": "Beeston F.C. U10 Girls",
      "goals_for": null,
      "goals_against": null
    },
    {
      "id": "2f982e5cf47fc315d505653f6e689b40",
      "date": "2026-02-15",
      "time": "11:15",
      "home_team": "Sherwood Colliery F.C. Ladies U11",
      "away_team": "Cotgrave FC U11 Girls",
      "home_score": null,
      "away_score": null,
      "venue": "",
      "division": "U11 Development",
      "league": "Nottinghamshire Girls and Ladies Football League 25/26",
      "team": "Sherwood Colliery F.C. Ladies U11",
      "home_away": "home",
      "opponent": "Cotgrave FC U11 Girls",
      "goals_for": null,
      "goals_against": null
    },
    {
      "id": "b07be26770f66d8ebecc008c202ee25a",
      "date": "2026-02-15",
      "time": "09:45",
      "home_team": "Sherwood Colliery F.C. Ladies U12 Black",
      "away_team": "Eastwood CFC U12 Girls",
      "home_score": 1,
      "away_score": 1,
      "venue": "",
      "division": "Other Fixtures",
      "league": "Nottinghamshire Girls and Ladies Football League 25/26",
      "team": "Sherwood Colliery F.C. Ladies U12 Black",
      "home_away": "home",
      "opponent": "Eastwood CFC U12 Girls",
      "goals_for": 1,
      "goals_against": 1
    },
    {
      "id": "7b589b81f8a862ef33c847e16a60517c",
      "date": "2026-02-08",
      "time": "14:30",
      "home_team": "Sherwood Colliery FC Ladies",
      "away_team": "Eastwood & Kimberley FC",
      "home_score": 0,
      "away_score": 2,
      "venue": "",
      "division": "Seniors Div 2",
      "league": "Nottinghamshire Girls and Ladies Football League 25/26",
      "team": "Sherwood Colliery FC Ladies",
      "home_away": "home",
      "opponent": "Eastwood & Kimberley FC",
      "goals_for": 0,
      "goals_against": 2
    },
    {
      "id": "54e51a62ad0e679b94924d70170eb036",
      "date": "2026-02-08",
      "time": "12:30",
      "home_team": "Sherwood Colliery F.C. Ladies U12 Black",
      "away_team": "Ravenshead Reds F.C. Youth U12",
      "home_score": 5,
      "away_score": 0,
      "venue": "",
      "division": "Other Fixtures",
      "league": "Nottinghamshire Girls and Ladies Football League 25/26",
      "team": "Sherwood Colliery F.C. Ladies U12 Black",
      "home_away": "home",
      "opponent": "Ravenshead Reds F.C. Youth U12",
      "goals_for": 5,
      "goals_against": 0
    },
    {
      "id": "c00dab49667eecac0396fd26c66613d5",
      "date": "2026-02-08",
      "time": "12:30",
      "home_team": "Sherwood Colliery F.C. Ladies U12 Blue",
      "away_team": "ATFA Brinsley FC U12",
      "home_score": 4,
      "away_score": 1,
      "venue": "",
      "division": "Other Fixtures",
      "league": "Nottinghamshire Girls and Ladies Football League 25/26",
      "team": "Sherwood Colliery F.C. Ladies U12 Blue",
      "home_away": "home",
      "opponent": "ATFA Brinsley FC U12",
      "goals_for": 4,
      "goals_against": 1
    },
    {
      "id": "8de8d70e8db8507adc157f8ff5fcdcc4",
      "date": "2026-02-08",
      "time": "10:00",
      "home_team": "Sherwood Colliery F.C. Ladies U11",
      "away_team": "Phoenix Inham F.C. U11 Flare",
      "home_score": null,
      "away_score": null,
      "venue": "",
      "division": "U11 Development",
      "league": "Nottinghamshire Girls and Ladies Football League 25/26",
      "team": "Sherwood Colliery F.C. Ladies U11",
      "home_away": "home",
      "opponent": "Phoenix Inham F.C. U11 Flare",
      "goals_for": null,
      "goals_against": null
    },
    {
      "id": "e85696d24e2b8f148201414efded0c9c",
      "date": "2026-02-01",
      "time": "14:30",
      "home_team": "Sherwood Colliery FC Ladies",
      "away_team": "Underwood Villa FC Youth Ladies",
      "home_score": 3,
      "away_score": 1,
      "venue": "",
      "division": "Seniors Div 2",
      "league": "Nottinghamshire Girls and Ladies Football League 25/26",
      "team": "Sherwood Colliery FC Ladies",
      "home_away": "home",
      "opponent": "Underwood Villa FC Youth Ladies",
      "goals_for": 3,
      "goals_against": 1
    },
    {
      "id": "e121d789bf068328f7444fa01b9993ab",
      "date": "2026-02-01",
      "time": "11:15",
      "home_team": "Priory Celtic F.C. U14 Girls",
      "away_team": "Sherwood Colliery F.C. Ladies U14",
      "home_score": 2,
      "away_score": 4,
      "venue": "",
      "division": "U14 Div 3",
      "league": "Nottinghamshire Girls and Ladies Football League 25/26",
      "team": "Sherwood Colliery F.C. Ladies U14",
      "home_away": "away",
      "opponent": "Priory Celtic F.C. U14 Girls",
      "goals_for": 4,
      "goals_against": 2
    },
    {
      "id": "2252c28b5de0efefd025484ebfe18d92",
      "date": "2026-02-01",
      "time": "10:00",
      "home_team": "Bingham Town F.C. U10 Girls",
      "away_team": "Sherwood Colliery F.C. Ladies U10",
      "home_score": null,
      "away_score": null,
      "venue": "",
      "division": "U10 Development",
      "league": "Nottinghamshire Girls and Ladies Football League 25/26",
      "team": "Sherwood Colliery F.C. Ladies U10",
      "home_away": "away",
      "opponent": "Bingham Town F.C. U10 Girls",
      "goals_for": null,
      "goals_against": null
    },
    {
      "id": "85a4ec85e74077d90a10362ab9ddb8b6",
      "date": "2026-01-25",
      "time": "14:30",
      "home_team": "Gedling Southbank FC Ladies",
      "away_team": "Sherwood Colliery FC Ladies",
      "home_score": 1,
      "away_score": 0,
      "venue": "",
      "division": "Senior Div 2 League Cup",
      "league": "Nottinghamshire Girls and Ladies Football League 25/26",
      "team": "Sherwood Colliery FC Ladies",
      "home_away": "away",
      "opponent": "Gedling Southbank FC Ladies",
      "goals_for": 0,
      "goals_against": 1
    },
    {
      "id": "c29dc524c6dd6e93d75f4f25f5c76d90",
      "date": "2026-01-25",
      "time": "11:45",
      "home_team": "Priory Celtic F.C. U15 Girls",
      "away_team": "Sherwood Colliery F.C. Ladies U15",
      "home_score": 0,
      "away_score": 12,
      "venue": "",
      "division": "U15 Div 2",
      "league": "Nottinghamshire Girls and Ladies Football League 25/26",
      "team": "Sherwood Colliery F.C. Ladies U15",
      "home_away": "away",
      "opponent": "Priory Celtic F.C. U15 Girls",
      "goals_for": 12,
      "goals_against": 0
    },
    {
      "id": "eb05a3a5d34ca6ff6d47dcb290888626",
      "date": "2026-01-25",
      "time": "11:15",
      "home_team": "Sherwood Colliery F.C. Ladies U12 Blue",
      "away_team": "Bingham Town F.C. U12 Girls Red",
      "home_score": 2,
      "away_score": 0,
      "venue": "",
      "division": "U12 Div 3",
      "league": "Nottinghamshire Girls and Ladies Football League 25/26",
      "team": "Sherwood Colliery F.C. Ladies U12 Blue",
      "home_away": "home",
      "opponent": "Bingham Town F.C. U12 Girls Red",
      "goals_for": 2,
      "goals_against": 0
    },
    {
      "id": "06fed9f40835d49cb9fa46a229640694",
      "date": "2026-01-25",
      "time": "11:15",
      "home_team": "Priory Celtic F.C. U14 Girls",
      "away_team": "Sherwood Colliery F.C. Ladies U14",
      "home_score": 1,
      "away_score": 10,
      "venue": "",
      "division": "U14 Div 3 League Cup",
      "league": "Nottinghamshire Girls and Ladies Football League 25/26",
      "team": "Sherwood Colliery F.C. Ladies U14",
      "home_away": "away",
      "opponent": "Priory Celtic F.C. U14 Girls",
      "goals_for": 10,
      "goals_against": 1
    },
    {
      "id": "7f0da4d06e3f79708ad63d52fc0008bb",
      "date": "2026-01-25",
      "time": "10:00",
      "home_team": "Eastwood CFC U12 Girls",
      "away_team": "Sherwood Colliery F.C. Ladies U12 Black",
      "home_score": 4,
      "away_score": 1,
      "venue": "",
      "division": "U12 Div 5",
      "league": "Nottinghamshire Girls and Ladies Football League 25/26",
      "team": "Sherwood Colliery F.C. Ladies U12 Black",
      "home_away": "away",
      "opponent": "Eastwood CFC U12 Girls",
      "goals_for": 1,
      "goals_against": 4
    },
    {
      "id": "09381a9be63c608eb13d1f0afe002e2c",
      "date": "2026-01-25",
      "time": "09:45",
      "home_team": "Sherwood Colliery F.C. Ladies U10",
      "away_team": "Arnold Town FC U10 Girls",
      "home_score": 2,
      "away_score": 3,
      "venue": "",
      "division": "U10 League Cup",
      "league": "Nottinghamshire Girls and Ladies Football League 25/26",
      "team": "Sherwood Colliery F.C. Ladies U10",
      "home_away": "home",
      "opponent": "Arnold Town FC U10 Girls",
      "goals_for": 2,
      "goals_against": 3
    },
    {
      "id": "81efaa376b525edb3ca91dd0c8059136",
      "date": "2026-01-18",
      "time": "14:30",
      "home_team": "Sherwood Colliery FC Ladies",
      "away_team": "Sherwood FC Development Women",
      "home_score": 6,
      "away_score": 0,
      "venue": "",
      "division": "Seniors Div 2",
      "league": "Nottinghamshire Girls and Ladies Football League 25/26",
      "team": "Sherwood Colliery FC Ladies",
      "home_away": "home",
      "opponent": "Sherwood FC Development Women",
      "goals_for": 6,
      "goals_against": 0
    },
    {
      "id": "dbab88a388e9d70ed225ce3fb064df34",
      "date": "2026-01-18",
      "time": "12:30",
      "home_team": "Sherwood Colliery F.C. Ladies U14",
      "away_team": "Nottingham F.C. Youth U14 Girls",
      "home_score": 8,
      "away_score": 1,
      "venue": "",
      "division": "U14 Div 3",
      "league": "Nottinghamshire Girls and Ladies Football League 25/26",
      "team": "Sherwood Colliery F.C. Ladies U14",
      "home_away": "home",
      "opponent": "Nottingham F.C. Youth U14 Girls",
      "goals_for": 8,
      "goals_against": 1
    },
    {
      "id": "ecd689a463ab844f2b236983b7068594",
      "date": "2026-01-18",
      "time": "10:00",
      "home_team": "Newark Brazil F.C. Juniors U11 Girls",
      "away_team": "Sherwood Colliery F.C. Ladies U11",
      "home_score": null,
      "away_score": null,
      "venue": "",
      "division": "U11 Development",
      "league": "Nottinghamshire Girls and Ladies Football League 25/26",
      "team": "Sherwood Colliery F.C. Ladies U11",
      "home_away": "away",
      "opponent": "Newark Brazil F.C. Juniors U11 Girls",
      "goals_for": null,
      "goals_against": null
    },
    {
      "id": "9264f41843c8868c998f482b70b85ea0",
      "date": "2026-01-18",
      "time": "09:30",
      "home_team": "West Bridgford Colts U10 Sun",
      "away_team": "Sherwood Colliery F.C. Ladies U10",
      "home_score": null,
      "away_score": null,
      "venue": "",
      "division": "U10 Development",
      "league": "Nottinghamshire Girls and Ladies Football League 25/26",
      "team": "Sherwood Colliery F.C. Ladies U10",
      "home_away": "away",
      "opponent": "West Bridgford Colts U10 Sun",
      "goals_for": null,
      "goals_against": null
    },
    {
      "id": "653323c03a3c259501b6906c42e142bf",
      "date": "2026-01-04",
      "time": "11:15",
      "home_team": "Sherwood Colliery F.C. Ladies U12 Black",
      "away_team": "Muskham Cougars F.C. Youth U12",
      "home_score": 1,
      "away_score": 1,
      "venue": "",
      "division": "U12 Cup",
      "league": "Nottinghamshire Girls and Ladies Football League 25/26",
      "team": "Sherwood Colliery F.C. Ladies U12 Black",
      "home_away": "home",
      "opponent": "Muskham Cougars F.C. Youth U12",
      "goals_for": 1,
      "goals_against": 1
    },
    {
      "id": "406b8e38cc6ddd2b06608c2deb702c74",
      "date": "2026-01-04",
      "time": "11:15",
      "home_team": "Sherwood Colliery F.C. Ladies U12 Blue",
      "away_team": "Blidworth Bengals F.C. U12",
      "home_score": 1,
      "away_score": 4,
      "venue": "",
      "division": "U12 Cup",
      "league": "Nottinghamshire Girls and Ladies Football League 25/26",
      "team": "Sherwood Colliery F.C. Ladies U12 Blue",
      "home_away": "home",
      "opponent": "Blidworth Bengals F.C. U12",
      "goals_for": 1,
      "goals_against": 4
    },
    {
      "id": "8fe412b541e2170bbf9936dd2d42734d",
      "date": "2026-01-04",
      "time": "10:30",
      "home_team": "West Bridgford Colts U11 Hurricanes",
      "away_team": "Sherwood Colliery F.C. Ladies U11",
      "home_score": null,
      "away_score": null,
      "venue": "",
      "division": "U11 Development",
      "league": "Nottinghamshire Girls and Ladies Football League 25/26",
      "team": "Sherwood Colliery F.C. Ladies U11",
      "home_away": "away",
      "opponent": "West Bridgford Colts U11 Hurricanes",
      "goals_for": null,
      "goals_against": null
    },
    {
      "id": "eed3dfb53de1f9a9dba5c9dcfea20eb9",
      "date": "2026-01-04",
      "time": "09:45",
      "home_team": "Sherwood Colliery F.C. Ladies U10",
      "away_team": "Ravenshead Reds F.C. Youth U10",
      "home_score": null,
      "away_score": null,
      "venue": "",
      "division": "U10 Development Yellow",
      "league": "Nottinghamshire Girls and Ladies Football League 25/26",
      "team": "Sherwood Colliery F.C. Ladies U10",
      "home_away": "home",
      "opponent": "Ravenshead Reds F.C. Youth U10",
      "goals_for": null,
      "goals_against": null
    },
    {
      "id": "e9be3c87795b074eb7d5edbdf8cc98fb",
      "date": "2025-12-14",
      "time": "12:30",
      "home_team": "Sherwood Colliery F.C. Ladies U10",
      "away_team": "Market Warsop F.C. Youth U10 Lionesses",
      "home_score": null,
      "away_score": null,
      "venue": "",
      "division": "U10 Development",
      "league": "Nottinghamshire Girls and Ladies Football League 25/26",
      "team": "Sherwood Colliery F.C. Ladies U10",
      "home_away": "home",
      "opponent": "Market Warsop F.C. Youth U10 Lionesses",
      "goals_for": null,
      "goals_against": null
    },
    {
      "id": "2c9a9e05619171a9f52977650e262fd3",
      "date": "2025-12-14",
      "time": "12:00",
      "home_team": "Ollerton Town Community FC U12 Girls",
      "away_team": "Sherwood Colliery F.C. Ladies U12 Blue",
      "home_score": 1,
      "away_score": 1,
      "venue": "",
      "division": "U12 Div 3",
      "league": "Nottinghamshire Girls and Ladies Football League 25/26",
      "team": "Sherwood Colliery F.C. Ladies U12 Blue",
      "home_away": "away",
      "opponent": "Ollerton Town Community FC U12 Girls",
      "goals_for": 1,
      "goals_against": 1
    },
    {
      "id": "962312311930470c479567862c26e195",
      "date": "2025-12-14",
      "time": "11:15",
      "home_team": "Sherwood Colliery F.C. Ladies U12 Black",
      "away_team": "Quarrydale United FC U12",
      "home_score": 1,
      "away_score": 0,
      "venue": "",
      "division": "U12 Div 5",
      "league": "Nottinghamshire Girls and Ladies Football League 25/26",
      "team": "Sherwood Colliery F.C. Ladies U12 Black",
      "home_away": "home",
      "opponent": "Quarrydale United FC U12",
      "goals_for": 1,
      "goals_against": 0
    },
    {
      "id": "c9d71995ef77ed9adb45c372ae23131a",
      "date": "2025-12-14",
      "time": "11:15",
      "home_team": "Sandiacre Town Youth U15 Girls Sparkle",
      "away_team": "Sherwood Colliery F.C. Ladies U15",
      "home_score": 0,
      "away_score": 2,
      "venue": "",
      "division": "U15 Div 2 League Cup",
      "league": "Nottinghamshire Girls and Ladies Football League 25/26",
      "team": "Sherwood Colliery F.C. Ladies U15",
      "home_away": "away",
      "opponent": "Sandiacre Town Youth U15 Girls Sparkle",
      "goals_for": 2,
      "goals_against": 0
    },
    {
      "id": "c8c1f22dcc8e3669b7fe86e9ccab23c7",
      "date": "2025-12-14",
      "time": "10:30",
      "home_team": "Riverside Junior U14 Rubies",
      "away_team": "Sherwood Colliery F.C. Ladies U14",
      "home_score": 4,
      "away_score": 2,
      "venue": "",
      "division": "U14 Div 3 League Cup",
      "league": "Nottinghamshire Girls and Ladies Football League 25/26",
      "team": "Sherwood Colliery F.C. Ladies U14",
      "home_away": "away",
      "opponent": "Riverside Junior U14 Rubies",
      "goals_for": 2,
      "goals_against": 4
    },
    {
      "id": "91614db7a6e4af5b16a2956e0e952789",
      "date": "2025-12-14",
      "time": "10:00",
      "home_team": "Priory Celtic FC Ladies First Team",
      "away_team": "Sherwood Colliery FC Ladies",
      "home_score": 1,
      "away_score": 6,
      "venue": "",
      "division": "Seniors Div 2",
      "league": "Nottinghamshire Girls and Ladies Football League 25/26",
      "team": "Sherwood Colliery FC Ladies",
      "home_away": "away",
      "opponent": "Priory Celtic FC Ladies First Team",
      "goals_for": 6,
      "goals_against": 1
    },
    {
      "id": "477f13551dd3966d45a1e34dd9efc67c",
      "date": "2025-12-07",
      "time": "14:00",
      "home_team": "Eastwood & Kimberley FC",
      "away_team": "Sherwood Colliery FC Ladies",
      "home_score": 6,
      "away_score": 2,
      "venue": "",
      "division": "Senior Div 2 League Cup",
      "league": "Nottinghamshire Girls and Ladies Football League 25/26",
      "team": "Sherwood Colliery FC Ladies",
      "home_away": "away",
      "opponent": "Eastwood & Kimberley FC",
      "goals_for": 2,
      "goals_against": 6
    },
    {
      "id": "fec82e3d274d8f3d8d91a98e5e9409bf",
      "date": "2025-12-07",
      "time": "12:30",
      "home_team": "Sherwood Colliery F.C. Ladies U14",
      "away_team": "Shirebrook Rangers & Juniors U14 Girls",
      "home_score": 3,
      "away_score": 0,
      "venue": "",
      "division": "U14 Div 3 League Cup",
      "league": "Nottinghamshire Girls and Ladies Football League 25/26",
      "team": "Sherwood Colliery F.C. Ladies U14",
      "home_away": "home",
      "opponent": "Shirebrook Rangers & Juniors U14 Girls",
      "goals_for": 3,
      "goals_against": 0
    },
    {
      "id": "ccffe71df72c344d3066cf5e8ba2f32e",
      "date": "2025-12-07",
      "time": "11:15",
      "home_team": "Sherwood Colliery F.C. Ladies U12 Blue",
      "away_team": "West Bridgford Colts U12 Lightning",
      "home_score": 4,
      "away_score": 2,
      "venue": "",
      "division": "U12 Div 3",
      "league": "Nottinghamshire Girls and Ladies Football League 25/26",
      "team": "Sherwood Colliery F.C. Ladies U12 Blue",
      "home_away": "home",
      "opponent": "West Bridgford Colts U12 Lightning",
      "goals_for": 4,
      "goals_against": 2
    },
    {
      "id": "ac58e2514400d05e62c728717b63ac79",
      "date": "2025-12-07",
      "time": "10:00",
      "home_team": "Muskham Cougars F.C. Youth U12",
      "away_team": "Sherwood Colliery F.C. Ladies U12 Black",
      "home_score": 4,
      "away_score": 1,
      "venue": "",
      "division": "U12 Div 5",
      "league": "Nottinghamshire Girls and Ladies Football League 25/26",
      "team": "Sherwood Colliery F.C. Ladies U12 Black",
      "home_away": "away",
      "opponent": "Muskham Cougars F.C. Youth U12",
      "goals_for": 1,
      "goals_against": 4
    },
    {
      "id": "33123812ec34eca35b0f82a58da0e1ec",
      "date": "2025-11-30",
      "time": "12:30",
      "home_team": "Sherwood Colliery F.C. Ladies U15",
      "away_team": "Woodlands Women U15",
      "home_score": 1,
      "away_score": 2,
      "venue": "",
      "division": "U15 Div 2",
      "league": "Nottinghamshire Girls and Ladies Football League 25/26",
      "team": "Sherwood Colliery F.C. Ladies U15",
      "home_away": "home",
      "opponent": "Woodlands Women U15",
      "goals_for": 1,
      "goals_against": 2
    },
    {
      "id": "bfab7eae5aa7017606d12e6b23ad4944",
      "date": "2025-11-30",
      "time": "11:15",
      "home_team": "Ravenshead Reds F.C. Youth U12",
      "away_team": "Sherwood Colliery F.C. Ladies U12 Black",
      "home_score": 0,
      "away_score": 3,
      "venue": "",
      "division": "U12 Cup",
      "league": "Nottinghamshire Girls and Ladies Football League 25/26",
      "team": "Sherwood Colliery F.C. Ladies U12 Black",
      "home_away": "away",
      "opponent": "Ravenshead Reds F.C. Youth U12",
      "goals_for": 3,
      "goals_against": 0
    },
    {
      "id": "8a35b36db3ff5a057a6551c2377c36b8",
      "date": "2025-11-30",
      "time": "11:15",
      "home_team": "Sherwood Colliery F.C. Ladies U12 Blue",
      "away_team": "Bingham Town F.C. U12 Girls Blue",
      "home_score": 0,
      "away_score": 2,
      "venue": "",
      "division": "U12 Cup",
      "league": "Nottinghamshire Girls and Ladies Football League 25/26",
      "team": "Sherwood Colliery F.C. Ladies U12 Blue",
      "home_away": "home",
      "opponent": "Bingham Town F.C. U12 Girls Blue",
      "goals_for": 0,
      "goals_against": 2
    },
    {
      "id": "c3314fe4d6dfcd06ceab44afb20588c7",
      "date": "2025-11-30",
      "time": "09:45",
      "home_team": "Sherwood Colliery F.C. Ladies U10",
      "away_team": "Arnold Eagles F.C. Girls U10 Braves",
      "home_score": null,
      "away_score": null,
      "venue": "",
      "division": "U10 Development Yellow",
      "league": "Nottinghamshire Girls and Ladies Football League 25/26",
      "team": "Sherwood Colliery F.C. Ladies U10",
      "home_away": "home",
      "opponent": "Arnold Eagles F.C. Girls U10 Braves",
      "goals_for": null,
      "goals_against": null
    },
    {
      "id": "8252982a5e2ce7bfd2b83e1530f32c18",
      "date": "2025-11-23",
      "time": "14:30",
      "home_team": "Sherwood Colliery FC Ladies",
      "away_team": "Gedling Southbank FC Ladies",
      "home_score": 0,
      "away_score": 3,
      "venue": "",
      "division": "Seniors Div 2",
      "league": "Nottinghamshire Girls and Ladies Football League 25/26",
      "team": "Sherwood Colliery FC Ladies",
      "home_away": "home",
      "opponent": "Gedling Southbank FC Ladies",
      "goals_for": 0,
      "goals_against": 3
    },
    {
      "id": "a6ed8e065714bfe4415b0f01e5e66af1",
      "date": "2025-11-23",
      "time": "12:30",
      "home_team": "Sherwood Colliery F.C. Ladies U14",
      "away_team": "Ravenshead Reds F.C. Youth U14",
      "home_score": 2,
      "away_score": 4,
      "venue": "",
      "division": "U14 Div 3",
      "league": "Nottinghamshire Girls and Ladies Football League 25/26",
      "team": "Sherwood Colliery F.C. Ladies U14",
      "home_away": "home",
      "opponent": "Ravenshead Reds F.C. Youth U14",
      "goals_for": 2,
      "goals_against": 4
    },
    {
      "id": "cb23e08daaeccf473381365a2380a105",
      "date": "2025-11-23",
      "time": "12:30",
      "home_team": "Sherwood Colliery F.C. Ladies U15",
      "away_team": "Tansley Juniors U15 Girls",
      "home_score": 2,
      "away_score": 4,
      "venue": "",
      "division": "U15 Div 2",
      "league": "Nottinghamshire Girls and Ladies Football League 25/26",
      "team": "Sherwood Colliery F.C. Ladies U15",
      "home_away": "home",
      "opponent": "Tansley Juniors U15 Girls",
      "goals_for": 2,
      "goals_against": 4
    },
    {
      "id": "e0cfb15ce8ae504abc20ab899198f250",
      "date": "2025-11-23",
      "time": "11:30",
      "home_team": "Ravenshead Reds F.C. Youth U12",
      "away_team": "Sherwood Colliery F.C. Ladies U12 Black",
      "home_score": 0,
      "away_score": 3,
      "venue": "",
      "division": "U12 Div 5",
      "league": "Nottinghamshire Girls and Ladies Football League 25/26",
      "team": "Sherwood Colliery F.C. Ladies U12 Black",
      "home_away": "away",
      "opponent": "Ravenshead Reds F.C. Youth U12",
      "goals_for": 3,
      "goals_against": 0
    },
    {
      "id": "516d76640e1be59ce1580f1415e5a5c1",
      "date": "2025-11-23",
      "time": "11:15",
      "home_team": "Sherwood Colliery F.C. Ladies U12 Blue",
      "away_team": "Bingham Town F.C. U12 Girls Blue",
      "home_score": 1,
      "away_score": 1,
      "venue": "",
      "division": "U12 Div 3",
      "league": "Nottinghamshire Girls and Ladies Football League 25/26",
      "team": "Sherwood Colliery F.C. Ladies U12 Blue",
      "home_away": "home",
      "opponent": "Bingham Town F.C. U12 Girls Blue",
      "goals_for": 1,
      "goals_against": 1
    },
    {
      "id": "0605cca11c90675338c62fba77770380",
      "date": "2025-11-23",
      "time": "09:45",
      "home_team": "Sherwood Colliery F.C. Ladies U10",
      "away_team": "Stanton Ilkeston U10 Steelers",
      "home_score": 3,
      "away_score": 3,
      "venue": "",
      "division": "U10 League Cup",
      "league": "Nottinghamshire Girls and Ladies Football League 25/26",
      "team": "Sherwood Colliery F.C. Ladies U10",
      "home_away": "home",
      "opponent": "Stanton Ilkeston U10 Steelers",
      "goals_for": 3,
      "goals_against": 3
    },
    {
      "id": "7c1b43f30e4f9097ff936222f79b2899",
      "date": "2025-11-16",
      "time": "12:30",
      "home_team": "Sherwood Colliery F.C. Ladies U10",
      "away_team": "Canoville FC U10 FC Gold",
      "home_score": null,
      "away_score": null,
      "venue": "",
      "division": "U10 Development Yellow",
      "league": "Nottinghamshire Girls and Ladies Football League 25/26",
      "team": "Sherwood Colliery F.C. Ladies U10",
      "home_away": "home",
      "opponent": "Canoville FC U10 FC Gold",
      "goals_for": null,
      "goals_against": null
    },
    {
      "id": "f0058965179ca86c4479c76add66ebd0",
      "date": "2025-11-16",
      "time": "12:30",
      "home_team": "Sherwood Colliery F.C. Ladies U12 Black",
      "away_team": "Tansley Juniors U12 Girls",
      "home_score": 8,
      "away_score": 0,
      "venue": "",
      "division": "U12 Div 5",
      "league": "Nottinghamshire Girls and Ladies Football League 25/26",
      "team": "Sherwood Colliery F.C. Ladies U12 Black",
      "home_away": "home",
      "opponent": "Tansley Juniors U12 Girls",
      "goals_for": 8,
      "goals_against": 0
    },
    {
      "id": "e51b24afc7e02e313b10391ec1f4fd66",
      "date": "2025-11-16",
      "time": "11:15",
      "home_team": "Sherwood Colliery F.C. Ladies U11",
      "away_team": "Calverton Miners Welfare FC U11 Girls",
      "home_score": null,
      "away_score": null,
      "venue": "",
      "division": "U11 Development Blue",
      "league": "Nottinghamshire Girls and Ladies Football League 25/26",
      "team": "Sherwood Colliery F.C. Ladies U11",
      "home_away": "home",
      "opponent": "Calverton Miners Welfare FC U11 Girls",
      "goals_for": null,
      "goals_against": null
    },
    {
      "id": "90b6439346f7ddc1ae685318c36aad81",
      "date": "2025-11-16",
      "time": "10:00",
      "home_team": "Bingham Town F.C. U15 Girls",
      "away_team": "Sherwood Colliery F.C. Ladies U15",
      "home_score": 1,
      "away_score": 8,
      "venue": "",
      "division": "U15 Div 2",
      "league": "Nottinghamshire Girls and Ladies Football League 25/26",
      "team": "Sherwood Colliery F.C. Ladies U15",
      "home_away": "away",
      "opponent": "Bingham Town F.C. U15 Girls",
      "goals_for": 8,
      "goals_against": 1
    },
    {
      "id": "93ad6dfa01a1f889c53e9645f2f4ffc8",
      "date": "2025-11-09",
      "time": "14:30",
      "home_team": "Sherwood Colliery FC Ladies",
      "away_team": "Arnold Town FC Women",
      "home_score": 5,
      "away_score": 1,
      "venue": "",
      "division": "Senior Div 2 League Cup",
      "league": "Nottinghamshire Girls and Ladies Football League 25/26",
      "team": "Sherwood Colliery FC Ladies",
      "home_away": "home",
      "opponent": "Arnold Town FC Women",
      "goals_for": 5,
      "goals_against": 1
    },
    {
      "id": "b4fbe6d0874f62ef1514824c04a02ecf",
      "date": "2025-11-09",
      "time": "12:30",
      "home_team": "Sherwood Colliery F.C. Ladies U12 Black",
      "away_team": "Sutton Bonington U12 Comets",
      "home_score": 10,
      "away_score": 0,
      "venue": "",
      "division": "U12 Cup",
      "league": "Nottinghamshire Girls and Ladies Football League 25/26",
      "team": "Sherwood Colliery F.C. Ladies U12 Black",
      "home_away": "home",
      "opponent": "Sutton Bonington U12 Comets",
      "goals_for": 10,
      "goals_against": 0
    },
    {
      "id": "d95dd540f60950b5e048f237174609e6",
      "date": "2025-11-09",
      "time": "12:30",
      "home_team": "Sherwood Colliery F.C. Ladies U15",
      "away_team": "Tansley Juniors U15 Girls",
      "home_score": 4,
      "away_score": 2,
      "venue": "",
      "division": "U15 Div 2 League Cup",
      "league": "Nottinghamshire Girls and Ladies Football League 25/26",
      "team": "Sherwood Colliery F.C. Ladies U15",
      "home_away": "home",
      "opponent": "Tansley Juniors U15 Girls",
      "goals_for": 4,
      "goals_against": 2
    },
    {
      "id": "f9053fe40e628f8c3afc4fe7238f336b",
      "date": "2025-11-09",
      "time": "11:00",
      "home_team": "West Bridgford Colts U12 Lightning",
      "away_team": "Sherwood Colliery F.C. Ladies U12 Blue",
      "home_score": 2,
      "away_score": 2,
      "venue": "",
      "division": "U12 Cup",
      "league": "Nottinghamshire Girls and Ladies Football League 25/26",
      "team": "Sherwood Colliery F.C. Ladies U12 Blue",
      "home_away": "away",
      "opponent": "West Bridgford Colts U12 Lightning",
      "goals_for": 2,
      "goals_against": 2
    },
    {
      "id": "be2fc0a7376d8b5e1f7f93630a91624c",
      "date": "2025-11-02",
      "time": "14:00",
      "home_team": "Sherwood Colliery FC Ladies",
      "away_team": "Arnold Town FC Women",
      "home_score": 4,
      "away_score": 0,
      "venue": "",
      "division": "Seniors Div 2",
      "league": "Nottinghamshire Girls and Ladies Football League 25/26",
      "team": "Sherwood Colliery FC Ladies",
      "home_away": "home",
      "opponent": "Arnold Town FC Women",
      "goals_for": 4,
      "goals_against": 0
    },
    {
      "id": "e9fc6a904a51d46f3b11ab58be82f5e1",
      "date": "2025-11-02",
      "time": "12:30",
      "home_team": "Gedling Southbank FC U12 Hunters",
      "away_team": "Sherwood Colliery F.C. Ladies U12 Blue",
      "home_score": 0,
      "away_score": 3,
      "venue": "",
      "division": "U12 Div 3",
      "league": "Nottinghamshire Girls and Ladies Football League 25/26",
      "team": "Sherwood Colliery F.C. Ladies U12 Blue",
      "home_away": "away",
      "opponent": "Gedling Southbank FC U12 Hunters",
      "goals_for": 3,
      "goals_against": 0
    },
    {
      "id": "3895e4c6980bceb090fd8034f6d93fb9",
      "date": "2025-11-02",
      "time": "12:00",
      "home_team": "Shirebrook Rangers & Juniors U14 Girls",
      "away_team": "Sherwood Colliery F.C. Ladies U14",
      "home_score": 2,
      "away_score": 1,
      "venue": "",
      "division": "U14 Div 3",
      "league": "Nottinghamshire Girls and Ladies Football League 25/26",
      "team": "Sherwood Colliery F.C. Ladies U14",
      "home_away": "away",
      "opponent": "Shirebrook Rangers & Juniors U14 Girls",
      "goals_for": 1,
      "goals_against": 2
    },
    {
      "id": "3422f12888cc771588d2ef7f69d7da93",
      "date": "2025-11-02",
      "time": "10:30",
      "home_team": "Lowdham Colts F.C. Youth U15 Girls",
      "away_team": "Sherwood Colliery F.C. Ladies U15",
      "home_score": 3,
      "away_score": 1,
      "venue": "",
      "division": "U15 Div 2",
      "league": "Nottinghamshire Girls and Ladies Football League 25/26",
      "team": "Sherwood Colliery F.C. Ladies U15",
      "home_away": "away",
      "opponent": "Lowdham Colts F.C. Youth U15 Girls",
      "goals_for": 1,
      "goals_against": 3
    },
    {
      "id": "9dbadc2a96feaf4b56307765d748f57d",
      "date": "2025-11-02",
      "time": "10:00",
      "home_team": "Market Warsop F.C. Youth U10 Lionesses",
      "away_team": "Sherwood Colliery F.C. Ladies U10",
      "home_score": null,
      "away_score": null,
      "venue": "",
      "division": "U10 Development Yellow",
      "league": "Nottinghamshire Girls and Ladies Football League 25/26",
      "team": "Sherwood Colliery F.C. Ladies U10",
      "home_away": "away",
      "opponent": "Market Warsop F.C. Youth U10 Lionesses",
      "goals_for": null,
      "goals_against": null
    },
    {
      "id": "7aeb51f6d1172cd68d2293ddb9067007",
      "date": "2025-10-19",
      "time": "11:15",
      "home_team": "Sherwood Colliery F.C. Ladies U12 Blue",
      "away_team": "Burton Joyce F.C. Girls U12 Outlaws",
      "home_score": 2,
      "away_score": 0,
      "venue": "",
      "division": "U12",
      "league": "Nottinghamshire Girls and Ladies Football League 25/26",
      "team": "Sherwood Colliery F.C. Ladies U12 Blue",
      "home_away": "home",
      "opponent": "Burton Joyce F.C. Girls U12 Outlaws",
      "goals_for": 2,
      "goals_against": 0
    },
    {
      "id": "dc1c201e448432d9c11db09206f03d90",
      "date": "2025-10-12",
      "time": "12:30",
      "home_team": "Sherwood Colliery F.C. Ladies U12 Blue",
      "away_team": "Blidworth Bengals F.C. U12",
      "home_score": 3,
      "away_score": 1,
      "venue": "",
      "division": "U12",
      "league": "Nottinghamshire Girls and Ladies Football League 25/26",
      "team": "Sherwood Colliery F.C. Ladies U12 Blue",
      "home_away": "home",
      "opponent": "Blidworth Bengals F.C. U12",
      "goals_for": 3,
      "goals_against": 1
    },
    {
      "id": "a6dd30d940e519f91b282301aeb1627d",
      "date": "2025-10-12",
      "time": "11:15",
      "home_team": "Sherwood Colliery F.C. Ladies U12 Black",
      "away_team": "Ravenshead Reds F.C. Youth U12",
      "home_score": 6,
      "away_score": 0,
      "venue": "",
      "division": "U12",
      "league": "Nottinghamshire Girls and Ladies Football League 25/26",
      "team": "Sherwood Colliery F.C. Ladies U12 Black",
      "home_away": "home",
      "opponent": "Ravenshead Reds F.C. Youth U12",
      "goals_for": 6,
      "goals_against": 0
    },
    {
      "id": "4a124403a46ef0eb842dee5dff932ccd",
      "date": "2025-10-12",
      "time": "10:30",
      "home_team": "Sherwood Colliery F.C. Ladies U14",
      "away_team": "Shirebrook Rangers & Juniors U14 Girls",
      "home_score": 2,
      "away_score": 1,
      "venue": "",
      "division": "U14 Div 3",
      "league": "Nottinghamshire Girls and Ladies Football League 25/26",
      "team": "Sherwood Colliery F.C. Ladies U14",
      "home_away": "home",
      "opponent": "Shirebrook Rangers & Juniors U14 Girls",
      "goals_for": 2,
      "goals_against": 1
    },
    {
      "id": "a6caa0870707ee431cbe434a5eca35d6",
      "date": "2025-10-12",
      "time": "09:30",
      "home_team": "Priory Celtic F.C. U10 Girls",
      "away_team": "Sherwood Colliery F.C. Ladies U10",
      "home_score": 0,
      "away_score": 9,
      "venue": "",
      "division": "U10 League Cup",
      "league": "Nottinghamshire Girls and Ladies Football League 25/26",
      "team": "Sherwood Colliery F.C. Ladies U10",
      "home_away": "away",
      "opponent": "Priory Celtic F.C. U10 Girls",
      "goals_for": 9,
      "goals_against": 0
    },
    {
      "id": "d5edb098541f2387941d4bd1023f26b1",
      "date": "2025-10-05",
      "time": "14:30",
      "home_team": "Arnold Eagles F.C. Girls U12 FC",
      "away_team": "Sherwood Colliery F.C. Ladies U12 Blue",
      "home_score": 2,
      "away_score": 2,
      "venue": "",
      "division": "U12",
      "league": "Nottinghamshire Girls and Ladies Football League 25/26",
      "team": "Sherwood Colliery F.C. Ladies U12 Blue",
      "home_away": "away",
      "opponent": "Arnold Eagles F.C. Girls U12 FC",
      "goals_for": 2,
      "goals_against": 2
    },
    {
      "id": "6a94734ba8fd469cb1542446c42da9cd",
      "date": "2025-10-05",
      "time": "14:00",
      "home_team": "Sherwood Colliery FC Ladies",
      "away_team": "Southwell City FC Ladies",
      "home_score": 2,
      "away_score": 1,
      "venue": "",
      "division": "Seniors Div 2",
      "league": "Nottinghamshire Girls and Ladies Football League 25/26",
      "team": "Sherwood Colliery FC Ladies",
      "home_away": "home",
      "opponent": "Southwell City FC Ladies",
      "goals_for": 2,
      "goals_against": 1
    },
    {
      "id": "c1cf406a66a633d792c6db646342ae28",
      "date": "2025-10-05",
      "time": "13:00",
      "home_team": "Arnold Eagles F.C. Girls U11 Rangers",
      "away_team": "Sherwood Colliery F.C. Ladies U11",
      "home_score": null,
      "away_score": null,
      "venue": "",
      "division": "U11 Development Blue",
      "league": "Nottinghamshire Girls and Ladies Football League 25/26",
      "team": "Sherwood Colliery F.C. Ladies U11",
      "home_away": "away",
      "opponent": "Arnold Eagles F.C. Girls U11 Rangers",
      "goals_for": null,
      "goals_against": null
    },
    {
      "id": "40d4b002c5d9076db03b2defc6b5b123",
      "date": "2025-10-05",
      "time": "11:30",
      "home_team": "Gedling Southbank FC U12 Hunters",
      "away_team": "Sherwood Colliery F.C. Ladies U12 Black",
      "home_score": 5,
      "away_score": 0,
      "venue": "",
      "division": "U12",
      "league": "Nottinghamshire Girls and Ladies Football League 25/26",
      "team": "Sherwood Colliery F.C. Ladies U12 Black",
      "home_away": "away",
      "opponent": "Gedling Southbank FC U12 Hunters",
      "goals_for": 0,
      "goals_against": 5
    },
    {
      "id": "9d87bddf914e47f64ffa41ac778d653a",
      "date": "2025-10-05",
      "time": "11:30",
      "home_team": "Keyworth United F.C. U15 Kobras",
      "away_team": "Sherwood Colliery F.C. Ladies U15",
      "home_score": 2,
      "away_score": 1,
      "venue": "",
      "division": "U15 Div 2",
      "league": "Nottinghamshire Girls and Ladies Football League 25/26",
      "team": "Sherwood Colliery F.C. Ladies U15",
      "home_away": "away",
      "opponent": "Keyworth United F.C. U15 Kobras",
      "goals_for": 1,
      "goals_against": 2
    },
    {
      "id": "6fb62a5c82fac49ec92eb17848a6fd1f",
      "date": "2025-10-05",
      "time": "10:30",
      "home_team": "Hucknall & Linby Harriers FC U10",
      "away_team": "Sherwood Colliery F.C. Ladies U10",
      "home_score": null,
      "away_score": null,
      "venue": "",
      "division": "U10 Development Yellow",
      "league": "Nottinghamshire Girls and Ladies Football League 25/26",
      "team": "Sherwood Colliery F.C. Ladies U10",
      "home_away": "away",
      "opponent": "Hucknall & Linby Harriers FC U10",
      "goals_for": null,
      "goals_against": null
    },
    {
      "id": "badc2e0e5286fe35de1b63e8cdeb5e7a",
      "date": "2025-10-05",
      "time": "10:00",
      "home_team": "Arnold Eagles F.C. Girls U14 Hurricanes",
      "away_team": "Sherwood Colliery F.C. Ladies U14",
      "home_score": 4,
      "away_score": 2,
      "venue": "",
      "division": "U14 Div 3",
      "league": "Nottinghamshire Girls and Ladies Football League 25/26",
      "team": "Sherwood Colliery F.C. Ladies U14",
      "home_away": "away",
      "opponent": "Arnold Eagles F.C. Girls U14 Hurricanes",
      "goals_for": 2,
      "goals_against": 4
    },
    {
      "id": "e672997c6ebfe01acce2f3667fde1edf",
      "date": "2025-09-28",
      "time": "14:30",
      "home_team": "Sherwood Colliery FC Ladies",
      "away_team": "Priory Celtic FC Ladies First Team",
      "home_score": 3,
      "away_score": 2,
      "venue": "",
      "division": "Seniors Div 2",
      "league": "Nottinghamshire Girls and Ladies Football League 25/26",
      "team": "Sherwood Colliery FC Ladies",
      "home_away": "home",
      "opponent": "Priory Celtic FC Ladies First Team",
      "goals_for": 3,
      "goals_against": 2
    },
    {
      "id": "5713d67b22359957a66bfb01dfa5fd06",
      "date": "2025-09-28",
      "time": "14:00",
      "home_team": "Sherwood Colliery F.C. Ladies U14",
      "away_team": "Priory Celtic F.C. U14 Girls",
      "home_score": 3,
      "away_score": 2,
      "venue": "",
      "division": "U14 Div 3",
      "league": "Nottinghamshire Girls and Ladies Football League 25/26",
      "team": "Sherwood Colliery F.C. Ladies U14",
      "home_away": "home",
      "opponent": "Priory Celtic F.C. U14 Girls",
      "goals_for": 3,
      "goals_against": 2
    },
    {
      "id": "91d2920f8ae44ec9906bff7484782ac6",
      "date": "2025-09-28",
      "time": "12:30",
      "home_team": "Sherwood Colliery F.C. Ladies U12 Black",
      "away_team": "Eastwood CFC U12 Girls",
      "home_score": 1,
      "away_score": 3,
      "venue": "",
      "division": "U12",
      "league": "Nottinghamshire Girls and Ladies Football League 25/26",
      "team": "Sherwood Colliery F.C. Ladies U12 Black",
      "home_away": "home",
      "opponent": "Eastwood CFC U12 Girls",
      "goals_for": 1,
      "goals_against": 3
    },
    {
      "id": "9139c598650a577a7685a6f7d15642e2",
      "date": "2025-09-28",
      "time": "12:30",
      "home_team": "Sherwood Colliery F.C. Ladies U12 Blue",
      "away_team": "Ollerton Town Community FC U12 Girls",
      "home_score": 1,
      "away_score": 2,
      "venue": "",
      "division": "U12",
      "league": "Nottinghamshire Girls and Ladies Football League 25/26",
      "team": "Sherwood Colliery F.C. Ladies U12 Blue",
      "home_away": "home",
      "opponent": "Ollerton Town Community FC U12 Girls",
      "goals_for": 1,
      "goals_against": 2
    },
    {
      "id": "14dcb834027ccfba3d37b707db990a43",
      "date": "2025-09-28",
      "time": "11:15",
      "home_team": "Sherwood Colliery F.C. Ladies U11",
      "away_team": "Nottingham F.C. Youth U11 Girls",
      "home_score": null,
      "away_score": null,
      "venue": "",
      "division": "U11 Development Blue",
      "league": "Nottinghamshire Girls and Ladies Football League 25/26",
      "team": "Sherwood Colliery F.C. Ladies U11",
      "home_away": "home",
      "opponent": "Nottingham F.C. Youth U11 Girls",
      "goals_for": null,
      "goals_against": null
    },
    {
      "id": "ef37798e583bce288cc452ada5d43d38",
      "date": "2025-09-28",
      "time": "10:30",
      "home_team": "Sherwood Colliery F.C. Ladies U15",
      "away_team": "Bottesford U15 Girls",
      "home_score": 8,
      "away_score": 4,
      "venue": "",
      "division": "U15 Div 2",
      "league": "Nottinghamshire Girls and Ladies Football League 25/26",
      "team": "Sherwood Colliery F.C. Ladies U15",
      "home_away": "home",
      "opponent": "Bottesford U15 Girls",
      "goals_for": 8,
      "goals_against": 4
    },
    {
      "id": "db8c66e916c413418d8b0fe398efbc12",
      "date": "2025-09-21",
      "time": "13:30",
      "home_team": "Lowdham Colts FC Ladies",
      "away_team": "Sherwood Colliery FC Ladies",
      "home_score": 6,
      "away_score": 2,
      "venue": "",
      "division": "Women's County Cup",
      "league": "Nottinghamshire Girls and Ladies Football League 25/26",
      "team": "Sherwood Colliery FC Ladies",
      "home_away": "away",
      "opponent": "Lowdham Colts FC Ladies",
      "goals_for": 2,
      "goals_against": 6
    },
    {
      "id": "00aa122d6843e117eada826b451eb1ce",
      "date": "2025-09-21",
      "time": "11:45",
      "home_team": "Bingham Town F.C. U12 Girls Blue",
      "away_team": "Sherwood Colliery F.C. Ladies U12 Blue",
      "home_score": 2,
      "away_score": 1,
      "venue": "",
      "division": "U12",
      "league": "Nottinghamshire Girls and Ladies Football League 25/26",
      "team": "Sherwood Colliery F.C. Ladies U12 Blue",
      "home_away": "away",
      "opponent": "Bingham Town F.C. U12 Girls Blue",
      "goals_for": 1,
      "goals_against": 2
    },
    {
      "id": "7d0102bdeb5d22c1c07b0c303f7a158f",
      "date": "2025-09-21",
      "time": "11:00",
      "home_team": "Gedling Southbank FC U10 Wolves",
      "away_team": "Sherwood Colliery F.C. Ladies U10",
      "home_score": null,
      "away_score": null,
      "venue": "",
      "division": "U10 Development Yellow",
      "league": "Nottinghamshire Girls and Ladies Football League 25/26",
      "team": "Sherwood Colliery F.C. Ladies U10",
      "home_away": "away",
      "opponent": "Gedling Southbank FC U10 Wolves",
      "goals_for": null,
      "goals_against": null
    },
    {
      "id": "e79035fb87032edf36e20f3d7abf891d",
      "date": "2025-09-21",
      "time": "10:00",
      "home_team": "Priory Celtic F.C. U11 Lionesses",
      "away_team": "Sherwood Colliery F.C. Ladies U11",
      "home_score": null,
      "away_score": null,
      "venue": "",
      "division": "U11 Development Blue",
      "league": "Nottinghamshire Girls and Ladies Football League 25/26",
      "team": "Sherwood Colliery F.C. Ladies U11",
      "home_away": "away",
      "opponent": "Priory Celtic F.C. U11 Lionesses",
      "goals_for": null,
      "goals_against": null
    },
    {
      "id": "832ece73e84570756ee33b2bd5b31519",
      "date": "2025-09-21",
      "time": "10:00",
      "home_team": "Eastwood CFC U12 Girls",
      "away_team": "Sherwood Colliery F.C. Ladies U12 Black",
      "home_score": 0,
      "away_score": 0,
      "venue": "",
      "division": "U12",
      "league": "Nottinghamshire Girls and Ladies Football League 25/26",
      "team": "Sherwood Colliery F.C. Ladies U12 Black",
      "home_away": "away",
      "opponent": "Eastwood CFC U12 Girls",
      "goals_for": 0,
      "goals_against": 0
    },
    {
      "id": "b084674b1a1fa12bfc1b8e6c61072cc0",
      "date": "2025-09-21",
      "time": "10:00",
      "home_team": "Ravenshead Reds F.C. Youth U14",
      "away_team": "Sherwood Colliery F.C. Ladies U14",
      "home_score": 1,
      "away_score": 1,
      "venue": "",
      "division": "U14 Div 3",
      "league": "Nottinghamshire Girls and Ladies Football League 25/26",
      "team": "Sherwood Colliery F.C. Ladies U14",
      "home_away": "away",
      "opponent": "Ravenshead Reds F.C. Youth U14",
      "goals_for": 1,
      "goals_against": 1
    },
    {
      "id": "3037c04a020805f97efef94d8364ed5e",
      "date": "2025-09-14",
      "time": "14:00",
      "home_team": "Sherwood Colliery FC Ladies",
      "away_team": "Retford FC Ladies",
      "home_score": 4,
      "away_score": 2,
      "venue": "",
      "division": "Seniors Div 2",
      "league": "Nottinghamshire Girls and Ladies Football League 25/26",
      "team": "Sherwood Colliery FC Ladies",
      "home_away": "home",
      "opponent": "Retford FC Ladies",
      "goals_for": 4,
      "goals_against": 2
    },
    {
      "id": "3f15ff1f605a6667e8e47dcd58612a7c",
      "date": "2025-09-14",
      "time": "12:30",
      "home_team": "Sherwood Colliery F.C. Ladies U12 Black",
      "away_team": "Phoenix Inham F.C. U12 Sparkles",
      "home_score": 4,
      "away_score": 6,
      "venue": "",
      "division": "U12",
      "league": "Nottinghamshire Girls and Ladies Football League 25/26",
      "team": "Sherwood Colliery F.C. Ladies U12 Black",
      "home_away": "home",
      "opponent": "Phoenix Inham F.C. U12 Sparkles",
      "goals_for": 4,
      "goals_against": 6
    },
    {
      "id": "541d0a906cf4d22a1eaa0bafc1bcebb8",
      "date": "2025-09-14",
      "time": "12:30",
      "home_team": "Sherwood Colliery F.C. Ladies U12 Blue",
      "away_team": "Matlock Town Junior U12 Girls Gladiators",
      "home_score": 3,
      "away_score": 0,
      "venue": "",
      "division": "U12",
      "league": "Nottinghamshire Girls and Ladies Football League 25/26",
      "team": "Sherwood Colliery F.C. Ladies U12 Blue",
      "home_away": "home",
      "opponent": "Matlock Town Junior U12 Girls Gladiators",
      "goals_for": 3,
      "goals_against": 0
    },
    {
      "id": "61b2013b5880591be8a1fa55c65bada6",
      "date": "2025-09-14",
      "time": "11:00",
      "home_team": "Sherwood Colliery F.C. Ladies U15",
      "away_team": "Willow Wanderers F.C. Youth U15 Amazons",
      "home_score": 2,
      "away_score": 1,
      "venue": "",
      "division": "U15 Div 2",
      "league": "Nottinghamshire Girls and Ladies Football League 25/26",
      "team": "Sherwood Colliery F.C. Ladies U15",
      "home_away": "home",
      "opponent": "Willow Wanderers F.C. Youth U15 Amazons",
      "goals_for": 2,
      "goals_against": 1
    },
    {
      "id": "6a2d2b66493e41bcfcc7eb3628c64447",
      "date": "2025-09-14",
      "time": "10:00",
      "home_team": "Arnold Town FC U10 Girls",
      "away_team": "Sherwood Colliery F.C. Ladies U10",
      "home_score": null,
      "away_score": null,
      "venue": "",
      "division": "U10 Development Yellow",
      "league": "Nottinghamshire Girls and Ladies Football League 25/26",
      "team": "Sherwood Colliery F.C. Ladies U10",
      "home_away": "away",
      "opponent": "Arnold Town FC U10 Girls",
      "goals_for": null,
      "goals_against": null
    },
    {
      "id": "2fcc64f6442a9d10092b98e7efe79d6f",
      "date": "2025-09-07",
      "time": "12:30",
      "home_team": "Sherwood Colliery F.C. Ladies U14",
      "away_team": "Gedling Southbank FC U14 Reds",
      "home_score": 6,
      "away_score": 2,
      "venue": "",
      "division": "U14 Div 3",
      "league": "Nottinghamshire Girls and Ladies Football League 25/26",
      "team": "Sherwood Colliery F.C. Ladies U14",
      "home_away": "home",
      "opponent": "Gedling Southbank FC U14 Reds",
      "goals_for": 6,
      "goals_against": 2
    },
    {
      "id": "c9bc81b45c67da85cd8823b74ba8c9d2",
      "date": "2025-09-07",
      "time": "11:15",
      "home_team": "Sherwood Colliery F.C. Ladies U11",
      "away_team": "Matlock Town Juniors U11 Girls",
      "home_score": null,
      "away_score": null,
      "venue": "",
      "division": "U11 Development Blue",
      "league": "Nottinghamshire Girls and Ladies Football League 25/26",
      "team": "Sherwood Colliery F.C. Ladies U11",
      "home_away": "home",
      "opponent": "Matlock Town Juniors U11 Girls",
      "goals_for": null,
      "goals_against": null
    },
    {
      "id": "b0ee28ed59d59214b831b8c8178955a4",
      "date": "2025-09-07",
      "time": "10:00",
      "home_team": "Muskham Cougars F.C. Youth U12",
      "away_team": "Sherwood Colliery F.C. Ladies U12 Black",
      "home_score": 0,
      "away_score": 2,
      "venue": "",
      "division": "U12",
      "league": "Nottinghamshire Girls and Ladies Football League 25/26",
      "team": "Sherwood Colliery F.C. Ladies U12 Black",
      "home_away": "away",
      "opponent": "Muskham Cougars F.C. Youth U12",
      "goals_for": 2,
      "goals_against": 0
    },
    {
      "id": "32f90ca0b61088120256bc2e8045b66b",
      "date": "2025-09-07",
      "time": "10:00",
      "home_team": "Hilton Harriers U15 Girls Sunday",
      "away_team": "Sherwood Colliery F.C. Ladies U15",
      "home_score": 3,
      "away_score": 3,
      "venue": "",
      "division": "U15 Div 2",
      "league": "Nottinghamshire Girls and Ladies Football League 25/26",
      "team": "Sherwood Colliery F.C. Ladies U15",
      "home_away": "away",
      "opponent": "Hilton Harriers U15 Girls Sunday",
      "goals_for": 3,
      "goals_against": 3
    },
    {
      "id": "fdcfbfdfc899dbf97e1df8afba445c6a",
      "date": "2025-09-07",
      "time": "09:45",
      "home_team": "Sherwood Colliery F.C. Ladies U10",
      "away_team": "Arnold Eagles F.C. Girls U10 Wizards",
      "home_score": null,
      "away_score": null,
      "venue": "",
      "division": "U10 Development Yellow",
      "league": "Nottinghamshire Girls and Ladies Football League 25/26",
      "team": "Sherwood Colliery F.C. Ladies U10",
      "home_away": "home",
      "opponent": "Arnold Eagles F.C. Girls U10 Wizards",
      "goals_for": null,
      "goals_against": null
    }
  ]
}