{
  "club": "South Normanton",
  "generated": "2026-04-11T06:48:24Z",
  "fixtures": [
    {
      "id": "76dfb18f01da224a647b21f7d22fcf5a",
      "date": "2026-04-15",
      "time": "18:30",
      "home_team": "Riverside FC Panthers U13",
      "away_team": "South Normanton Ath Blue U13",
      "venue": "West Park Long Eaton NG10 4AA",
      "division": "U13 Sun Spring Div 6",
      "league": "YEL East Midlands Sunday 25/26",
      "team": "South Normanton Ath Blue U13",
      "home_away": "away",
      "opponent": "Riverside FC Panthers U13"
    },
    {
      "id": "f443f53c9e0e3a3eb5e985a552446b6e",
      "date": "2026-04-18",
      "time": "10:00",
      "home_team": "South Normanton Athletic U13",
      "away_team": "WBYFC Galaxy U13",
      "venue": "South Street Rec DE55 2DA",
      "division": "U13 Sat Spring Div 2 Blue",
      "league": "YEL East Midlands Saturday 25/26",
      "team": "South Normanton Athletic U13",
      "home_away": "home",
      "opponent": "WBYFC Galaxy U13"
    },
    {
      "id": "8b4c6e1b3fd6ce9232166b087b1e3713",
      "date": "2026-04-19",
      "time": "10:30",
      "home_team": "Breaston Park Green U13",
      "away_team": "South Normanton Ath Blue U13",
      "venue": "Wilsthorpe high school NG10 4WT",
      "division": "U13 Sun Spring Div 6",
      "league": "YEL East Midlands Sunday 25/26",
      "team": "South Normanton Ath Blue U13",
      "home_away": "away",
      "opponent": "Breaston Park Green U13"
    },
    {
      "id": "702309be8ff8785d87300b5886c0b36d",
      "date": "2026-04-25",
      "time": "11:00",
      "home_team": "AFC Chellaston Rams U13",
      "away_team": "South Normanton Athletic U13",
      "venue": "Chaddesden Park DE21 6LA",
      "division": "U13 Sat Spring Div 2 Blue",
      "league": "YEL East Midlands Saturday 25/26",
      "team": "South Normanton Athletic U13",
      "home_away": "away",
      "opponent": "AFC Chellaston Rams U13"
    },
    {
      "id": "39eca744827f348db726635bee6203c1",
      "date": "2026-04-26",
      "time": "11:00",
      "home_team": "South Normanton Ath Blue U13",
      "away_team": "Breaston Park Green U13",
      "venue": "South Street Recreation Ground DE55 2BZ",
      "division": "U13 Sunday",
      "league": "YEL East Midlands Sunday 25/26",
      "team": "South Normanton Ath Blue U13",
      "home_away": "home",
      "opponent": "Breaston Park Green U13"
    }
  ],
  "results": [
    {
      "id": "9abcba115cf1fa3f3d7f4c35cf8aea81",
      "date": "2026-03-28",
      "time": "11:00",
      "home_team": "Repton Casuals U13",
      "away_team": "South Normanton Athletic U13",
      "home_score": 4,
      "away_score": 2,
      "venue": "",
      "division": "U13 Sat Spring Div 2 Blue",
      "league": "YEL East Midlands Saturday 25/26",
      "team": "South Normanton Athletic U13",
      "home_away": "away",
      "opponent": "Repton Casuals U13",
      "goals_for": 2,
      "goals_against": 4
    },
    {
      "id": "143a2f08c16cebae697c5f937ab62005",
      "date": "2026-03-22",
      "time": "11:00",
      "home_team": "South Normanton Ath Blue U13",
      "away_team": "Clipstone Welfare Porto U13",
      "home_score": 0,
      "away_score": 2,
      "venue": "",
      "division": "U13 Sun Spring Div 6",
      "league": "YEL East Midlands Sunday 25/26",
      "team": "South Normanton Ath Blue U13",
      "home_away": "home",
      "opponent": "Clipstone Welfare Porto U13",
      "goals_for": 0,
      "goals_against": 2
    },
    {
      "id": "078272d2ebc68ff9fd15f813b4b38699",
      "date": "2026-03-21",
      "time": "11:00",
      "home_team": "South Normanton Athletic U13",
      "away_team": "Mickleover Jnrs Benfica U13",
      "home_score": 0,
      "away_score": 4,
      "venue": "",
      "division": "U13 Sat Spring Div 2 Blue",
      "league": "YEL East Midlands Saturday 25/26",
      "team": "South Normanton Athletic U13",
      "home_away": "home",
      "opponent": "Mickleover Jnrs Benfica U13",
      "goals_for": 0,
      "goals_against": 4
    },
    {
      "id": "5952b5384bcc164b4fb19bce28010247",
      "date": "2026-03-14",
      "time": "11:00",
      "home_team": "South Normanton Athletic U13",
      "away_team": "Hilton Harriers Cobras U13",
      "home_score": 1,
      "away_score": 7,
      "venue": "",
      "division": "U13 Sat Spring Div 2 Blue",
      "league": "YEL East Midlands Saturday 25/26",
      "team": "South Normanton Athletic U13",
      "home_away": "home",
      "opponent": "Hilton Harriers Cobras U13",
      "goals_for": 1,
      "goals_against": 7
    },
    {
      "id": "2a1a66f8338214b84ed64a29e409c82e",
      "date": "2026-03-08",
      "time": "11:00",
      "home_team": "South Normanton Ath Blue U13",
      "away_team": "Castle Don Hawks U13",
      "home_score": 0,
      "away_score": 5,
      "venue": "",
      "division": "U13 Sun Spring Div 6",
      "league": "YEL East Midlands Sunday 25/26",
      "team": "South Normanton Ath Blue U13",
      "home_away": "home",
      "opponent": "Castle Don Hawks U13",
      "goals_for": 0,
      "goals_against": 5
    },
    {
      "id": "8da20c1ca49c6f9be84c44b51316950f",
      "date": "2026-03-07",
      "time": "10:00",
      "home_team": "Duffield Dynamo United U13",
      "away_team": "South Normanton Athletic U13",
      "home_score": 1,
      "away_score": 3,
      "venue": "",
      "division": "U13 Sat Spring Div 2 Blue",
      "league": "YEL East Midlands Saturday 25/26",
      "team": "South Normanton Athletic U13",
      "home_away": "away",
      "opponent": "Duffield Dynamo United U13",
      "goals_for": 3,
      "goals_against": 1
    },
    {
      "id": "b81aee920789866deb1671c3a34d356b",
      "date": "2026-02-01",
      "time": "11:00",
      "home_team": "South Normanton Ath Blue U13",
      "away_team": "DJFC U13",
      "home_score": 0,
      "away_score": 8,
      "venue": "",
      "division": "U13 Sun Spring Div 6",
      "league": "YEL East Midlands Sunday 25/26",
      "team": "South Normanton Ath Blue U13",
      "home_away": "home",
      "opponent": "DJFC U13",
      "goals_for": 0,
      "goals_against": 8
    },
    {
      "id": "1448cfd4427f07c28e063ce0a3da63fa",
      "date": "2026-01-31",
      "time": "11:00",
      "home_team": "Repton Casuals U13",
      "away_team": "South Normanton Athletic U13",
      "home_score": 3,
      "away_score": 0,
      "venue": "",
      "division": "U13 Sat YEL Trophy",
      "league": "YEL East Midlands Saturday 25/26",
      "team": "South Normanton Athletic U13",
      "home_away": "away",
      "opponent": "Repton Casuals U13",
      "goals_for": 0,
      "goals_against": 3
    },
    {
      "id": "8a5811a6180c29a42e1ce28c2041b5b9",
      "date": "2026-01-24",
      "time": "11:00",
      "home_team": "South Normanton Athletic U13",
      "away_team": "Silva FC Rushcliffe Black U13",
      "home_score": 3,
      "away_score": 1,
      "venue": "",
      "division": "U13 Sat Spring Div 2 Blue",
      "league": "YEL East Midlands Saturday 25/26",
      "team": "South Normanton Athletic U13",
      "home_away": "home",
      "opponent": "Silva FC Rushcliffe Black U13",
      "goals_for": 3,
      "goals_against": 1
    },
    {
      "id": "2f9e910b3516aac8f77bca6842b244ec",
      "date": "2026-01-18",
      "time": "11:00",
      "home_team": "South Normanton Ath Blue U13",
      "away_team": "Teversal FC U13",
      "home_score": 0,
      "away_score": 1,
      "venue": "",
      "division": "U13 Sun Spring Div 6",
      "league": "YEL East Midlands Sunday 25/26",
      "team": "South Normanton Ath Blue U13",
      "home_away": "home",
      "opponent": "Teversal FC U13",
      "goals_for": 0,
      "goals_against": 1
    },
    {
      "id": "5dba8c580466309af1dcaeea4853dcda",
      "date": "2025-12-14",
      "time": "11:00",
      "home_team": "South Normanton Ath Blue U13",
      "away_team": "Mansfield Athletic U13",
      "home_score": 0,
      "away_score": 5,
      "venue": "",
      "division": "U13 Sun YEL Challenge Trophy",
      "league": "YEL East Midlands Sunday 25/26",
      "team": "South Normanton Ath Blue U13",
      "home_away": "home",
      "opponent": "Mansfield Athletic U13",
      "goals_for": 0,
      "goals_against": 5
    },
    {
      "id": "370fc2a91f8bb209e0ce376765582d02",
      "date": "2025-12-13",
      "time": "09:30",
      "home_team": "Duffield Dynamo United U13",
      "away_team": "South Normanton Athletic U13",
      "home_score": 2,
      "away_score": 3,
      "venue": "",
      "division": "U13 Sat YEL Trophy",
      "league": "YEL East Midlands Saturday 25/26",
      "team": "South Normanton Athletic U13",
      "home_away": "away",
      "opponent": "Duffield Dynamo United U13",
      "goals_for": 3,
      "goals_against": 2
    },
    {
      "id": "a2df8aeb9b326f6ea600b121ba549ff3",
      "date": "2025-12-06",
      "time": "11:00",
      "home_team": "G3A FC Benfica U13",
      "away_team": "South Normanton Athletic U13",
      "home_score": 10,
      "away_score": 4,
      "venue": "",
      "division": "U13 Sat Winter Div 2 Red",
      "league": "YEL East Midlands Saturday 25/26",
      "team": "South Normanton Athletic U13",
      "home_away": "away",
      "opponent": "G3A FC Benfica U13",
      "goals_for": 4,
      "goals_against": 10
    },
    {
      "id": "b7631f3b086808d97526981154c67cb0",
      "date": "2025-11-23",
      "time": "10:45",
      "home_team": "Riverside FC Panthers U13",
      "away_team": "South Normanton Ath Blue U13",
      "home_score": 3,
      "away_score": 2,
      "venue": "",
      "division": "U13 Sun Winter Div 6",
      "league": "YEL East Midlands Sunday 25/26",
      "team": "South Normanton Ath Blue U13",
      "home_away": "away",
      "opponent": "Riverside FC Panthers U13",
      "goals_for": 2,
      "goals_against": 3
    },
    {
      "id": "4f2e1106df2417906d4eb92fea2bf2a0",
      "date": "2025-11-16",
      "time": "11:00",
      "home_team": "South Normanton Ath Blue U13",
      "away_team": "Robin Hood Colts Red U13",
      "home_score": 0,
      "away_score": 9,
      "venue": "",
      "division": "U13 Sun Winter Div 6",
      "league": "YEL East Midlands Sunday 25/26",
      "team": "South Normanton Ath Blue U13",
      "home_away": "home",
      "opponent": "Robin Hood Colts Red U13",
      "goals_for": 0,
      "goals_against": 9
    },
    {
      "id": "a48ae83d4273b9d90eed7c32468cef94",
      "date": "2025-11-08",
      "time": "10:00",
      "home_team": "Quarrydale United U13",
      "away_team": "South Normanton Athletic U13",
      "home_score": 2,
      "away_score": 5,
      "venue": "",
      "division": "U13 Sat Winter Div 2 Red",
      "league": "YEL East Midlands Saturday 25/26",
      "team": "South Normanton Athletic U13",
      "home_away": "away",
      "opponent": "Quarrydale United U13",
      "goals_for": 5,
      "goals_against": 2
    },
    {
      "id": "beb43fa49e60114e805442cc8920185c",
      "date": "2025-10-25",
      "time": "11:00",
      "home_team": "South Normanton Athletic U13",
      "away_team": "Sandiacre Town Sharks U13",
      "home_score": 5,
      "away_score": 1,
      "venue": "",
      "division": "U13 Saturday",
      "league": "YEL East Midlands Saturday 25/26",
      "team": "South Normanton Athletic U13",
      "home_away": "home",
      "opponent": "Sandiacre Town Sharks U13",
      "goals_for": 5,
      "goals_against": 1
    },
    {
      "id": "41f4db015ae2f89d150d925a14b1c41f",
      "date": "2025-10-18",
      "time": "10:00",
      "home_team": "Market Warsop Colts U13",
      "away_team": "South Normanton Athletic U13",
      "home_score": 2,
      "away_score": 4,
      "venue": "",
      "division": "U13 Saturday",
      "league": "YEL East Midlands Saturday 25/26",
      "team": "South Normanton Athletic U13",
      "home_away": "away",
      "opponent": "Market Warsop Colts U13",
      "goals_for": 4,
      "goals_against": 2
    },
    {
      "id": "7f98cab7a8f79226b56052edfddf48e9",
      "date": "2025-10-12",
      "time": "11:00",
      "home_team": "South Normanton Ath Blue U13",
      "away_team": "Gonerby Blue U13",
      "home_score": 0,
      "away_score": 7,
      "venue": "",
      "division": "U13 Sun Winter Div 6",
      "league": "YEL East Midlands Sunday 25/26",
      "team": "South Normanton Ath Blue U13",
      "home_away": "home",
      "opponent": "Gonerby Blue U13",
      "goals_for": 0,
      "goals_against": 7
    },
    {
      "id": "b60cc6899a7b0eb4607cf1719cc513a7",
      "date": "2025-10-11",
      "time": "11:00",
      "home_team": "South Normanton Athletic U13",
      "away_team": "Willow Wanderers Wolves U13",
      "home_score": 1,
      "away_score": 1,
      "venue": "",
      "division": "U13 Sat Winter Div 2 Red",
      "league": "YEL East Midlands Saturday 25/26",
      "team": "South Normanton Athletic U13",
      "home_away": "home",
      "opponent": "Willow Wanderers Wolves U13",
      "goals_for": 1,
      "goals_against": 1
    },
    {
      "id": "04c8dbd40f25633ac9792da808847860",
      "date": "2025-10-04",
      "time": "11:00",
      "home_team": "FC Cavaliers U13",
      "away_team": "South Normanton Athletic U13",
      "home_score": 1,
      "away_score": 3,
      "venue": "",
      "division": "U13 Sat Winter Div 2 Red",
      "league": "YEL East Midlands Saturday 25/26",
      "team": "South Normanton Athletic U13",
      "home_away": "away",
      "opponent": "FC Cavaliers U13",
      "goals_for": 3,
      "goals_against": 1
    },
    {
      "id": "24125108ace8861e772478cea3f98e34",
      "date": "2025-09-28",
      "time": "11:00",
      "home_team": "South Normanton Ath Blue U13",
      "away_team": "Clipstone Welfare Porto U13",
      "home_score": 0,
      "away_score": 2,
      "venue": "",
      "division": "U13 Sun Winter Div 6",
      "league": "YEL East Midlands Sunday 25/26",
      "team": "South Normanton Ath Blue U13",
      "home_away": "home",
      "opponent": "Clipstone Welfare Porto U13",
      "goals_for": 0,
      "goals_against": 2
    },
    {
      "id": "8ce3b8a79df3ca1c3dea283cde76f3c7",
      "date": "2025-09-27",
      "time": "11:00",
      "home_team": "South Normanton Athletic U13",
      "away_team": "G3A FC Juve U13",
      "home_score": 7,
      "away_score": 2,
      "venue": "",
      "division": "U13 Sat Winter Div 2 Red",
      "league": "YEL East Midlands Saturday 25/26",
      "team": "South Normanton Athletic U13",
      "home_away": "home",
      "opponent": "G3A FC Juve U13",
      "goals_for": 7,
      "goals_against": 2
    },
    {
      "id": "aaa26ab62b71a6cbc041200b837dd006",
      "date": "2025-09-21",
      "time": "10:00",
      "home_team": "Pegasus FC U13",
      "away_team": "South Normanton Ath Blue U13",
      "home_score": 8,
      "away_score": 1,
      "venue": "",
      "division": "U13 Sun Winter Div 6",
      "league": "YEL East Midlands Sunday 25/26",
      "team": "South Normanton Ath Blue U13",
      "home_away": "away",
      "opponent": "Pegasus FC U13",
      "goals_for": 1,
      "goals_against": 8
    },
    {
      "id": "09751a09fe3a428b531f1a39a8be9a74",
      "date": "2025-09-20",
      "time": "10:00",
      "home_team": "Market Warsop Stags U13",
      "away_team": "South Normanton Athletic U13",
      "home_score": 4,
      "away_score": 1,
      "venue": "",
      "division": "U13 Sat Winter Div 2 Red",
      "league": "YEL East Midlands Saturday 25/26",
      "team": "South Normanton Athletic U13",
      "home_away": "away",
      "opponent": "Market Warsop Stags U13",
      "goals_for": 1,
      "goals_against": 4
    },
    {
      "id": "f041dba77894859b18e30bc71a2e02bb",
      "date": "2025-09-14",
      "time": "11:00",
      "home_team": "Breaston Park Green U13",
      "away_team": "South Normanton Ath Blue U13",
      "home_score": 9,
      "away_score": 0,
      "venue": "",
      "division": "U13 Sun Winter Div 6",
      "league": "YEL East Midlands Sunday 25/26",
      "team": "South Normanton Ath Blue U13",
      "home_away": "away",
      "opponent": "Breaston Park Green U13",
      "goals_for": 0,
      "goals_against": 9
    },
    {
      "id": "29f2839a69b10681675da5cc79e473e5",
      "date": "2025-09-13",
      "time": "11:00",
      "home_team": "South Normanton Athletic U13",
      "away_team": "Repton Casuals U13",
      "home_score": 2,
      "away_score": 3,
      "venue": "",
      "division": "U13 Saturday",
      "league": "YEL East Midlands Saturday 25/26",
      "team": "South Normanton Athletic U13",
      "home_away": "home",
      "opponent": "Repton Casuals U13",
      "goals_for": 2,
      "goals_against": 3
    },
    {
      "id": "f77b116a9d523650975aab20480e2022",
      "date": "2025-09-07",
      "time": "11:00",
      "home_team": "South Normanton Ath Blue U13",
      "away_team": "Barrowby Junior Black U13",
      "home_score": 0,
      "away_score": 4,
      "venue": "",
      "division": "U13 Sunday",
      "league": "YEL East Midlands Sunday 25/26",
      "team": "South Normanton Ath Blue U13",
      "home_away": "home",
      "opponent": "Barrowby Junior Black U13",
      "goals_for": 0,
      "goals_against": 4
    }
  ]
}