{
  "club": "Winthorpe & Cod T",
  "generated": "2026-05-04T08:16:50Z",
  "fixtures": [
    {
      "id": "2c19cbecd0f35696609a0d1d2f11b1f2",
      "date": "2026-05-16",
      "time": "10:00",
      "home_team": "DLFC Orange U11",
      "away_team": "Winthorpe & Cod T Amber U11",
      "venue": "Norman Archer Memorial Ground NG11 9AZ",
      "division": "U11 Sat YEL Foundation Shield",
      "league": "YEL East Midlands Saturday 25/26",
      "team": "Winthorpe & Cod T Amber U11",
      "home_away": "away",
      "opponent": "DLFC Orange U11"
    },
    {
      "id": "6d489726036935f0065b6fc312d10870",
      "date": "2026-05-16",
      "time": "12:00",
      "home_team": "WBYFC Mustangs U11",
      "away_team": "Winthorpe & Cod T Black U11",
      "venue": "Norman Archer Memorial Ground NG11 9AZ",
      "division": "U11 Sat YEL Challenge Trophy",
      "league": "YEL East Midlands Saturday 25/26",
      "team": "Winthorpe & Cod T Black U11",
      "home_away": "away",
      "opponent": "WBYFC Mustangs U11"
    }
  ],
  "results": [
    {
      "id": "07d4c0631fa6f97feb852122e93a3109",
      "date": "2026-04-28",
      "time": "18:15",
      "home_team": "Newark Town Saxons U11",
      "away_team": "Winthorpe & Cod T Amber U11",
      "home_score": 1,
      "away_score": 1,
      "venue": "",
      "division": "U11 Sat Spring Div 8",
      "league": "YEL East Midlands Saturday 25/26",
      "team": "Winthorpe & Cod T Amber U11",
      "home_away": "away",
      "opponent": "Newark Town Saxons U11",
      "goals_for": 1,
      "goals_against": 1
    },
    {
      "id": "27a965875b0600e50da9364ae3822c74",
      "date": "2026-04-25",
      "time": "11:30",
      "home_team": "Winthorpe & Cod T Amber U11",
      "away_team": "Nottingham Second Chance U11",
      "home_score": 2,
      "away_score": 1,
      "venue": "",
      "division": "U11 Sat YEL Foundation Shield",
      "league": "YEL East Midlands Saturday 25/26",
      "team": "Winthorpe & Cod T Amber U11",
      "home_away": "home",
      "opponent": "Nottingham Second Chance U11",
      "goals_for": 2,
      "goals_against": 1
    },
    {
      "id": "011976de673ed7e92ad7c11f98e9f6ca",
      "date": "2026-04-25",
      "time": "11:00",
      "home_team": "Winthorpe & Cod T Black U12",
      "away_team": "Radcliffe Olympic Red U12",
      "home_score": 3,
      "away_score": 2,
      "venue": "",
      "division": "U12 Sat Spring Div 2 Red",
      "league": "YEL East Midlands Saturday 25/26",
      "team": "Winthorpe & Cod T Black U12",
      "home_away": "home",
      "opponent": "Radcliffe Olympic Red U12",
      "goals_for": 3,
      "goals_against": 2
    },
    {
      "id": "e10b3ed55cb719e5da3f19238dce3376",
      "date": "2026-04-25",
      "time": "10:00",
      "home_team": "Hucknall Sports White U9",
      "away_team": "Winthorpe & Cod T Amber U9",
      "home_score": 3,
      "away_score": 3,
      "venue": "",
      "division": "U9 Sat Spring Div 7 Red",
      "league": "YEL East Midlands Saturday 25/26",
      "team": "Winthorpe & Cod T Amber U9",
      "home_away": "away",
      "opponent": "Hucknall Sports White U9",
      "goals_for": 3,
      "goals_against": 3
    },
    {
      "id": "cff3b4c1d1c94555de88dfae0b95fe7d",
      "date": "2026-04-25",
      "time": "10:00",
      "home_team": "Winthorpe & Cod T Black U11",
      "away_team": "Sherwood FC Red U11",
      "home_score": 4,
      "away_score": 3,
      "venue": "",
      "division": "U11 Sat YEL Challenge Trophy",
      "league": "YEL East Midlands Saturday 25/26",
      "team": "Winthorpe & Cod T Black U11",
      "home_away": "home",
      "opponent": "Sherwood FC Red U11",
      "goals_for": 4,
      "goals_against": 3
    },
    {
      "id": "e16f351f93feb0a4cb3a91f5b17d2fb6",
      "date": "2026-04-25",
      "time": "10:00",
      "home_team": "Bottesford Blue U10",
      "away_team": "Winthorpe & Cod T U10",
      "home_score": 3,
      "away_score": 1,
      "venue": "",
      "division": "U10 Sat Spring Div 7 Blue",
      "league": "YEL East Midlands Saturday 25/26",
      "team": "Winthorpe & Cod T U10",
      "home_away": "away",
      "opponent": "Bottesford Blue U10",
      "goals_for": 1,
      "goals_against": 3
    },
    {
      "id": "4348a3d5693e43195bcd77a00002e062",
      "date": "2026-04-25",
      "time": "09:30",
      "home_team": "Winthorpe & Cod T Black U9",
      "away_team": "Newark Brazil Corinthians U9",
      "home_score": 3,
      "away_score": 0,
      "venue": "",
      "division": "U9 Sat Spring Div 9 Blue",
      "league": "YEL East Midlands Saturday 25/26",
      "team": "Winthorpe & Cod T Black U9",
      "home_away": "home",
      "opponent": "Newark Brazil Corinthians U9",
      "goals_for": 3,
      "goals_against": 0
    },
    {
      "id": "c622189f384fb4a980cabc5123982269",
      "date": "2026-04-18",
      "time": "11:00",
      "home_team": "Winthorpe & Cod T Black U11",
      "away_team": "Southwell City Panthers U11",
      "home_score": 4,
      "away_score": 1,
      "venue": "",
      "division": "U11 Sat YEL Challenge Trophy",
      "league": "YEL East Midlands Saturday 25/26",
      "team": "Winthorpe & Cod T Black U11",
      "home_away": "home",
      "opponent": "Southwell City Panthers U11",
      "goals_for": 4,
      "goals_against": 1
    },
    {
      "id": "c70d75a439270a0d346198f06bd5960a",
      "date": "2026-04-18",
      "time": "11:00",
      "home_team": "Winthorpe & Cod T Black U12",
      "away_team": "Calverton MW Blue U12",
      "home_score": 2,
      "away_score": 5,
      "venue": "",
      "division": "U12 Sat Spring Div 2 Red",
      "league": "YEL East Midlands Saturday 25/26",
      "team": "Winthorpe & Cod T Black U12",
      "home_away": "home",
      "opponent": "Calverton MW Blue U12",
      "goals_for": 2,
      "goals_against": 5
    },
    {
      "id": "e9f06b2cfa7c7ef4e09c8ec7c4d5971e",
      "date": "2026-04-18",
      "time": "10:00",
      "home_team": "Gonerby Yellow U9",
      "away_team": "Winthorpe & Cod T Black U9",
      "home_score": 2,
      "away_score": 4,
      "venue": "",
      "division": "U9 Sat Spring Div 9 Blue",
      "league": "YEL East Midlands Saturday 25/26",
      "team": "Winthorpe & Cod T Black U9",
      "home_away": "away",
      "opponent": "Gonerby Yellow U9",
      "goals_for": 4,
      "goals_against": 2
    },
    {
      "id": "c2a1837da6869cbff01bcfb2c8bc1d7f",
      "date": "2026-04-18",
      "time": "10:00",
      "home_team": "Cotgrave FC Black U10",
      "away_team": "Winthorpe & Cod T U10",
      "home_score": null,
      "away_score": null,
      "venue": "",
      "division": "U10 Saturday",
      "league": "YEL East Midlands Saturday 25/26",
      "team": "Winthorpe & Cod T U10",
      "home_away": "away",
      "opponent": "Cotgrave FC Black U10",
      "goals_for": null,
      "goals_against": null
    },
    {
      "id": "f2602156040fe3cdc12e1bf128db4922",
      "date": "2026-04-18",
      "time": "09:30",
      "home_team": "Winthorpe & Cod T Amber U11",
      "away_team": "ATFA Brinsley Bullets U11",
      "home_score": 11,
      "away_score": 0,
      "venue": "",
      "division": "U11 Sat Spring Div 8",
      "league": "YEL East Midlands Saturday 25/26",
      "team": "Winthorpe & Cod T Amber U11",
      "home_away": "home",
      "opponent": "ATFA Brinsley Bullets U11",
      "goals_for": 11,
      "goals_against": 0
    },
    {
      "id": "853181caf60beedc2536eb88efedb268",
      "date": "2026-04-18",
      "time": "09:30",
      "home_team": "Winthorpe & Cod T Amber U9",
      "away_team": "Shirebrook Rangers Blue U9",
      "home_score": null,
      "away_score": null,
      "venue": "",
      "division": "U9 Saturday",
      "league": "YEL East Midlands Saturday 25/26",
      "team": "Winthorpe & Cod T Amber U9",
      "home_away": "home",
      "opponent": "Shirebrook Rangers Blue U9",
      "goals_for": null,
      "goals_against": null
    },
    {
      "id": "e5c5943307bb2cb5305cfe09f42fc422",
      "date": "2026-04-14",
      "time": "18:00",
      "home_team": "Southwell City Panthers U11",
      "away_team": "Winthorpe & Cod T Black U11",
      "home_score": 4,
      "away_score": 3,
      "venue": "",
      "division": "U11 Sat Spring Div 6 Red",
      "league": "YEL East Midlands Saturday 25/26",
      "team": "Winthorpe & Cod T Black U11",
      "home_away": "away",
      "opponent": "Southwell City Panthers U11",
      "goals_for": 3,
      "goals_against": 4
    },
    {
      "id": "03eaf8189e608c407647136d30098657",
      "date": "2026-03-28",
      "time": "10:00",
      "home_team": "Winthorpe & Cod T Black U9",
      "away_team": "Woodthorpe Com Fire U9",
      "home_score": 5,
      "away_score": 3,
      "venue": "",
      "division": "U9 Sat Spring Div 9 Blue",
      "league": "YEL East Midlands Saturday 25/26",
      "team": "Winthorpe & Cod T Black U9",
      "home_away": "home",
      "opponent": "Woodthorpe Com Fire U9",
      "goals_for": 5,
      "goals_against": 3
    },
    {
      "id": "7460d5bf8573cd855ab5d799ec8429a2",
      "date": "2026-03-28",
      "time": "09:30",
      "home_team": "Woodborough Celtic U10",
      "away_team": "Winthorpe & Cod T U10",
      "home_score": 4,
      "away_score": 1,
      "venue": "",
      "division": "U10 Sat Spring Div 7 Blue",
      "league": "YEL East Midlands Saturday 25/26",
      "team": "Winthorpe & Cod T U10",
      "home_away": "away",
      "opponent": "Woodborough Celtic U10",
      "goals_for": 1,
      "goals_against": 4
    },
    {
      "id": "a1908cca3700838a30315a8b391f9135",
      "date": "2026-03-28",
      "time": "09:00",
      "home_team": "Southwell City Cobras U9",
      "away_team": "Winthorpe & Cod T Amber U9",
      "home_score": 0,
      "away_score": 4,
      "venue": "",
      "division": "U9 Sat Spring Div 7 Red",
      "league": "YEL East Midlands Saturday 25/26",
      "team": "Winthorpe & Cod T Amber U9",
      "home_away": "away",
      "opponent": "Southwell City Cobras U9",
      "goals_for": 4,
      "goals_against": 0
    },
    {
      "id": "744f7aa99a8ac9045661244bfcf789d0",
      "date": "2026-03-21",
      "time": "11:00",
      "home_team": "Winthorpe & Cod T Amber U11",
      "away_team": "Newark Town Cavaliers U11",
      "home_score": null,
      "away_score": null,
      "venue": "",
      "division": "U11 Saturday",
      "league": "YEL East Midlands Saturday 25/26",
      "team": "Winthorpe & Cod T Amber U11",
      "home_away": "home",
      "opponent": "Newark Town Cavaliers U11",
      "goals_for": null,
      "goals_against": null
    },
    {
      "id": "01f1ed9e7199d071c17a0b31de4e51b0",
      "date": "2026-03-21",
      "time": "10:00",
      "home_team": "Mapperley All Stars Stripes U11",
      "away_team": "Winthorpe & Cod T Black U11",
      "home_score": null,
      "away_score": null,
      "venue": "",
      "division": "U11 Saturday",
      "league": "YEL East Midlands Saturday 25/26",
      "team": "Winthorpe & Cod T Black U11",
      "home_away": "away",
      "opponent": "Mapperley All Stars Stripes U11",
      "goals_for": null,
      "goals_against": null
    },
    {
      "id": "4cdfcbdb758b4ec591fe6e6194c9c144",
      "date": "2026-03-21",
      "time": "10:00",
      "home_team": "Hucknall Sports Red U12",
      "away_team": "Winthorpe & Cod T Black U12",
      "home_score": 4,
      "away_score": 4,
      "venue": "",
      "division": "U12 Sat Spring Div 2 Red",
      "league": "YEL East Midlands Saturday 25/26",
      "team": "Winthorpe & Cod T Black U12",
      "home_away": "away",
      "opponent": "Hucknall Sports Red U12",
      "goals_for": 4,
      "goals_against": 4
    },
    {
      "id": "c72ccce0df127e81480688d0fd979670",
      "date": "2026-03-21",
      "time": "10:00",
      "home_team": "Gonerby Blue U9",
      "away_team": "Winthorpe & Cod T Black U9",
      "home_score": 3,
      "away_score": 9,
      "venue": "",
      "division": "U9 Sat Spring Div 9 Blue",
      "league": "YEL East Midlands Saturday 25/26",
      "team": "Winthorpe & Cod T Black U9",
      "home_away": "away",
      "opponent": "Gonerby Blue U9",
      "goals_for": 9,
      "goals_against": 3
    },
    {
      "id": "a6eeac079ea422e8f50204c5be46e4d2",
      "date": "2026-03-21",
      "time": "10:00",
      "home_team": "Winthorpe & Cod T U10",
      "away_team": "Nottingham Second Chance U10",
      "home_score": 2,
      "away_score": 6,
      "venue": "",
      "division": "U10 Sat Spring Div 7 Blue",
      "league": "YEL East Midlands Saturday 25/26",
      "team": "Winthorpe & Cod T U10",
      "home_away": "home",
      "opponent": "Nottingham Second Chance U10",
      "goals_for": 2,
      "goals_against": 6
    },
    {
      "id": "a98c437476a5e8f046098db3e10b5028",
      "date": "2026-03-21",
      "time": "09:30",
      "home_team": "Winthorpe & Cod T Amber U9",
      "away_team": "AFC Warriors Hunters U9",
      "home_score": 1,
      "away_score": 4,
      "venue": "",
      "division": "U9 Sat Spring Div 7 Red",
      "league": "YEL East Midlands Saturday 25/26",
      "team": "Winthorpe & Cod T Amber U9",
      "home_away": "home",
      "opponent": "AFC Warriors Hunters U9",
      "goals_for": 1,
      "goals_against": 4
    },
    {
      "id": "79554526b386d4f63ff489494b37471f",
      "date": "2026-03-14",
      "time": "11:30",
      "home_team": "Winthorpe & Cod T Black U9",
      "away_team": "Silva FC Brunts U9",
      "home_score": 6,
      "away_score": 3,
      "venue": "",
      "division": "U9 Sat Spring Div 9 Blue",
      "league": "YEL East Midlands Saturday 25/26",
      "team": "Winthorpe & Cod T Black U9",
      "home_away": "home",
      "opponent": "Silva FC Brunts U9",
      "goals_for": 6,
      "goals_against": 3
    },
    {
      "id": "63c5d13e3ff4777ca0f15a24af274241",
      "date": "2026-03-14",
      "time": "11:15",
      "home_team": "Burton Joyce Blue U10",
      "away_team": "Winthorpe & Cod T U10",
      "home_score": null,
      "away_score": null,
      "venue": "",
      "division": "U10 Saturday",
      "league": "YEL East Midlands Saturday 25/26",
      "team": "Winthorpe & Cod T U10",
      "home_away": "away",
      "opponent": "Burton Joyce Blue U10",
      "goals_for": null,
      "goals_against": null
    },
    {
      "id": "3c6f36b664e4c599a44b7008617c5112",
      "date": "2026-03-14",
      "time": "11:00",
      "home_team": "Winthorpe & Cod T Black U12",
      "away_team": "Bagthorpe Athletic Eagles U12",
      "home_score": 2,
      "away_score": 1,
      "venue": "",
      "division": "U12 Sat Spring Div 2 Red",
      "league": "YEL East Midlands Saturday 25/26",
      "team": "Winthorpe & Cod T Black U12",
      "home_away": "home",
      "opponent": "Bagthorpe Athletic Eagles U12",
      "goals_for": 2,
      "goals_against": 1
    },
    {
      "id": "bfd03c806a5ac276a5a5e84b16011bd7",
      "date": "2026-03-14",
      "time": "10:00",
      "home_team": "Winthorpe & Cod T Amber U11",
      "away_team": "Hucknall Sports Red U11",
      "home_score": 1,
      "away_score": 1,
      "venue": "",
      "division": "U11 Sat Spring Div 8",
      "league": "YEL East Midlands Saturday 25/26",
      "team": "Winthorpe & Cod T Amber U11",
      "home_away": "home",
      "opponent": "Hucknall Sports Red U11",
      "goals_for": 1,
      "goals_against": 1
    },
    {
      "id": "d6e490f4615153ec8c2d39f1020daafe",
      "date": "2026-03-14",
      "time": "10:00",
      "home_team": "Shirebrook Rangers Blue U9",
      "away_team": "Winthorpe & Cod T Amber U9",
      "home_score": 3,
      "away_score": 1,
      "venue": "",
      "division": "U9 Sat Spring Div 7 Red",
      "league": "YEL East Midlands Saturday 25/26",
      "team": "Winthorpe & Cod T Amber U9",
      "home_away": "away",
      "opponent": "Shirebrook Rangers Blue U9",
      "goals_for": 1,
      "goals_against": 3
    },
    {
      "id": "84097b5815720152dd7c25208c0cf3fc",
      "date": "2026-03-14",
      "time": "10:00",
      "home_team": "Mapperley All Stars Blue U13",
      "away_team": "Winthorpe & Cod T U13",
      "home_score": 10,
      "away_score": 1,
      "venue": "",
      "division": "U13 Sat Spring Div 7 Red",
      "league": "YEL East Midlands Saturday 25/26",
      "team": "Winthorpe & Cod T U13",
      "home_away": "away",
      "opponent": "Mapperley All Stars Blue U13",
      "goals_for": 1,
      "goals_against": 10
    },
    {
      "id": "145540e947445401fb523d19a09bc890",
      "date": "2026-03-14",
      "time": "09:30",
      "home_team": "Winthorpe & Cod T Black U11",
      "away_team": "Sutton-on-Trent Tornadoes U11",
      "home_score": 3,
      "away_score": 2,
      "venue": "",
      "division": "U11 Sat Spring Div 6 Red",
      "league": "YEL East Midlands Saturday 25/26",
      "team": "Winthorpe & Cod T Black U11",
      "home_away": "home",
      "opponent": "Sutton-on-Trent Tornadoes U11",
      "goals_for": 3,
      "goals_against": 2
    },
    {
      "id": "3e3c7a0ed74d81757fc2403ac5f6c51e",
      "date": "2026-03-07",
      "time": "11:30",
      "home_team": "DLFC Blue U11",
      "away_team": "Winthorpe & Cod T Amber U11",
      "home_score": 1,
      "away_score": 9,
      "venue": "",
      "division": "U11 Sat Spring Div 8",
      "league": "YEL East Midlands Saturday 25/26",
      "team": "Winthorpe & Cod T Amber U11",
      "home_away": "away",
      "opponent": "DLFC Blue U11",
      "goals_for": 9,
      "goals_against": 1
    },
    {
      "id": "5c17dfb3b0790281b248711ea2445091",
      "date": "2026-03-07",
      "time": "11:30",
      "home_team": "Bingham Town Red U12",
      "away_team": "Winthorpe & Cod T Black U12",
      "home_score": 1,
      "away_score": 4,
      "venue": "",
      "division": "U12 Sat Spring Div 2 Red",
      "league": "YEL East Midlands Saturday 25/26",
      "team": "Winthorpe & Cod T Black U12",
      "home_away": "away",
      "opponent": "Bingham Town Red U12",
      "goals_for": 4,
      "goals_against": 1
    },
    {
      "id": "708b355e5783f2344f2684fde81210c0",
      "date": "2026-03-07",
      "time": "11:00",
      "home_team": "Southwell City Troopers U13",
      "away_team": "Winthorpe & Cod T U13",
      "home_score": 11,
      "away_score": 2,
      "venue": "",
      "division": "U13 Sat Spring Div 7 Red",
      "league": "YEL East Midlands Saturday 25/26",
      "team": "Winthorpe & Cod T U13",
      "home_away": "away",
      "opponent": "Southwell City Troopers U13",
      "goals_for": 2,
      "goals_against": 11
    },
    {
      "id": "2df43129725f9b76e4be32f44a193f40",
      "date": "2026-03-07",
      "time": "10:00",
      "home_team": "Winthorpe & Cod T Amber U9",
      "away_team": "Tuxford FC U9",
      "home_score": 3,
      "away_score": 2,
      "venue": "",
      "division": "U9 Sat Spring Div 7 Red",
      "league": "YEL East Midlands Saturday 25/26",
      "team": "Winthorpe & Cod T Amber U9",
      "home_away": "home",
      "opponent": "Tuxford FC U9",
      "goals_for": 3,
      "goals_against": 2
    },
    {
      "id": "4fe2960f3c4081ae98251215459e9630",
      "date": "2026-03-07",
      "time": "10:00",
      "home_team": "Radcliffe Olympic Blue U9",
      "away_team": "Winthorpe & Cod T Black U9",
      "home_score": null,
      "away_score": null,
      "venue": "",
      "division": "U9 Saturday",
      "league": "YEL East Midlands Saturday 25/26",
      "team": "Winthorpe & Cod T Black U9",
      "home_away": "away",
      "opponent": "Radcliffe Olympic Blue U9",
      "goals_for": null,
      "goals_against": null
    },
    {
      "id": "edbe4350e7ea24de25ea2312af13beb8",
      "date": "2026-03-07",
      "time": "10:00",
      "home_team": "Gedling Southbank Arrows U10",
      "away_team": "Winthorpe & Cod T U10",
      "home_score": 5,
      "away_score": 0,
      "venue": "",
      "division": "U10 Sat Spring Div 7 Blue",
      "league": "YEL East Midlands Saturday 25/26",
      "team": "Winthorpe & Cod T U10",
      "home_away": "away",
      "opponent": "Gedling Southbank Arrows U10",
      "goals_for": 0,
      "goals_against": 5
    },
    {
      "id": "9da1ce4f69f3bf91a27c4c523650d23c",
      "date": "2026-03-07",
      "time": "09:30",
      "home_team": "Winthorpe & Cod T Black U11",
      "away_team": "Hucknall Sports Blue U11",
      "home_score": 3,
      "away_score": 0,
      "venue": "",
      "division": "U11 Sat Spring Div 6 Red",
      "league": "YEL East Midlands Saturday 25/26",
      "team": "Winthorpe & Cod T Black U11",
      "home_away": "home",
      "opponent": "Hucknall Sports Blue U11",
      "goals_for": 3,
      "goals_against": 0
    },
    {
      "id": "feb3ffa0105009e1dddb708a600c919e",
      "date": "2026-02-28",
      "time": "10:00",
      "home_team": "Sherwood FC Yellow U11",
      "away_team": "Winthorpe & Cod T Black U11",
      "home_score": 2,
      "away_score": 9,
      "venue": "",
      "division": "U11 Sat Spring Div 6 Red",
      "league": "YEL East Midlands Saturday 25/26",
      "team": "Winthorpe & Cod T Black U11",
      "home_away": "away",
      "opponent": "Sherwood FC Yellow U11",
      "goals_for": 9,
      "goals_against": 2
    },
    {
      "id": "c9eb7e740f92fcb6eb4d2be71540eb22",
      "date": "2026-02-28",
      "time": "10:00",
      "home_team": "Winthorpe & Cod T U10",
      "away_team": "Willow Wanderers Hornets U10",
      "home_score": 4,
      "away_score": 4,
      "venue": "",
      "division": "U10 Sat Spring Div 7 Blue",
      "league": "YEL East Midlands Saturday 25/26",
      "team": "Winthorpe & Cod T U10",
      "home_away": "home",
      "opponent": "Willow Wanderers Hornets U10",
      "goals_for": 4,
      "goals_against": 4
    },
    {
      "id": "63092dd48d3f9f38c832a01f723ba2de",
      "date": "2026-02-21",
      "time": "10:00",
      "home_team": "Arnold Town Blue U9",
      "away_team": "Winthorpe & Cod T Amber U9",
      "home_score": null,
      "away_score": null,
      "venue": "",
      "division": "U9 Sat 2026 Friendly 7 Green",
      "league": "YEL East Midlands Saturday 25/26",
      "team": "Winthorpe & Cod T Amber U9",
      "home_away": "away",
      "opponent": "Arnold Town Blue U9",
      "goals_for": null,
      "goals_against": null
    },
    {
      "id": "824a6a69cd6cf714e78750fa2dfbb1f6",
      "date": "2026-02-21",
      "time": "09:30",
      "home_team": "Winthorpe & Cod T U10",
      "away_team": "Fernwood Foxes Red U10",
      "home_score": null,
      "away_score": null,
      "venue": "",
      "division": "U10 Sat Friendly 2026 7 Blue",
      "league": "YEL East Midlands Saturday 25/26",
      "team": "Winthorpe & Cod T U10",
      "home_away": "home",
      "opponent": "Fernwood Foxes Red U10",
      "goals_for": null,
      "goals_against": null
    },
    {
      "id": "293481f5b23dea09546dcdaf7cff8bcd",
      "date": "2026-02-14",
      "time": "10:00",
      "home_team": "Winthorpe & Cod T Amber U9",
      "away_team": "Newark Brazil Corinthians U9",
      "home_score": null,
      "away_score": null,
      "venue": "",
      "division": "U9 Sat 2026 Friendly 7 Green",
      "league": "YEL East Midlands Saturday 25/26",
      "team": "Winthorpe & Cod T Amber U9",
      "home_away": "home",
      "opponent": "Newark Brazil Corinthians U9",
      "goals_for": null,
      "goals_against": null
    },
    {
      "id": "84b205e1acbdd948b887e11a6ac4541a",
      "date": "2026-02-14",
      "time": "10:00",
      "home_team": "Arnold Town Yellow U10",
      "away_team": "Winthorpe & Cod T U10",
      "home_score": null,
      "away_score": null,
      "venue": "",
      "division": "U10 Sat Friendly 2026 7 Blue",
      "league": "YEL East Midlands Saturday 25/26",
      "team": "Winthorpe & Cod T U10",
      "home_away": "away",
      "opponent": "Arnold Town Yellow U10",
      "goals_for": null,
      "goals_against": null
    },
    {
      "id": "e522c11e85ea9745e6ab1de95499405c",
      "date": "2026-02-07",
      "time": "10:00",
      "home_team": "Woodhouse Colts Rhinos U12",
      "away_team": "Winthorpe & Cod T Black U12",
      "home_score": 2,
      "away_score": 0,
      "venue": "",
      "division": "U12 Sat Spring Div 2 Red",
      "league": "YEL East Midlands Saturday 25/26",
      "team": "Winthorpe & Cod T Black U12",
      "home_away": "away",
      "opponent": "Woodhouse Colts Rhinos U12",
      "goals_for": 0,
      "goals_against": 2
    },
    {
      "id": "d963c447d97ab5ad48178475cb5c1e5f",
      "date": "2026-01-31",
      "time": "12:15",
      "home_team": "Ernehale Colts U11",
      "away_team": "Winthorpe & Cod T Black U11",
      "home_score": 1,
      "away_score": 9,
      "venue": "",
      "division": "U11 Sat YEL Challenge Trophy",
      "league": "YEL East Midlands Saturday 25/26",
      "team": "Winthorpe & Cod T Black U11",
      "home_away": "away",
      "opponent": "Ernehale Colts U11",
      "goals_for": 9,
      "goals_against": 1
    },
    {
      "id": "4189e86d460f936fa5a67273743252e5",
      "date": "2026-01-31",
      "time": "11:00",
      "home_team": "Carlton Town Lions U11",
      "away_team": "Winthorpe & Cod T Amber U11",
      "home_score": 2,
      "away_score": 2,
      "venue": "",
      "division": "U11 Sat Spring Div 8",
      "league": "YEL East Midlands Saturday 25/26",
      "team": "Winthorpe & Cod T Amber U11",
      "home_away": "away",
      "opponent": "Carlton Town Lions U11",
      "goals_for": 2,
      "goals_against": 2
    },
    {
      "id": "256e499fdaae48a86dae21da52588259",
      "date": "2026-01-31",
      "time": "11:00",
      "home_team": "Winthorpe & Cod T U13",
      "away_team": "Market Warsop Warriors U13",
      "home_score": 1,
      "away_score": 2,
      "venue": "",
      "division": "U13 Sat Spring Div 7 Red",
      "league": "YEL East Midlands Saturday 25/26",
      "team": "Winthorpe & Cod T U13",
      "home_away": "home",
      "opponent": "Market Warsop Warriors U13",
      "goals_for": 1,
      "goals_against": 2
    },
    {
      "id": "1cd36c7500dde7f3a5a086e4ead88ba3",
      "date": "2026-01-31",
      "time": "09:30",
      "home_team": "Winthorpe & Cod T Amber U9",
      "away_team": "Hucknall Sports White U9",
      "home_score": 1,
      "away_score": 3,
      "venue": "",
      "division": "U9 Sat YEL Challenge Blue",
      "league": "YEL East Midlands Saturday 25/26",
      "team": "Winthorpe & Cod T Amber U9",
      "home_away": "home",
      "opponent": "Hucknall Sports White U9",
      "goals_for": 1,
      "goals_against": 3
    },
    {
      "id": "17d03bdc6a61442032b229b99522dd86",
      "date": "2026-01-24",
      "time": "11:00",
      "home_team": "Winthorpe & Cod T Amber U11",
      "away_team": "Radcliffe Olympic Blue U11",
      "home_score": 2,
      "away_score": 1,
      "venue": "",
      "division": "U11 Sat Spring Div 8",
      "league": "YEL East Midlands Saturday 25/26",
      "team": "Winthorpe & Cod T Amber U11",
      "home_away": "home",
      "opponent": "Radcliffe Olympic Blue U11",
      "goals_for": 2,
      "goals_against": 1
    },
    {
      "id": "f1a803ab74cd18a99c4b3c5f363ef8ec",
      "date": "2026-01-24",
      "time": "11:00",
      "home_team": "Winthorpe & Cod T U13",
      "away_team": "G3A FC Zenit U13",
      "home_score": 1,
      "away_score": 7,
      "venue": "",
      "division": "U13 Sat Spring Div 7 Red",
      "league": "YEL East Midlands Saturday 25/26",
      "team": "Winthorpe & Cod T U13",
      "home_away": "home",
      "opponent": "G3A FC Zenit U13",
      "goals_for": 1,
      "goals_against": 7
    },
    {
      "id": "b11e0f806fe2da6857204bf91b2a8b19",
      "date": "2026-01-24",
      "time": "10:00",
      "home_team": "Newark Brazil Santos U9",
      "away_team": "Winthorpe & Cod T Amber U9",
      "home_score": 0,
      "away_score": 2,
      "venue": "",
      "division": "U9 Sat YEL Challenge Blue",
      "league": "YEL East Midlands Saturday 25/26",
      "team": "Winthorpe & Cod T Amber U9",
      "home_away": "away",
      "opponent": "Newark Brazil Santos U9",
      "goals_for": 2,
      "goals_against": 0
    },
    {
      "id": "f39beebc583abf3666fe242d66d9b2d4",
      "date": "2026-01-24",
      "time": "10:00",
      "home_team": "Long Bennington FC U11",
      "away_team": "Winthorpe & Cod T Black U11",
      "home_score": 0,
      "away_score": 3,
      "venue": "",
      "division": "U11 Sat Spring Div 6 Red",
      "league": "YEL East Midlands Saturday 25/26",
      "team": "Winthorpe & Cod T Black U11",
      "home_away": "away",
      "opponent": "Long Bennington FC U11",
      "goals_for": 3,
      "goals_against": 0
    },
    {
      "id": "601163ef67fa9fcac9de37ded5366c38",
      "date": "2026-01-24",
      "time": "10:00",
      "home_team": "Arnold Town Blue U9",
      "away_team": "Winthorpe & Cod T Black U9",
      "home_score": null,
      "away_score": null,
      "venue": "",
      "division": "U9 Sat 2026 Friendly 7 Green",
      "league": "YEL East Midlands Saturday 25/26",
      "team": "Winthorpe & Cod T Black U9",
      "home_away": "away",
      "opponent": "Arnold Town Blue U9",
      "goals_for": null,
      "goals_against": null
    },
    {
      "id": "b9f85f7e62a1ef0ac319e22ed2c74d5d",
      "date": "2026-01-24",
      "time": "09:30",
      "home_team": "Winthorpe & Cod T U10",
      "away_team": "Radcliffe Olympic Outlaws U10",
      "home_score": null,
      "away_score": null,
      "venue": "",
      "division": "U10 Sat Friendly 2026 7 Blue",
      "league": "YEL East Midlands Saturday 25/26",
      "team": "Winthorpe & Cod T U10",
      "home_away": "home",
      "opponent": "Radcliffe Olympic Outlaws U10",
      "goals_for": null,
      "goals_against": null
    },
    {
      "id": "291bac97031bcd86b1a7c56db4bd5d22",
      "date": "2026-01-17",
      "time": "11:15",
      "home_team": "DLFC Green U11",
      "away_team": "Winthorpe & Cod T Amber U11",
      "home_score": 1,
      "away_score": 7,
      "venue": "",
      "division": "U11 Sat Spring Div 8",
      "league": "YEL East Midlands Saturday 25/26",
      "team": "Winthorpe & Cod T Amber U11",
      "home_away": "away",
      "opponent": "DLFC Green U11",
      "goals_for": 7,
      "goals_against": 1
    },
    {
      "id": "037f15f1fd281b03d04820c8ffa1234c",
      "date": "2026-01-17",
      "time": "11:00",
      "home_team": "Winthorpe & Cod T Black U11",
      "away_team": "AC United U11",
      "home_score": 12,
      "away_score": 1,
      "venue": "",
      "division": "U11 Sat Spring Div 6 Red",
      "league": "YEL East Midlands Saturday 25/26",
      "team": "Winthorpe & Cod T Black U11",
      "home_away": "home",
      "opponent": "AC United U11",
      "goals_for": 12,
      "goals_against": 1
    },
    {
      "id": "61998400620c8141d62a0ce2ff2579d0",
      "date": "2026-01-17",
      "time": "11:00",
      "home_team": "Nottingham Second Chance U13",
      "away_team": "Winthorpe & Cod T U13",
      "home_score": 2,
      "away_score": 1,
      "venue": "",
      "division": "U13 Sat Spring Div 7 Red",
      "league": "YEL East Midlands Saturday 25/26",
      "team": "Winthorpe & Cod T U13",
      "home_away": "away",
      "opponent": "Nottingham Second Chance U13",
      "goals_for": 1,
      "goals_against": 2
    },
    {
      "id": "380bdb32fc75377f2d32611114011bd1",
      "date": "2026-01-17",
      "time": "10:00",
      "home_team": "Long Bennington FC U9",
      "away_team": "Winthorpe & Cod T Amber U9",
      "home_score": null,
      "away_score": null,
      "venue": "",
      "division": "U9 Saturday",
      "league": "YEL East Midlands Saturday 25/26",
      "team": "Winthorpe & Cod T Amber U9",
      "home_away": "away",
      "opponent": "Long Bennington FC U9",
      "goals_for": null,
      "goals_against": null
    },
    {
      "id": "ae78f3db0631ad35bc1c4f7c158e38fe",
      "date": "2026-01-17",
      "time": "10:00",
      "home_team": "Teversal FC U12",
      "away_team": "Winthorpe & Cod T Black U12",
      "home_score": 5,
      "away_score": 3,
      "venue": "",
      "division": "U12 Sat Spring Div 2 Red",
      "league": "YEL East Midlands Saturday 25/26",
      "team": "Winthorpe & Cod T Black U12",
      "home_away": "away",
      "opponent": "Teversal FC U12",
      "goals_for": 3,
      "goals_against": 5
    },
    {
      "id": "464bb3476210ed7193b9c55bbf128551",
      "date": "2026-01-17",
      "time": "10:00",
      "home_team": "Winthorpe & Cod T U10",
      "away_team": "G3A FC Leverkusen U10",
      "home_score": null,
      "away_score": null,
      "venue": "",
      "division": "U10 Sat Friendly 2026 7 Blue",
      "league": "YEL East Midlands Saturday 25/26",
      "team": "Winthorpe & Cod T U10",
      "home_away": "home",
      "opponent": "G3A FC Leverkusen U10",
      "goals_for": null,
      "goals_against": null
    },
    {
      "id": "98ca3ccf2e044edda3fe7654d896b08b",
      "date": "2026-01-17",
      "time": "09:30",
      "home_team": "Winthorpe & Cod T Black U9",
      "away_team": "Newark Brazil Corinthians U9",
      "home_score": null,
      "away_score": null,
      "venue": "",
      "division": "U9 Sat 2026 Friendly 7 Green",
      "league": "YEL East Midlands Saturday 25/26",
      "team": "Winthorpe & Cod T Black U9",
      "home_away": "home",
      "opponent": "Newark Brazil Corinthians U9",
      "goals_for": null,
      "goals_against": null
    },
    {
      "id": "7b441b52b4dfdfcb997b26e3b3317632",
      "date": "2025-12-13",
      "time": "11:00",
      "home_team": "Winthorpe & Cod T Black U11",
      "away_team": "Bingham Town Blue U11",
      "home_score": 6,
      "away_score": 0,
      "venue": "",
      "division": "U11 Sat YEL Challenge Trophy",
      "league": "YEL East Midlands Saturday 25/26",
      "team": "Winthorpe & Cod T Black U11",
      "home_away": "home",
      "opponent": "Bingham Town Blue U11",
      "goals_for": 6,
      "goals_against": 0
    },
    {
      "id": "89b18ede4eefd4f09cf4dc0bea41eca0",
      "date": "2025-12-13",
      "time": "11:00",
      "home_team": "Newark Brazil Santos U13",
      "away_team": "Winthorpe & Cod T U13",
      "home_score": 5,
      "away_score": 1,
      "venue": "",
      "division": "U13 Saturday",
      "league": "YEL East Midlands Saturday 25/26",
      "team": "Winthorpe & Cod T U13",
      "home_away": "away",
      "opponent": "Newark Brazil Santos U13",
      "goals_for": 1,
      "goals_against": 5
    },
    {
      "id": "3405f9a7ea72ce8e10089f84d3e7835e",
      "date": "2025-12-13",
      "time": "10:00",
      "home_team": "Burton Joyce Green U11",
      "away_team": "Winthorpe & Cod T Amber U11",
      "home_score": null,
      "away_score": null,
      "venue": "",
      "division": "U11 Saturday",
      "league": "YEL East Midlands Saturday 25/26",
      "team": "Winthorpe & Cod T Amber U11",
      "home_away": "away",
      "opponent": "Burton Joyce Green U11",
      "goals_for": null,
      "goals_against": null
    },
    {
      "id": "815b343e0166aaebc159f46a6a7f9fd5",
      "date": "2025-12-13",
      "time": "10:00",
      "home_team": "PMG Excel U12",
      "away_team": "Winthorpe & Cod T Black U12",
      "home_score": 4,
      "away_score": 1,
      "venue": "",
      "division": "U12 Saturday",
      "league": "YEL East Midlands Saturday 25/26",
      "team": "Winthorpe & Cod T Black U12",
      "home_away": "away",
      "opponent": "PMG Excel U12",
      "goals_for": 1,
      "goals_against": 4
    },
    {
      "id": "a7088bf1b9f63e539cd66cf231ea8422",
      "date": "2025-12-13",
      "time": "10:00",
      "home_team": "WBYFC Atletico U10",
      "away_team": "Winthorpe & Cod T U10",
      "home_score": 4,
      "away_score": 1,
      "venue": "",
      "division": "U10 Sat Winter Div 9 Gold",
      "league": "YEL East Midlands Saturday 25/26",
      "team": "Winthorpe & Cod T U10",
      "home_away": "away",
      "opponent": "WBYFC Atletico U10",
      "goals_for": 1,
      "goals_against": 4
    },
    {
      "id": "5e4b76a372a57edf37ac6a0e46c394ab",
      "date": "2025-12-13",
      "time": "09:30",
      "home_team": "Winthorpe & Cod T Amber U9",
      "away_team": "WBYFC Union U9",
      "home_score": null,
      "away_score": null,
      "venue": "",
      "division": "U9 Saturday",
      "league": "YEL East Midlands Saturday 25/26",
      "team": "Winthorpe & Cod T Amber U9",
      "home_away": "home",
      "opponent": "WBYFC Union U9",
      "goals_for": null,
      "goals_against": null
    },
    {
      "id": "789a3f6d8c5c6ffb7330264f956f49e0",
      "date": "2025-12-13",
      "time": "09:30",
      "home_team": "Winthorpe & Cod T Black U9",
      "away_team": "Muskham Cougars U9",
      "home_score": null,
      "away_score": null,
      "venue": "",
      "division": "U9 Saturday",
      "league": "YEL East Midlands Saturday 25/26",
      "team": "Winthorpe & Cod T Black U9",
      "home_away": "home",
      "opponent": "Muskham Cougars U9",
      "goals_for": null,
      "goals_against": null
    },
    {
      "id": "51fad1344d72fa5d3772de3733e32cfe",
      "date": "2025-12-06",
      "time": "11:00",
      "home_team": "Winthorpe & Cod T U13",
      "away_team": "Mapperley All Stars Blue U13",
      "home_score": 0,
      "away_score": 13,
      "venue": "",
      "division": "U13 Saturday",
      "league": "YEL East Midlands Saturday 25/26",
      "team": "Winthorpe & Cod T U13",
      "home_away": "home",
      "opponent": "Mapperley All Stars Blue U13",
      "goals_for": 0,
      "goals_against": 13
    },
    {
      "id": "e23dd158b2548d750b65542b0c1e59dc",
      "date": "2025-12-06",
      "time": "10:00",
      "home_team": "Bingham Town Red U12",
      "away_team": "Winthorpe & Cod T Black U12",
      "home_score": 1,
      "away_score": 2,
      "venue": "",
      "division": "U12 Saturday",
      "league": "YEL East Midlands Saturday 25/26",
      "team": "Winthorpe & Cod T Black U12",
      "home_away": "away",
      "opponent": "Bingham Town Red U12",
      "goals_for": 2,
      "goals_against": 1
    },
    {
      "id": "d1db0fa6beabe2753a865fd0778e1bf7",
      "date": "2025-12-06",
      "time": "10:00",
      "home_team": "Quarrydale United U9",
      "away_team": "Winthorpe & Cod T Black U9",
      "home_score": 4,
      "away_score": 2,
      "venue": "",
      "division": "U9 Sat YEL Challenge Blue",
      "league": "YEL East Midlands Saturday 25/26",
      "team": "Winthorpe & Cod T Black U9",
      "home_away": "away",
      "opponent": "Quarrydale United U9",
      "goals_for": 2,
      "goals_against": 4
    },
    {
      "id": "9c28474d6c67959925ace97ed0a77777",
      "date": "2025-12-06",
      "time": "09:30",
      "home_team": "Winthorpe & Cod T Black U11",
      "away_team": "Bingham Town White U11",
      "home_score": null,
      "away_score": null,
      "venue": "",
      "division": "U11 Saturday",
      "league": "YEL East Midlands Saturday 25/26",
      "team": "Winthorpe & Cod T Black U11",
      "home_away": "home",
      "opponent": "Bingham Town White U11",
      "goals_for": null,
      "goals_against": null
    },
    {
      "id": "36e4294e2d7964ff94f43c3c8a2dd694",
      "date": "2025-12-06",
      "time": "09:30",
      "home_team": "Winthorpe & Cod T U10",
      "away_team": "Newark Town Cavaliers U10",
      "home_score": 1,
      "away_score": 4,
      "venue": "",
      "division": "U10 Sat YEL Foundation Gold",
      "league": "YEL East Midlands Saturday 25/26",
      "team": "Winthorpe & Cod T U10",
      "home_away": "home",
      "opponent": "Newark Town Cavaliers U10",
      "goals_for": 1,
      "goals_against": 4
    },
    {
      "id": "d13d840ed7846f1c9d64bf8f6c98e7a4",
      "date": "2025-11-29",
      "time": "11:00",
      "home_team": "DLFC Orange U11",
      "away_team": "Winthorpe & Cod T Amber U11",
      "home_score": null,
      "away_score": null,
      "venue": "",
      "division": "U11 Saturday",
      "league": "YEL East Midlands Saturday 25/26",
      "team": "Winthorpe & Cod T Amber U11",
      "home_away": "away",
      "opponent": "DLFC Orange U11",
      "goals_for": null,
      "goals_against": null
    },
    {
      "id": "4fe097c18a8bec0346c2455499d3bb3c",
      "date": "2025-11-29",
      "time": "11:00",
      "home_team": "Winthorpe & Cod T Black U11",
      "away_team": "Keyworth United Black U11",
      "home_score": null,
      "away_score": null,
      "venue": "",
      "division": "U11 Saturday",
      "league": "YEL East Midlands Saturday 25/26",
      "team": "Winthorpe & Cod T Black U11",
      "home_away": "home",
      "opponent": "Keyworth United Black U11",
      "goals_for": null,
      "goals_against": null
    },
    {
      "id": "b5c56df3dc796fd9d90c745c8dd891a3",
      "date": "2025-11-29",
      "time": "11:00",
      "home_team": "Winthorpe & Cod T Black U12",
      "away_team": "WBYFC Palmeiras U12",
      "home_score": 2,
      "away_score": 3,
      "venue": "",
      "division": "U12 Sat YEL Trophy",
      "league": "YEL East Midlands Saturday 25/26",
      "team": "Winthorpe & Cod T Black U12",
      "home_away": "home",
      "opponent": "WBYFC Palmeiras U12",
      "goals_for": 2,
      "goals_against": 3
    },
    {
      "id": "e9187e0d34dce9daf83b0740c48f9fa5",
      "date": "2025-11-29",
      "time": "10:00",
      "home_team": "Newark Brazil Corinthians U9",
      "away_team": "Winthorpe & Cod T Amber U9",
      "home_score": 2,
      "away_score": 8,
      "venue": "",
      "division": "U9 Sat Winter Div 8 Red",
      "league": "YEL East Midlands Saturday 25/26",
      "team": "Winthorpe & Cod T Amber U9",
      "home_away": "away",
      "opponent": "Newark Brazil Corinthians U9",
      "goals_for": 8,
      "goals_against": 2
    },
    {
      "id": "209f01f8e2cc1d93ddab3b4ca403235b",
      "date": "2025-11-29",
      "time": "09:30",
      "home_team": "Winthorpe & Cod T Black U9",
      "away_team": "AFC Warriors Hunters U9",
      "home_score": null,
      "away_score": null,
      "venue": "",
      "division": "U9 Saturday",
      "league": "YEL East Midlands Saturday 25/26",
      "team": "Winthorpe & Cod T Black U9",
      "home_away": "home",
      "opponent": "AFC Warriors Hunters U9",
      "goals_for": null,
      "goals_against": null
    },
    {
      "id": "2fb80e05dd53760bce56d446b10ac34e",
      "date": "2025-11-22",
      "time": "11:00",
      "home_team": "Carlton Town Lions U11",
      "away_team": "Winthorpe & Cod T Amber U11",
      "home_score": 2,
      "away_score": 7,
      "venue": "",
      "division": "U11 Sat Winter Div 9",
      "league": "YEL East Midlands Saturday 25/26",
      "team": "Winthorpe & Cod T Amber U11",
      "home_away": "away",
      "opponent": "Carlton Town Lions U11",
      "goals_for": 7,
      "goals_against": 2
    },
    {
      "id": "e4736831d338527792ffb7302bb3ea56",
      "date": "2025-11-22",
      "time": "11:00",
      "home_team": "Gedling FC Tigers U12 *",
      "away_team": "Winthorpe & Cod T Black U12",
      "home_score": 4,
      "away_score": 1,
      "venue": "",
      "division": "U12 Saturday",
      "league": "YEL East Midlands Saturday 25/26",
      "team": "Winthorpe & Cod T Black U12",
      "home_away": "away",
      "opponent": "Gedling FC Tigers U12 *",
      "goals_for": 1,
      "goals_against": 4
    },
    {
      "id": "285514b2af7160f98a3364aa89aa1d09",
      "date": "2025-11-22",
      "time": "10:00",
      "home_team": "Robin Hood Colts U11",
      "away_team": "Winthorpe & Cod T Black U11",
      "home_score": 0,
      "away_score": 10,
      "venue": "",
      "division": "U11 Sat Winter Div 7 Red",
      "league": "YEL East Midlands Saturday 25/26",
      "team": "Winthorpe & Cod T Black U11",
      "home_away": "away",
      "opponent": "Robin Hood Colts U11",
      "goals_for": 10,
      "goals_against": 0
    },
    {
      "id": "c073bc5ddab95c7aaee829b4d753ba67",
      "date": "2025-11-22",
      "time": "10:00",
      "home_team": "Gonerby Yellow U9",
      "away_team": "Winthorpe & Cod T Black U9",
      "home_score": 4,
      "away_score": 4,
      "venue": "",
      "division": "U9 Sat Winter Div 8 Blue",
      "league": "YEL East Midlands Saturday 25/26",
      "team": "Winthorpe & Cod T Black U9",
      "home_away": "away",
      "opponent": "Gonerby Yellow U9",
      "goals_for": 4,
      "goals_against": 4
    },
    {
      "id": "056f2a4674f851d769631872ad053383",
      "date": "2025-11-22",
      "time": "10:00",
      "home_team": "Mapperley All Stars Blue U13",
      "away_team": "Winthorpe & Cod T U13",
      "home_score": 7,
      "away_score": 1,
      "venue": "",
      "division": "U13 Saturday",
      "league": "YEL East Midlands Saturday 25/26",
      "team": "Winthorpe & Cod T U13",
      "home_away": "away",
      "opponent": "Mapperley All Stars Blue U13",
      "goals_for": 1,
      "goals_against": 7
    },
    {
      "id": "37418f3f8eb86eb4301ecdb4ad10f28d",
      "date": "2025-11-22",
      "time": "09:30",
      "home_team": "Winthorpe & Cod T Amber U9",
      "away_team": "Woodborough Celtic Warriors U9",
      "home_score": 6,
      "away_score": 2,
      "venue": "",
      "division": "U9 Sat Winter Div 8 Red",
      "league": "YEL East Midlands Saturday 25/26",
      "team": "Winthorpe & Cod T Amber U9",
      "home_away": "home",
      "opponent": "Woodborough Celtic Warriors U9",
      "goals_for": 6,
      "goals_against": 2
    },
    {
      "id": "6e3662e8d99d2ce6c69f7eb988fbf479",
      "date": "2025-11-15",
      "time": "11:00",
      "home_team": "Winthorpe & Cod T Amber U11",
      "away_team": "Radcliffe Olympic Blue U11",
      "home_score": 3,
      "away_score": 3,
      "venue": "",
      "division": "U11 Sat Winter Div 9",
      "league": "YEL East Midlands Saturday 25/26",
      "team": "Winthorpe & Cod T Amber U11",
      "home_away": "home",
      "opponent": "Radcliffe Olympic Blue U11",
      "goals_for": 3,
      "goals_against": 3
    },
    {
      "id": "879d7ebbdd643933f90e7c3f75c5eac1",
      "date": "2025-11-15",
      "time": "11:00",
      "home_team": "Winthorpe & Cod T Black U12",
      "away_team": "PMG Excel U12",
      "home_score": 3,
      "away_score": 1,
      "venue": "",
      "division": "U12 Sat Winter Div 2 Red",
      "league": "YEL East Midlands Saturday 25/26",
      "team": "Winthorpe & Cod T Black U12",
      "home_away": "home",
      "opponent": "PMG Excel U12",
      "goals_for": 3,
      "goals_against": 1
    },
    {
      "id": "589b1fe9d306cb7807ac2fadc9810e12",
      "date": "2025-11-15",
      "time": "09:30",
      "home_team": "Winthorpe & Cod T Black U9",
      "away_team": "Edwalton Cavaliers White U9",
      "home_score": 1,
      "away_score": 12,
      "venue": "",
      "division": "U9 Sat Winter Div 8 Blue",
      "league": "YEL East Midlands Saturday 25/26",
      "team": "Winthorpe & Cod T Black U9",
      "home_away": "home",
      "opponent": "Edwalton Cavaliers White U9",
      "goals_for": 1,
      "goals_against": 12
    },
    {
      "id": "b5d81beb6f46c2759ed56294a622e1d3",
      "date": "2025-11-15",
      "time": "09:30",
      "home_team": "Winthorpe & Cod T U10",
      "away_team": "Carlton Town Lions U10",
      "home_score": 5,
      "away_score": 1,
      "venue": "",
      "division": "U10 Sat Winter Div 9 Gold",
      "league": "YEL East Midlands Saturday 25/26",
      "team": "Winthorpe & Cod T U10",
      "home_away": "home",
      "opponent": "Carlton Town Lions U10",
      "goals_for": 5,
      "goals_against": 1
    },
    {
      "id": "1d7926b4f96ea4c36e80c4549ce1b0e5",
      "date": "2025-11-08",
      "time": "11:30",
      "home_team": "Cotgrave FC Claret U9",
      "away_team": "Winthorpe & Cod T Black U9",
      "home_score": 4,
      "away_score": 3,
      "venue": "",
      "division": "U9 Sat Winter Div 8 Blue",
      "league": "YEL East Midlands Saturday 25/26",
      "team": "Winthorpe & Cod T Black U9",
      "home_away": "away",
      "opponent": "Cotgrave FC Claret U9",
      "goals_for": 3,
      "goals_against": 4
    },
    {
      "id": "8a96a6463f90a9523ce6ea77d326f002",
      "date": "2025-11-08",
      "time": "11:00",
      "home_team": "Winthorpe & Cod T Black U11",
      "away_team": "Notts County Women U11 ^",
      "home_score": 6,
      "away_score": 3,
      "venue": "",
      "division": "U11 Sat Winter Div 7 Red",
      "league": "YEL East Midlands Saturday 25/26",
      "team": "Winthorpe & Cod T Black U11",
      "home_away": "home",
      "opponent": "Notts County Women U11 ^",
      "goals_for": 6,
      "goals_against": 3
    },
    {
      "id": "cee6d46124005f303d97065da4ca708d",
      "date": "2025-11-08",
      "time": "11:00",
      "home_team": "Northgate Olympic FC U12",
      "away_team": "Winthorpe & Cod T Black U12",
      "home_score": 0,
      "away_score": 4,
      "venue": "",
      "division": "U12 Sat Winter Div 2 Red",
      "league": "YEL East Midlands Saturday 25/26",
      "team": "Winthorpe & Cod T Black U12",
      "home_away": "away",
      "opponent": "Northgate Olympic FC U12",
      "goals_for": 4,
      "goals_against": 0
    },
    {
      "id": "39af832e7e9542d7e427d167dd286bc1",
      "date": "2025-11-08",
      "time": "11:00",
      "home_team": "Keyworth United White U13",
      "away_team": "Winthorpe & Cod T U13",
      "home_score": 1,
      "away_score": 5,
      "venue": "",
      "division": "U13 Sat Winter Div 7 Brown",
      "league": "YEL East Midlands Saturday 25/26",
      "team": "Winthorpe & Cod T U13",
      "home_away": "away",
      "opponent": "Keyworth United White U13",
      "goals_for": 5,
      "goals_against": 1
    },
    {
      "id": "a2c73979499435e7c28d2d18195530e2",
      "date": "2025-11-08",
      "time": "10:00",
      "home_team": "Newark Town Saxons U11",
      "away_team": "Winthorpe & Cod T Amber U11",
      "home_score": 0,
      "away_score": 8,
      "venue": "",
      "division": "U11 Sat Winter Div 9",
      "league": "YEL East Midlands Saturday 25/26",
      "team": "Winthorpe & Cod T Amber U11",
      "home_away": "away",
      "opponent": "Newark Town Saxons U11",
      "goals_for": 8,
      "goals_against": 0
    },
    {
      "id": "7cd028ff179b1fdb78a54ae377b31569",
      "date": "2025-11-08",
      "time": "10:00",
      "home_team": "Gedling Southbank Reds U9",
      "away_team": "Winthorpe & Cod T Amber U9",
      "home_score": 0,
      "away_score": 3,
      "venue": "",
      "division": "U9 Sat Winter Div 8 Red",
      "league": "YEL East Midlands Saturday 25/26",
      "team": "Winthorpe & Cod T Amber U9",
      "home_away": "away",
      "opponent": "Gedling Southbank Reds U9",
      "goals_for": 3,
      "goals_against": 0
    },
    {
      "id": "7e38a3e79d544d2ef4d33cec62310974",
      "date": "2025-11-08",
      "time": "10:00",
      "home_team": "Winthorpe & Cod T U10",
      "away_team": "Toton Tornados Vortex U10",
      "home_score": 7,
      "away_score": 5,
      "venue": "",
      "division": "U10 Sat Winter Div 9 Gold",
      "league": "YEL East Midlands Saturday 25/26",
      "team": "Winthorpe & Cod T U10",
      "home_away": "home",
      "opponent": "Toton Tornados Vortex U10",
      "goals_for": 7,
      "goals_against": 5
    },
    {
      "id": "0763b394294b83cfdeb39bab242469d0",
      "date": "2025-11-01",
      "time": "10:00",
      "home_team": "Spirit Celtic Tigers U9",
      "away_team": "Winthorpe & Cod T Amber U9",
      "home_score": null,
      "away_score": null,
      "venue": "",
      "division": "U9 Sat Autumn 8 Blue",
      "league": "YEL East Midlands Saturday 25/26",
      "team": "Winthorpe & Cod T Amber U9",
      "home_away": "away",
      "opponent": "Spirit Celtic Tigers U9",
      "goals_for": null,
      "goals_against": null
    },
    {
      "id": "29c73da06acf5be52ba3fb7168f1b04e",
      "date": "2025-11-01",
      "time": "09:30",
      "home_team": "Winthorpe & Cod T U10",
      "away_team": "Newark Brazil Rio U10",
      "home_score": null,
      "away_score": null,
      "venue": "",
      "division": "U10 Saturday",
      "league": "YEL East Midlands Saturday 25/26",
      "team": "Winthorpe & Cod T U10",
      "home_away": "home",
      "opponent": "Newark Brazil Rio U10",
      "goals_for": null,
      "goals_against": null
    },
    {
      "id": "114396f7475d27c5762b698aa3b1bf61",
      "date": "2025-10-25",
      "time": "10:00",
      "home_team": "DJFC U10",
      "away_team": "Winthorpe & Cod T U10",
      "home_score": null,
      "away_score": null,
      "venue": "",
      "division": "U10 Saturday",
      "league": "YEL East Midlands Saturday 25/26",
      "team": "Winthorpe & Cod T U10",
      "home_away": "away",
      "opponent": "DJFC U10",
      "goals_for": null,
      "goals_against": null
    },
    {
      "id": "3a538134b4beadcf1b01c343a41da58a",
      "date": "2025-10-18",
      "time": "10:00",
      "home_team": "Gonerby Blue U9",
      "away_team": "Winthorpe & Cod T Amber U9",
      "home_score": null,
      "away_score": null,
      "venue": "",
      "division": "U9 Saturday",
      "league": "YEL East Midlands Saturday 25/26",
      "team": "Winthorpe & Cod T Amber U9",
      "home_away": "away",
      "opponent": "Gonerby Blue U9",
      "goals_for": null,
      "goals_against": null
    },
    {
      "id": "1537aeaa0ca52fcd237c530e23b86b2f",
      "date": "2025-10-11",
      "time": "11:00",
      "home_team": "Winthorpe & Cod T Amber U11",
      "away_team": "Burton Joyce Green U11",
      "home_score": 4,
      "away_score": 6,
      "venue": "",
      "division": "U11 Sat Winter Div 9",
      "league": "YEL East Midlands Saturday 25/26",
      "team": "Winthorpe & Cod T Amber U11",
      "home_away": "home",
      "opponent": "Burton Joyce Green U11",
      "goals_for": 4,
      "goals_against": 6
    },
    {
      "id": "70e6328cd0d31f89082a5a8105969d27",
      "date": "2025-10-11",
      "time": "11:00",
      "home_team": "Ernehale Colts U11",
      "away_team": "Winthorpe & Cod T Black U11",
      "home_score": 3,
      "away_score": 3,
      "venue": "",
      "division": "U11 Sat Winter Div 7 Red",
      "league": "YEL East Midlands Saturday 25/26",
      "team": "Winthorpe & Cod T Black U11",
      "home_away": "away",
      "opponent": "Ernehale Colts U11",
      "goals_for": 3,
      "goals_against": 3
    },
    {
      "id": "1e280882db14ff55fa72972c53bf518f",
      "date": "2025-10-11",
      "time": "10:00",
      "home_team": "Lowdham FC Garibaldi U12",
      "away_team": "Winthorpe & Cod T Black U12",
      "home_score": 0,
      "away_score": 5,
      "venue": "",
      "division": "U12 Sat Winter Div 2 Red",
      "league": "YEL East Midlands Saturday 25/26",
      "team": "Winthorpe & Cod T Black U12",
      "home_away": "away",
      "opponent": "Lowdham FC Garibaldi U12",
      "goals_for": 5,
      "goals_against": 0
    },
    {
      "id": "7b103bf29befec4e953b6d1446f57787",
      "date": "2025-10-11",
      "time": "10:00",
      "home_team": "Radcliffe Olympic Blue U9",
      "away_team": "Winthorpe & Cod T Black U9",
      "home_score": 4,
      "away_score": 2,
      "venue": "",
      "division": "U9 Sat Winter Div 8 Blue",
      "league": "YEL East Midlands Saturday 25/26",
      "team": "Winthorpe & Cod T Black U9",
      "home_away": "away",
      "opponent": "Radcliffe Olympic Blue U9",
      "goals_for": 2,
      "goals_against": 4
    },
    {
      "id": "31b2a5d932f18fbce386e20426c94912",
      "date": "2025-10-11",
      "time": "10:00",
      "home_team": "Spirit Celtic Red U10",
      "away_team": "Winthorpe & Cod T U10",
      "home_score": 0,
      "away_score": 6,
      "venue": "",
      "division": "U10 Sat Winter Div 9 Gold",
      "league": "YEL East Midlands Saturday 25/26",
      "team": "Winthorpe & Cod T U10",
      "home_away": "away",
      "opponent": "Spirit Celtic Red U10",
      "goals_for": 6,
      "goals_against": 0
    },
    {
      "id": "c7384405d0547ca1941913b7a7c0cd7c",
      "date": "2025-10-11",
      "time": "09:30",
      "home_team": "Winthorpe & Cod T Amber U9",
      "away_team": "Silva FC Brunts U9",
      "home_score": 4,
      "away_score": 1,
      "venue": "",
      "division": "U9 Sat Winter Div 8 Red",
      "league": "YEL East Midlands Saturday 25/26",
      "team": "Winthorpe & Cod T Amber U9",
      "home_away": "home",
      "opponent": "Silva FC Brunts U9",
      "goals_for": 4,
      "goals_against": 1
    },
    {
      "id": "dd32e16c868a5cc207da85c43093134f",
      "date": "2025-10-04",
      "time": "11:00",
      "home_team": "Winthorpe & Cod T Black U11",
      "away_team": "Sutton-on-Trent Tornadoes U11",
      "home_score": 1,
      "away_score": 3,
      "venue": "",
      "division": "U11 Sat Winter Div 7 Red",
      "league": "YEL East Midlands Saturday 25/26",
      "team": "Winthorpe & Cod T Black U11",
      "home_away": "home",
      "opponent": "Sutton-on-Trent Tornadoes U11",
      "goals_for": 1,
      "goals_against": 3
    },
    {
      "id": "45af02fb516c37cb5dde34cdc7112879",
      "date": "2025-10-04",
      "time": "11:00",
      "home_team": "Winthorpe & Cod T Black U12",
      "away_team": "Woodhouse Colts Rhinos U12",
      "home_score": 1,
      "away_score": 4,
      "venue": "",
      "division": "U12 Sat Winter Div 2 Red",
      "league": "YEL East Midlands Saturday 25/26",
      "team": "Winthorpe & Cod T Black U12",
      "home_away": "home",
      "opponent": "Woodhouse Colts Rhinos U12",
      "goals_for": 1,
      "goals_against": 4
    },
    {
      "id": "f02b9934525192e04d0d82bf3f341f7d",
      "date": "2025-10-04",
      "time": "10:30",
      "home_team": "Collingham FC Lions U13",
      "away_team": "Winthorpe & Cod T U13",
      "home_score": 8,
      "away_score": 1,
      "venue": "",
      "division": "U13 Sat Winter Div 7 Brown",
      "league": "YEL East Midlands Saturday 25/26",
      "team": "Winthorpe & Cod T U13",
      "home_away": "away",
      "opponent": "Collingham FC Lions U13",
      "goals_for": 1,
      "goals_against": 8
    },
    {
      "id": "42fb1e6fa046dbe7ab8c285f4febb94c",
      "date": "2025-10-04",
      "time": "10:00",
      "home_team": "Hucknall Sports Red U11",
      "away_team": "Winthorpe & Cod T Amber U11",
      "home_score": 0,
      "away_score": 4,
      "venue": "",
      "division": "U11 Sat Winter Div 9",
      "league": "YEL East Midlands Saturday 25/26",
      "team": "Winthorpe & Cod T Amber U11",
      "home_away": "away",
      "opponent": "Hucknall Sports Red U11",
      "goals_for": 4,
      "goals_against": 0
    },
    {
      "id": "d54992c4dc52468f3f7bb3f6d959d4b7",
      "date": "2025-10-04",
      "time": "09:30",
      "home_team": "Winthorpe & Cod T Black U9",
      "away_team": "WBYFC Rio U9",
      "home_score": 5,
      "away_score": 4,
      "venue": "",
      "division": "U9 Sat Winter Div 8 Blue",
      "league": "YEL East Midlands Saturday 25/26",
      "team": "Winthorpe & Cod T Black U9",
      "home_away": "home",
      "opponent": "WBYFC Rio U9",
      "goals_for": 5,
      "goals_against": 4
    },
    {
      "id": "d5fa43eb730103aeffcd77a08bc3cb6e",
      "date": "2025-10-04",
      "time": "09:30",
      "home_team": "Winthorpe & Cod T U10",
      "away_team": "WBYFC Atletico U10",
      "home_score": 1,
      "away_score": 1,
      "venue": "",
      "division": "U10 Sat Winter Div 9 Gold",
      "league": "YEL East Midlands Saturday 25/26",
      "team": "Winthorpe & Cod T U10",
      "home_away": "home",
      "opponent": "WBYFC Atletico U10",
      "goals_for": 1,
      "goals_against": 1
    },
    {
      "id": "1202977f85266389fe715760eda24a69",
      "date": "2025-09-27",
      "time": "11:00",
      "home_team": "Winthorpe & Cod T Amber U11",
      "away_team": "DLFC Blue U11",
      "home_score": 2,
      "away_score": 1,
      "venue": "",
      "division": "U11 Sat Winter Div 9",
      "league": "YEL East Midlands Saturday 25/26",
      "team": "Winthorpe & Cod T Amber U11",
      "home_away": "home",
      "opponent": "DLFC Blue U11",
      "goals_for": 2,
      "goals_against": 1
    },
    {
      "id": "5b65acaf2d1603a5881a7d968f81d331",
      "date": "2025-09-27",
      "time": "11:00",
      "home_team": "Southwell City Lions U11",
      "away_team": "Winthorpe & Cod T Black U11",
      "home_score": 0,
      "away_score": 7,
      "venue": "",
      "division": "U11 Sat Winter Div 7 Red",
      "league": "YEL East Midlands Saturday 25/26",
      "team": "Winthorpe & Cod T Black U11",
      "home_away": "away",
      "opponent": "Southwell City Lions U11",
      "goals_for": 7,
      "goals_against": 0
    },
    {
      "id": "b6ab6f4921888f98951f65f5319b6e69",
      "date": "2025-09-27",
      "time": "11:00",
      "home_team": "Edwalton Cavaliers Blue U9",
      "away_team": "Winthorpe & Cod T Black U9",
      "home_score": null,
      "away_score": null,
      "venue": "",
      "division": "U9 Saturday",
      "league": "YEL East Midlands Saturday 25/26",
      "team": "Winthorpe & Cod T Black U9",
      "home_away": "away",
      "opponent": "Edwalton Cavaliers Blue U9",
      "goals_for": null,
      "goals_against": null
    },
    {
      "id": "2843c236608ad1f138412d41c19b87c2",
      "date": "2025-09-27",
      "time": "11:00",
      "home_team": "Newark Brazil Rio U10",
      "away_team": "Winthorpe & Cod T U10",
      "home_score": null,
      "away_score": null,
      "venue": "",
      "division": "U10 Saturday",
      "league": "YEL East Midlands Saturday 25/26",
      "team": "Winthorpe & Cod T U10",
      "home_away": "away",
      "opponent": "Newark Brazil Rio U10",
      "goals_for": null,
      "goals_against": null
    },
    {
      "id": "1d7c8cd0a501d22ebcb6c6d9866a2aa0",
      "date": "2025-09-27",
      "time": "11:00",
      "home_team": "Winthorpe & Cod T U13",
      "away_team": "Saxilby Athletic Allstars U13",
      "home_score": 1,
      "away_score": 11,
      "venue": "",
      "division": "U13 Sat Winter Div 7 Brown",
      "league": "YEL East Midlands Saturday 25/26",
      "team": "Winthorpe & Cod T U13",
      "home_away": "home",
      "opponent": "Saxilby Athletic Allstars U13",
      "goals_for": 1,
      "goals_against": 11
    },
    {
      "id": "ebd7b9152e80d055a492c3434ae76ce2",
      "date": "2025-09-27",
      "time": "10:00",
      "home_team": "Hucknall Sports Red U12",
      "away_team": "Winthorpe & Cod T Black U12",
      "home_score": 0,
      "away_score": 1,
      "venue": "",
      "division": "U12 Sat Winter Div 2 Red",
      "league": "YEL East Midlands Saturday 25/26",
      "team": "Winthorpe & Cod T Black U12",
      "home_away": "away",
      "opponent": "Hucknall Sports Red U12",
      "goals_for": 1,
      "goals_against": 0
    },
    {
      "id": "9a6ccc57cc52b9dfedfafd4ad3badadd",
      "date": "2025-09-27",
      "time": "09:30",
      "home_team": "Winthorpe & Cod T Amber U9",
      "away_team": "Keyworth United White U9",
      "home_score": null,
      "away_score": null,
      "venue": "",
      "division": "U9 Sat Autumn 8 Blue",
      "league": "YEL East Midlands Saturday 25/26",
      "team": "Winthorpe & Cod T Amber U9",
      "home_away": "home",
      "opponent": "Keyworth United White U9",
      "goals_for": null,
      "goals_against": null
    },
    {
      "id": "11a6b25e71c2b946a081be5bc8fb4eaa",
      "date": "2025-09-20",
      "time": "12:30",
      "home_team": "Newark Town Cavaliers U11",
      "away_team": "Winthorpe & Cod T Amber U11",
      "home_score": 5,
      "away_score": 1,
      "venue": "",
      "division": "U11 Sat Winter Div 9",
      "league": "YEL East Midlands Saturday 25/26",
      "team": "Winthorpe & Cod T Amber U11",
      "home_away": "away",
      "opponent": "Newark Town Cavaliers U11",
      "goals_for": 1,
      "goals_against": 5
    },
    {
      "id": "b6b9cf04472367fc38832132270a2184",
      "date": "2025-09-20",
      "time": "11:00",
      "home_team": "Winthorpe & Cod T Black U12",
      "away_team": "Alfreton Town Jnrs Goats U12",
      "home_score": 0,
      "away_score": 1,
      "venue": "",
      "division": "U12 Sat Winter Div 2 Red",
      "league": "YEL East Midlands Saturday 25/26",
      "team": "Winthorpe & Cod T Black U12",
      "home_away": "home",
      "opponent": "Alfreton Town Jnrs Goats U12",
      "goals_for": 0,
      "goals_against": 1
    },
    {
      "id": "9c7b1de1a1bb5be21ecdd38480a994a6",
      "date": "2025-09-20",
      "time": "11:00",
      "home_team": "Winthorpe & Cod T U13",
      "away_team": "AFC Warriors Spartans U13",
      "home_score": 0,
      "away_score": 7,
      "venue": "",
      "division": "U13 Sat Winter Div 7 Brown",
      "league": "YEL East Midlands Saturday 25/26",
      "team": "Winthorpe & Cod T U13",
      "home_away": "home",
      "opponent": "AFC Warriors Spartans U13",
      "goals_for": 0,
      "goals_against": 7
    },
    {
      "id": "1a3faaa93588408dcb16ea082bd7ce96",
      "date": "2025-09-20",
      "time": "10:00",
      "home_team": "Woodthorpe Com Fire U9",
      "away_team": "Winthorpe & Cod T Amber U9",
      "home_score": null,
      "away_score": null,
      "venue": "",
      "division": "U9 Sat Autumn 8 Blue",
      "league": "YEL East Midlands Saturday 25/26",
      "team": "Winthorpe & Cod T Amber U9",
      "home_away": "away",
      "opponent": "Woodthorpe Com Fire U9",
      "goals_for": null,
      "goals_against": null
    },
    {
      "id": "a4be29407ceb74b4d05a2570f8a24fa8",
      "date": "2025-09-20",
      "time": "09:30",
      "home_team": "Winthorpe & Cod T Black U11",
      "away_team": "DLFC Orange U11",
      "home_score": 9,
      "away_score": 1,
      "venue": "",
      "division": "U11 Sat Winter Div 7 Red",
      "league": "YEL East Midlands Saturday 25/26",
      "team": "Winthorpe & Cod T Black U11",
      "home_away": "home",
      "opponent": "DLFC Orange U11",
      "goals_for": 9,
      "goals_against": 1
    },
    {
      "id": "b6ccd17dff8761bc9801ad9db42a80ea",
      "date": "2025-09-20",
      "time": "09:30",
      "home_team": "Winthorpe & Cod T Black U9",
      "away_team": "Star Strike Tigers U9",
      "home_score": null,
      "away_score": null,
      "venue": "",
      "division": "U9 Sat Autumn 7 Red",
      "league": "YEL East Midlands Saturday 25/26",
      "team": "Winthorpe & Cod T Black U9",
      "home_away": "home",
      "opponent": "Star Strike Tigers U9",
      "goals_for": null,
      "goals_against": null
    },
    {
      "id": "04848c6e821ae94d2d909eaa1f29577c",
      "date": "2025-09-20",
      "time": "09:30",
      "home_team": "Winthorpe & Cod T U10",
      "away_team": "WBYFC Atletico U10",
      "home_score": null,
      "away_score": null,
      "venue": "",
      "division": "U10 Sat Autumn 9",
      "league": "YEL East Midlands Saturday 25/26",
      "team": "Winthorpe & Cod T U10",
      "home_away": "home",
      "opponent": "WBYFC Atletico U10",
      "goals_for": null,
      "goals_against": null
    },
    {
      "id": "52d94e2dd6d6f2a83c9a02b3258c9e4d",
      "date": "2025-09-13",
      "time": "12:30",
      "home_team": "Southwell City Troopers U13",
      "away_team": "Winthorpe & Cod T U13",
      "home_score": 4,
      "away_score": 4,
      "venue": "",
      "division": "U13 Sat Winter Div 7 Brown",
      "league": "YEL East Midlands Saturday 25/26",
      "team": "Winthorpe & Cod T U13",
      "home_away": "away",
      "opponent": "Southwell City Troopers U13",
      "goals_for": 4,
      "goals_against": 4
    },
    {
      "id": "bbd4fe04fd3f5a97e1399939406f61bf",
      "date": "2025-09-13",
      "time": "11:00",
      "home_team": "Winthorpe & Cod T Black U11",
      "away_team": "Priory Celtic Phoenix U11",
      "home_score": 5,
      "away_score": 3,
      "venue": "",
      "division": "U11 Sat Winter Div 7 Red",
      "league": "YEL East Midlands Saturday 25/26",
      "team": "Winthorpe & Cod T Black U11",
      "home_away": "home",
      "opponent": "Priory Celtic Phoenix U11",
      "goals_for": 5,
      "goals_against": 3
    },
    {
      "id": "8258e560cd6e81b83c2f0bf870000e81",
      "date": "2025-09-13",
      "time": "11:00",
      "home_team": "Nottingham FC Green U12",
      "away_team": "Winthorpe & Cod T Black U12",
      "home_score": 2,
      "away_score": 2,
      "venue": "",
      "division": "U12 Sat Winter Div 2 Red",
      "league": "YEL East Midlands Saturday 25/26",
      "team": "Winthorpe & Cod T Black U12",
      "home_away": "away",
      "opponent": "Nottingham FC Green U12",
      "goals_for": 2,
      "goals_against": 2
    },
    {
      "id": "04e77f8c8a758f7274212cc8b40dfea1",
      "date": "2025-09-13",
      "time": "10:00",
      "home_team": "Winthorpe & Cod T Amber U9",
      "away_team": "Muskham Cougars U9",
      "home_score": null,
      "away_score": null,
      "venue": "",
      "division": "U9 Sat Autumn 8 Blue",
      "league": "YEL East Midlands Saturday 25/26",
      "team": "Winthorpe & Cod T Amber U9",
      "home_away": "home",
      "opponent": "Muskham Cougars U9",
      "goals_for": null,
      "goals_against": null
    },
    {
      "id": "8030f6f99af9e9b9d7530a4c23ff163e",
      "date": "2025-09-13",
      "time": "10:00",
      "home_team": "Southwell City Cobras U9",
      "away_team": "Winthorpe & Cod T Black U9",
      "home_score": null,
      "away_score": null,
      "venue": "",
      "division": "U9 Sat Autumn 7 Red",
      "league": "YEL East Midlands Saturday 25/26",
      "team": "Winthorpe & Cod T Black U9",
      "home_away": "away",
      "opponent": "Southwell City Cobras U9",
      "goals_for": null,
      "goals_against": null
    },
    {
      "id": "041e48511f07d2d831f59d42359c4e16",
      "date": "2025-09-13",
      "time": "10:00",
      "home_team": "NG United U10",
      "away_team": "Winthorpe & Cod T U10",
      "home_score": null,
      "away_score": null,
      "venue": "",
      "division": "U10 Saturday",
      "league": "YEL East Midlands Saturday 25/26",
      "team": "Winthorpe & Cod T U10",
      "home_away": "away",
      "opponent": "NG United U10",
      "goals_for": null,
      "goals_against": null
    },
    {
      "id": "ad7cb437334bc2dce93040217e2d5421",
      "date": "2025-09-06",
      "time": "12:30",
      "home_team": "Radcliffe Olympic Outlaws U10",
      "away_team": "Winthorpe & Cod T U10",
      "home_score": null,
      "away_score": null,
      "venue": "",
      "division": "U10 Sat Autumn 9",
      "league": "YEL East Midlands Saturday 25/26",
      "team": "Winthorpe & Cod T U10",
      "home_away": "away",
      "opponent": "Radcliffe Olympic Outlaws U10",
      "goals_for": null,
      "goals_against": null
    },
    {
      "id": "f40b64da0d8ac44bdc52a770ab3f6b48",
      "date": "2025-09-06",
      "time": "11:00",
      "home_team": "Winthorpe & Cod T Amber U11",
      "away_team": "Newark Town Saxons U11",
      "home_score": null,
      "away_score": null,
      "venue": "",
      "division": "U11 Saturday",
      "league": "YEL East Midlands Saturday 25/26",
      "team": "Winthorpe & Cod T Amber U11",
      "home_away": "home",
      "opponent": "Newark Town Saxons U11",
      "goals_for": null,
      "goals_against": null
    },
    {
      "id": "5eda87fe33a2e6c2c0948d3ca1d00a98",
      "date": "2025-09-06",
      "time": "11:00",
      "home_team": "Winthorpe & Cod T Black U12",
      "away_team": "Northgate Olympic FC U12",
      "home_score": 3,
      "away_score": 1,
      "venue": "",
      "division": "U12 Saturday",
      "league": "YEL East Midlands Saturday 25/26",
      "team": "Winthorpe & Cod T Black U12",
      "home_away": "home",
      "opponent": "Northgate Olympic FC U12",
      "goals_for": 3,
      "goals_against": 1
    },
    {
      "id": "605a9d9fe63586d52072bfb04acedc99",
      "date": "2025-09-06",
      "time": "11:00",
      "home_team": "Winthorpe & Cod T U13",
      "away_team": "Aslockton & Orston Red U13",
      "home_score": 10,
      "away_score": 0,
      "venue": "",
      "division": "U13 Saturday",
      "league": "YEL East Midlands Saturday 25/26",
      "team": "Winthorpe & Cod T U13",
      "home_away": "home",
      "opponent": "Aslockton & Orston Red U13",
      "goals_for": 10,
      "goals_against": 0
    },
    {
      "id": "a54632ae28825288d8235e7bed9b8982",
      "date": "2025-09-06",
      "time": "10:00",
      "home_team": "Carlton Town Blue U9",
      "away_team": "Winthorpe & Cod T Black U9",
      "home_score": null,
      "away_score": null,
      "venue": "",
      "division": "U9 Sat Autumn 7 Red",
      "league": "YEL East Midlands Saturday 25/26",
      "team": "Winthorpe & Cod T Black U9",
      "home_away": "away",
      "opponent": "Carlton Town Blue U9",
      "goals_for": null,
      "goals_against": null
    },
    {
      "id": "6afb27e042c40f7a6aded5a099c89c96",
      "date": "2025-09-06",
      "time": "09:30",
      "home_team": "Winthorpe & Cod T Amber U9",
      "away_team": "Arnold Town Blue U9",
      "home_score": null,
      "away_score": null,
      "venue": "",
      "division": "U9 Sat Autumn 8 Blue",
      "league": "YEL East Midlands Saturday 25/26",
      "team": "Winthorpe & Cod T Amber U9",
      "home_away": "home",
      "opponent": "Arnold Town Blue U9",
      "goals_for": null,
      "goals_against": null
    },
    {
      "id": "b920723f943bdff434e2292d0b9fa706",
      "date": "2025-09-06",
      "time": "09:30",
      "home_team": "Winthorpe & Cod T Black U11",
      "away_team": "Bingham Town Blue U11",
      "home_score": null,
      "away_score": null,
      "venue": "",
      "division": "U11 Saturday",
      "league": "YEL East Midlands Saturday 25/26",
      "team": "Winthorpe & Cod T Black U11",
      "home_away": "home",
      "opponent": "Bingham Town Blue U11",
      "goals_for": null,
      "goals_against": null
    }
  ]
}