{
  "team": "Heanor Juniors Badgers U14",
  "league": "YEL East Midlands Saturday 25/26",
  "generated": "2026-03-20T21:15:50Z",
  "fixtures": [
    {
      "id": "e50106ad57c58fdde7ce0a8f86c7fccf",
      "date": "2026-03-21",
      "time": "10:00",
      "home_team": "Heanor Juniors Badgers U14",
      "away_team": "Basford United Ambers U14",
      "venue": "Kilburn Welfare Social Club DE56 0NR",
      "division": "U14 Sat Spring Premier Division",
      "home_away": "home",
      "opponent": "Basford United Ambers U14"
    },
    {
      "id": "d6c07b4dc79c8e62ae58cb7f98c99af9",
      "date": "2026-03-28",
      "time": "10:00",
      "home_team": "Marlborough Rovers U14",
      "away_team": "Heanor Juniors Badgers U14",
      "venue": "Measham Road Recreation Ground DE12 6AA",
      "division": "U14 Sat Spring Premier Division",
      "home_away": "away",
      "opponent": "Marlborough Rovers U14"
    },
    {
      "id": "94b3fa5dea6a4a414af5e126ece2cfb5",
      "date": "2026-04-18",
      "time": "10:00",
      "home_team": "Sporting Markfield U14",
      "away_team": "Heanor Juniors Badgers U14",
      "venue": "Jubilee Playing Fields  LE67 9PX",
      "division": "U14 Sat Spring Premier Division",
      "home_away": "away",
      "opponent": "Sporting Markfield U14"
    },
    {
      "id": "78bd2f434c812f9eb9928c7acb186319",
      "date": "2026-04-25",
      "time": "11:00",
      "home_team": "Heanor Juniors Badgers U14",
      "away_team": "Bestwood Colliery U14",
      "venue": "Kilburn Welfare Social Club DE56 0NR",
      "division": "U14 Sat Spring Premier Division",
      "home_away": "home",
      "opponent": "Bestwood Colliery U14"
    }
  ]
}