{
  "team": "Nottingham FC Emeralds U11",
  "league": "YEL East Midlands Saturday 25/26",
  "generated": "2026-04-17T07:18:48Z",
  "fixtures": [
    {
      "id": "b732e808d61a54abaf897a8329d97d2a",
      "date": "2026-04-18",
      "time": "10:00",
      "home_team": "Shirebrook Rangers U11",
      "away_team": "Nottingham FC Emeralds U11",
      "venue": "Shirebrook Academy  NG20 8QF",
      "division": "U11 Sat YEL Inter Cup",
      "home_away": "away",
      "opponent": "Shirebrook Rangers U11"
    },
    {
      "id": "a36ba92de9e73361777f6964e04739ae",
      "date": "2026-04-21",
      "time": "18:00",
      "home_team": "Long Eaton United Purple U11",
      "away_team": "Nottingham FC Emeralds U11",
      "venue": "Grange Park NG10 2EF",
      "division": "U11 Sat Spring Div 5 Blue",
      "home_away": "away",
      "opponent": "Long Eaton United Purple U11"
    },
    {
      "id": "15222fad3bebb2051b73232a2725fde4",
      "date": "2026-04-25",
      "time": "11:00",
      "home_team": "Nottingham FC Emeralds U11",
      "away_team": "Shirebrook Rangers U11",
      "venue": "Melbourne Park NG8 5HL",
      "division": "U11 Saturday",
      "home_away": "home",
      "opponent": "Shirebrook Rangers U11"
    }
  ],
  "results": [
    {
      "id": "57e6ebd8805e257ab246ec96f3d8931d",
      "date": "2026-04-14",
      "time": "18:30",
      "home_team": "Nottingham FC Emeralds U11",
      "away_team": "Wollaton H & B Dragons U11",
      "home_score": 3,
      "away_score": 4,
      "venue": "",
      "division": "U11 Sat Spring Div 5 Blue",
      "home_away": "home",
      "opponent": "Wollaton H & B Dragons U11",
      "goals_for": 3,
      "goals_against": 4
    },
    {
      "id": "c9f928b6dc64919dc5bd2e63d57e97da",
      "date": "2026-04-11",
      "time": "11:00",
      "home_team": "Nottingham FC Emeralds U11",
      "away_team": "Sherwood FC Red U11",
      "home_score": 2,
      "away_score": 3,
      "venue": "",
      "division": "U11 Sat Spring Div 5 Blue",
      "home_away": "home",
      "opponent": "Sherwood FC Red U11",
      "goals_for": 2,
      "goals_against": 3
    },
    {
      "id": "e6aa8687eb9ae8d06daea7c6d0e0f1a1",
      "date": "2026-03-21",
      "time": "10:30",
      "home_team": "Hucknall Sports Blue U11",
      "away_team": "Nottingham FC Emeralds U11",
      "home_score": 1,
      "away_score": 3,
      "venue": "",
      "division": "U11 Sat YEL Inter Cup",
      "home_away": "away",
      "opponent": "Hucknall Sports Blue U11",
      "goals_for": 3,
      "goals_against": 1
    },
    {
      "id": "5e68f07986d4e4ce5aab681ae9ffef1d",
      "date": "2026-03-14",
      "time": "10:00",
      "home_team": "Nottingham FC Emeralds U11",
      "away_team": "PMG Engage U11",
      "home_score": 1,
      "away_score": 4,
      "venue": "",
      "division": "U11 Sat Spring Div 5 Blue",
      "home_away": "home",
      "opponent": "PMG Engage U11",
      "goals_for": 1,
      "goals_against": 4
    },
    {
      "id": "23c409b792263c66890f13974f811a31",
      "date": "2026-03-07",
      "time": "10:00",
      "home_team": "Dunkirk U11",
      "away_team": "Nottingham FC Emeralds U11",
      "home_score": 3,
      "away_score": 4,
      "venue": "",
      "division": "U11 Sat Spring Div 5 Blue",
      "home_away": "away",
      "opponent": "Dunkirk U11",
      "goals_for": 4,
      "goals_against": 3
    },
    {
      "id": "eeff8c9904ded85e2ca7d20b278d3840",
      "date": "2026-01-31",
      "time": "10:00",
      "home_team": "Toton Tigers U11",
      "away_team": "Nottingham FC Emeralds U11",
      "home_score": 1,
      "away_score": 3,
      "venue": "",
      "division": "U11 Sat Spring Div 5 Blue",
      "home_away": "away",
      "opponent": "Toton Tigers U11",
      "goals_for": 3,
      "goals_against": 1
    },
    {
      "id": "d903febb79c9ae41a58f08dcd476d5d3",
      "date": "2026-01-24",
      "time": "11:00",
      "home_team": "Toton Tigers U11",
      "away_team": "Nottingham FC Emeralds U11",
      "home_score": 1,
      "away_score": 5,
      "venue": "",
      "division": "U11 Sat YEL Inter Cup",
      "home_away": "away",
      "opponent": "Toton Tigers U11",
      "goals_for": 5,
      "goals_against": 1
    },
    {
      "id": "58330ffa6713d012ea651bb0caab96bd",
      "date": "2026-01-17",
      "time": "10:00",
      "home_team": "Stanton Ilkeston Galacticos U11",
      "away_team": "Nottingham FC Emeralds U11",
      "home_score": 2,
      "away_score": 2,
      "venue": "",
      "division": "U11 Sat Spring Div 5 Blue",
      "home_away": "away",
      "opponent": "Stanton Ilkeston Galacticos U11",
      "goals_for": 2,
      "goals_against": 2
    },
    {
      "id": "74db4c50a43c8ef3c6135265ebd7acdc",
      "date": "2025-12-13",
      "time": "11:00",
      "home_team": "Ravenshead FC U11",
      "away_team": "Nottingham FC Emeralds U11",
      "home_score": 7,
      "away_score": 2,
      "venue": "",
      "division": "U11 Sat Winter Div 4 Red",
      "home_away": "away",
      "opponent": "Ravenshead FC U11",
      "goals_for": 2,
      "goals_against": 7
    },
    {
      "id": "e51725af574727b118a9fda553040496",
      "date": "2025-11-22",
      "time": "10:00",
      "home_team": "Bestwood Colliery U11",
      "away_team": "Nottingham FC Emeralds U11",
      "home_score": 0,
      "away_score": 5,
      "venue": "",
      "division": "U11 Sat Winter Div 4 Red",
      "home_away": "away",
      "opponent": "Bestwood Colliery U11",
      "goals_for": 5,
      "goals_against": 0
    },
    {
      "id": "5b22ab1cbdd6367ed7f44a351c1cbda3",
      "date": "2025-11-08",
      "time": "11:00",
      "home_team": "Nottingham FC Emeralds U11",
      "away_team": "Shirebrook Rangers U11",
      "home_score": 1,
      "away_score": 2,
      "venue": "",
      "division": "U11 Sat Winter Div 4 Red",
      "home_away": "home",
      "opponent": "Shirebrook Rangers U11",
      "goals_for": 1,
      "goals_against": 2
    },
    {
      "id": "b1f3a77163260200b961585a8adab892",
      "date": "2025-10-11",
      "time": "10:00",
      "home_team": "Meden Vale Colts Green U11",
      "away_team": "Nottingham FC Emeralds U11",
      "home_score": 3,
      "away_score": 2,
      "venue": "",
      "division": "U11 Sat Winter Div 4 Red",
      "home_away": "away",
      "opponent": "Meden Vale Colts Green U11",
      "goals_for": 2,
      "goals_against": 3
    },
    {
      "id": "6cf00c58dec970d47c1ef459571a109b",
      "date": "2025-09-27",
      "time": "10:00",
      "home_team": "Arnold Town Yellow U11",
      "away_team": "Nottingham FC Emeralds U11",
      "home_score": 3,
      "away_score": 1,
      "venue": "",
      "division": "U11 Sat Winter Div 4 Red",
      "home_away": "away",
      "opponent": "Arnold Town Yellow U11",
      "goals_for": 1,
      "goals_against": 3
    },
    {
      "id": "3a1672a961f61ae68edb655517635238",
      "date": "2025-09-13",
      "time": "11:00",
      "home_team": "Nottingham FC Emeralds U11",
      "away_team": "Clay Cross Town Bulldogs U11",
      "home_score": 2,
      "away_score": 8,
      "venue": "",
      "division": "U11 Sat Winter Div 4 Red",
      "home_away": "home",
      "opponent": "Clay Cross Town Bulldogs U11",
      "goals_for": 2,
      "goals_against": 8
    },
    {
      "id": "ce91ac840e93b62cc2d6fde44ec79c17",
      "date": "2025-09-06",
      "time": "10:00",
      "home_team": "Shirebrook Rangers U11",
      "away_team": "Nottingham FC Emeralds U11",
      "home_score": null,
      "away_score": null,
      "venue": "",
      "division": "U11 Saturday",
      "home_away": "away",
      "opponent": "Shirebrook Rangers U11",
      "goals_for": null,
      "goals_against": null
    }
  ]
}